Workbook

Sheet OfertaPlazas
A1: Columna1 | B1: UNIVERSIDAD | C1: UNIVERSIDAD (denominación en MoveOn) | D1: CIUDAD | E1: CÓDIGO ERASMUS | F1: PAÍS | G1: Universidades con DT (duración DT) | H1: Deadline 1 FALL SEMESTER | I1: Deadline 1S NOMINACIÓN (OI) | J1: Deadline 1S APLICACIÓN (alumno) | K1: Deadline 2 SPRING SEMESTER | L1: Deadline 2S NOMINACIÓN (OI) | M1: Deadline 2S APLICACIÓN (alumno) | N1: PROGRAMA | O1: Code SECD: 713-Electrical Engineering (Electricity and Energy) | P1: Code SECD: 714-Electrical Engineering (Electronics and Automation) | Q1: Code SECD: 061-Computer Science (Information and Communication Technologies) | R1: Code SECD: 914-Biomedical Engineering (Medical Diagnostic and Treatment Technology) | S1: Area de Estudios | T1: Posibilidad de beca? | U1: PLAZAS | V1: MES | W1: E-mail contacto | X1: Persona de contacto | Y1: GRADOS | Z1: GITST | AA1: GIB | AB1: GISD | AC1: MASTER | AD1: TITULACIÓN | AE1: S5 | AF1: S6 | AG1: C3 | AH1: S7 | AI1: S8 | AJ1: S7+T | AK1: S8+T | AL1: C4º | AM1: C4º+T | AN1: T | AO1: MS2ºAÑO (UN SEMESTRE) | AP1: MS2ºAÑO+TFM | AQ1: TFM | AR1: DT(MASTER) | AS1: CERT | AT1: OBSERVACIONES IDIOMAS | AU1: OBSERVACIONES | AV1: OBSERVACIONES2 | AW1: ToR verificable | AX1: GICO_CODE | AY1: Acuerdo desde la Universidad de origen | AZ1: Areas de estudios | BA1: Departamento Uni de destino | BB1: Contact | BC1: Acuerdo desde la ETSIT-UPM | BD1: Observaciones3 | BE1: OBSERVACIONES (archivo Teams) | BF1: Universidades que contestaron la encuesta | BG1: UNIVERSIDADES QUE NO ESTÁN EN TEAMS
A2: 1 | B2: Technische Universität Graz | C2: Technische Universität Graz | D2: Graz | E2: A GRAZ02 | F2: AT | H2: 10 de abril (nomination) -17 de abril (application) | I2: 04.10 | J2: 04.17 | K2: 16 de octubre (nomination) - 1 de noviembre (application) | L2: 10.16 | M2: 11.01 | N2: ER | Q2: SÍ | R2: SÍ | S2: Computer Science (Information and CommunicationTechnologies) / Biomedical Engineering (Medical Diagnostic and Treatment Technology) | T2: Sí | U2: 3 | V2: 10 | W2: erasmus.incoming@tugraz.at | X2: Kerry John (she/her) | Y2: SI | Z2: SI | AA2: SI | AB2: SI | AC2: SI | AD2: =_xlfn.TEXTJOIN("/",TRUE,IF(OfertaPlazas[[#This Row],[GITST]]="SI","GITST",""),IF(OfertaPlazas[[#This Row],[GIB]]="SI","GIB",""),IF(OfertaPlazas[[#This Row],[GISD]]="SI","GISD",""),IF(OfertaPlazas[[#This Row],[MASTER]]="SI","MASTER","")) -> GITST/GIB/GISD/MASTER | AE2: SI | AF2: SI | AG2: SI | AH2: SI | AI2: SI | AJ2: SI | AK2: SI | AL2: SI | AM2: SI | AN2: SI | AO2: SI | AP2: SI | AQ2: SI | AR2: NO | AS2: ALEMÁN B2 o INGLÉS B2 | AT2: INGLÉS B2 (TOEFL 75, IELTS 6.0, TOEIC (785 listening and reading - 310 speaking and writing), Cambridge ESOL First Certificate in English (FCE) OR Certificate in Advanced English (CAE) OR Certificate of Proficiency in English (CPE) or Certificate issued by the language centre of a University | AU2: Sólo se puede hacerse el TFG/TFM si un profesor acepta al alumno. El área de estudios para alumnos de GITST y MUIT es computer science. | AV2: se puede desdoblar nº de meses | AW2: ToR verificable | AX2: ToR verificable | AY2: Departamental | AZ2: Computer Science y Biomedical Engineering | BA2: Computer Science | BC2: ETSIT | BE2: =VLOOKUP(B2,'TEAMS_30-09-2021'!$D:$AG,30,FALSE) -> 0 | BF2: =VLOOKUP(B2,'ENCUESTAS JUN-2021'!I:I,1,FALSE) -> #N/A | BG2: =VLOOKUP(B2,'TEAMS_30-09-2021'!D:D,1,FALSE) -> Technische Universität Graz
A3: 2 | B3: FH Joanneum | C3: FH JOANNEUM - University of Applied Sciences | D3: Graz | E3: A GRAZ09 | F3: AT | H3: 1 de junio (nomination) 15 de junio (application) | I3: 06.01 | J3: 06.15 | K3: 1 de noviembre (nomination) - 15 de noviembre (application) | L3: 11.01 | M3: 11.15 | N3: ER | P3: SÍ | S3: Electrical Engineering (Electronics and Automation) | T3: Sí | U3: 2 | V3: 10 | W3: international@fh-joanneum.at; incoming-students@fh-joanneum.at | X3: Regina Käfer-Goiginger | Y3: SI | Z3: SI | AA3: NO | AB3: NO | AC3: SI | AD3: =_xlfn.TEXTJOIN("/",TRUE,IF(OfertaPlazas[[#This Row],[GITST]]="SI","GITST",""),IF(OfertaPlazas[[#This Row],[GIB]]="SI","GIB",""),IF(OfertaPlazas[[#This Row],[GISD]]="SI","GISD",""),IF(OfertaPlazas[[#This Row],[MASTER]]="SI","MASTER","")) -> GITST/MASTER | AE3: SI | AF3: SI | AG3: SI | AH3: SI | AI3: SI | AJ3: SI | AK3: SI | AL3: SI | AM3: SI | AN3: SI | AO3: SI | AP3: SI | AQ3: SI | AR3: NO | AS3: ALEMÁN B2 o INGLÉS B2 | AU3: https://www.fh-joanneum.at/en/international/study-programmes/international-programme-kapfenberg/ https://www.fh-joanneum.at/en/international/study-programmes/ | AV3: se puede desdoblar nº de meses / se quita el área de bio mayo 2026
A4: 3 | B4: MCI | THE ENTREPRENEURIAL SCHOOL | C4: MCI - Management Center Innsbruck | D4: Innsbruck | E4: A INNSBRU08 | F4: AT | H4: 1 de abril (nomination) 1 de mayo (application) | I4: 04.01 | J4: 05.01 | K4: 1 de octubre (nomination) - 1 de noviembre (application) | L4: 10.01 | M4: 11.01 | N4: ER | P4: SÍ | Q4: SÍ | R4: SÍ | S4: Electrical Engineering (Electronics and Automation) / Biomedical Engineering (Medical Diagnosticand Treatment Technology) /Computer Science (Information and CommunicationTechnologies) | T4: Sí | U4: 2 | V4: 10 | W4: Daniel.Dassisi@mci.edu; incoming@mci.edu | X4: Daniel D'Assissi | Y4: SI | Z4: SI | AA4: SI | AB4: SI | AC4: SI | AD4: =_xlfn.TEXTJOIN("/",TRUE,IF(OfertaPlazas[[#This Row],[GITST]]="SI","GITST",""),IF(OfertaPlazas[[#This Row],[GIB]]="SI","GIB",""),IF(OfertaPlazas[[#This Row],[GISD]]="SI","GISD",""),IF(OfertaPlazas[[#This Row],[MASTER]]="SI","MASTER","")) -> GITST/GIB/GISD/MASTER | AE4: SI | AF4: NO | AG4: NO | AH4: SI | AI4: NO | AJ4: SI | AK4: NO | AL4: NO | AM4: NO | AN4: SI | AO4: SI | AP4: SI | AQ4: SI | AR4: NO | AS4: INGLÉS B2 o INGLÉS C1 o ALEMÁN B1 | AT4: GRADO:INGLÉS B2 (TOEFL iBT ≥ 75 o TOEFL pBT ≥ 540 o IELTS Academic ≥ 5.5 o PTE Academic ≥ 50 o Cambridge English BEC Vantage ≥ 160 o CAE ≥ 160 o Oxford Test of English ≥ 111 en todas las destrezas o LanguageCert Academic ≥ 60) MÁSTER:INGLÉS C1 (TOEFL iBT ≥ 85 o TOEFL pBT ≥ 560 o IELTS Academic ≥ 6.5 o PTE Academic ≥ 65 o Cambridge English BEC Higher ≥ 180 o CAE ≥ 180 o Cambridge English Proficiency (CPE) ≥ 200 o Oxford Test of English ≥ 120 en todas las destrezas o LanguageCert Academic ≥ 75) o ALEMÁN B1 (www.mci.edu/exchange-incoming) | AU4: On undergraduate level, the courses are only offered in the fall semester // No permiten coger asignaturas de varios materes por tema de solapamiento de horarios | AV4: Acuerdo firmado en septiembre 2022 - se puede desdoblar nº de meses
A5: 4 | B5: Technische Universität Wien | C5: Technische Universität Wien | D5: Viena | E5: A WIEN02 | F5: AT | H5: 31 de mayo (nomination) -30 junio (application) | I5: 05.31 | J5: 06.30 | K5: 15 de diciembre (nomination)- 31 de diciembre (application) | L5: 12.15 | M5: 12.31 | N5: ER | P5: SÍ | R5: SÍ | S5: Electrical Engineering (Electronics and Automation) / Biomedical Engineering (Medical Diagnosticand Treatment Technology) | T5: Sí | U5: 4 | V5: 10 | W5: exchangein@tuwien.ac.at | X5: international office | Y5: SI | Z5: SI | AA5: NO | AB5: NO | AC5: SI | AD5: =_xlfn.TEXTJOIN("/",TRUE,IF(OfertaPlazas[[#This Row],[GITST]]="SI","GITST",""),IF(OfertaPlazas[[#This Row],[GIB]]="SI","GIB",""),IF(OfertaPlazas[[#This Row],[GISD]]="SI","GISD",""),IF(OfertaPlazas[[#This Row],[MASTER]]="SI","MASTER","")) -> GITST/MASTER | AE5: SI | AF5: SI | AG5: SI | AH5: SI | AI5: SI | AJ5: SI | AK5: SI | AL5: SI | AM5: SI | AN5: SI | AO5: SI | AP5: SI | AQ5: SI | AR5: NO | AS5: ALEMÁN B1 o ALEMÁN A2 o INGLÉS B1 | AT5: Junto con curso intentivo de alemán.Se acepta el certificado del departamento de lingüística | AU5: En la solicitud online hay que registrarse como Master students. Asignaturas en INGLÉS sólo a nivel MASTER. Para poder realizar el TFM ponen como condición necesaria el tener un tutor y un tema para el TFM prevío a la llegada, dan una oferta de TFMs y hay que coger uno o renunciar a hacer el TFM. Se puede coger algunas asignaturas de la Faculty of informatics | AV5: se puede desdoblar nº de meses | AY5: Institucional | AZ5: Electrical Engineering | BC5: UPM (varias Escuelas) | BD5: se añade el área de bio | BE5: =VLOOKUP(B5,'TEAMS_30-09-2021'!$D:$AG,30,FALSE) -> se añade el área de bio acordado con TU Wien | BF5: =VLOOKUP(B5,'ENCUESTAS JUN-2021'!I:I,1,FALSE) -> #N/A | BG5: =VLOOKUP(B5,'TEAMS_30-09-2021'!D:D,1,FALSE) -> Technische Universität Wien
A6: 5 | B6: Université Libre de Bruxelles ULB - Ecole Polytechnique de Bruxelles | C6: Université Libre de Bruxelles | D6: Bruselas | E6: B BRUXEL04 | F6: BE | H6: 15 de mayo (nomination) 1 de junio (application) | I6: 05.15 | J6: 06.01 | K6: 15 de octubre (nomination) - 30 de octubre (application) | L6: 10.15 | M6: 10.30 | N6: ER | P6: SÍ | R6: SÍ | S6: Electrical Engineering (Electronics and Automation) / Biomedical Engineering (Medical Diagnosticand Treatment Technology) | T6: Sí | U6: 2 | V6: 12 | W6: mobilite@ulb.be; international.polytech@ulb.be; alice.hoslet@ulb.be | X6: Hoslet Alice; Rose-Marie Brynaert (EPB) | Y6: SI | Z6: SI | AA6: SI | AB6: NO | AC6: SI | AD6: =_xlfn.TEXTJOIN("/",TRUE,IF(OfertaPlazas[[#This Row],[GITST]]="SI","GITST",""),IF(OfertaPlazas[[#This Row],[GIB]]="SI","GIB",""),IF(OfertaPlazas[[#This Row],[GISD]]="SI","GISD",""),IF(OfertaPlazas[[#This Row],[MASTER]]="SI","MASTER","")) -> GITST/GIB/MASTER | AE6: SI | AF6: SI | AG6: SI | AH6: SI | AI6: SI | AJ6: SI | AK6: SI | AL6: SI | AM6: SI | AN6: NO | AO6: SI | AP6: SI | AQ6: SI | AR6: NO | AS6: FRANCÉS B1 o INGLÉS B1 | AU6: Sólo se puede hacer TFG con asignaturas que incluyan un proyecto. Se requiere cursar 15ECTS de asignaturas (a parte del TFG). ENG para el Master en ingeniería eléctrica. Se debe encontrar un "Promoter" para realizar el research project (TFM) antes del 1 de junio. | AV6: se puede desdoblar nº de meses | AY6: Institucional | AZ6: Electrical Engineering | BC6: UPM (varias Escuelas) | BD6: OJO: hay que añadir biomedical engineering en la renovación. Ya acordada | BE6: =VLOOKUP(B6,'TEAMS_30-09-2021'!$D:$AG,30,FALSE) -> #N/A | BF6: =VLOOKUP(B6,'ENCUESTAS JUN-2021'!I:I,1,FALSE) -> #N/A | BG6: =VLOOKUP(B6,'TEAMS_30-09-2021'!D:D,1,FALSE) -> #N/A | BL6: =VLOOKUP(E6,#REF!,1,FALSE) -> #REF!
A7: 6 | B7: Universiteit Gent | C7: Universiteit Gent | D7: Gent | E7: B GENT01 | F7: BE | H7: 15 de abril (nomination) 15 de mayo (application) | I7: 04.15 | J7: 05.15 | K7: 15 octubre(nomination) - 15 de noviembre(application) | L7: 10.15 | M7: 11.15 | N7: ER | P7: SÍ | R7: SÍ | S7: Electrical Engineering (Electronics and Automation) / Biomedical Engineering (Medical Diagnosticand Treatment Technology) | T7: Sí | U7: 4 | V7: 12 | W7: international.ea@ugent.be; outgoing.students@ugent.be; internationalsupport@ugent.be | X7: Ann Vanoutryve | Y7: SI | Z7: SI | AA7: SI | AB7: NO | AC7: SI | AD7: =_xlfn.TEXTJOIN("/",TRUE,IF(OfertaPlazas[[#This Row],[GITST]]="SI","GITST",""),IF(OfertaPlazas[[#This Row],[GIB]]="SI","GIB",""),IF(OfertaPlazas[[#This Row],[GISD]]="SI","GISD",""),IF(OfertaPlazas[[#This Row],[MASTER]]="SI","MASTER","")) -> GITST/GIB/MASTER | AE7: SI | AF7: SI | AG7: SI | AH7: SI | AI7: SI | AJ7: SI | AK7: SI | AL7: SI | AM7: SI | AN7: SI | AO7: SI | AP7: SI | AQ7: SI | AR7: NO | AS7: INGLÉS B2 o HOLANDÉS B2 | AT7: INGLÉS B2: TOEFL min 87 o IELTS 6,0 (min 6,0 in writing) o TOEIC min 785 o FCE, CAE, CPE o University language Center certifying a level B2 o HOLANDES B2 (proof that the student finished successfully a Dutch study programme of at least 1 year) | AU7: 2 plazas para Biomedical Engineering y 2 plazas para Electrical Engineering (se puede nominar solamente en un área) | AV7: La solicitud de alojamiento abre a ppio de abril así que es mejor hacer la e-nomination pronto aunque el deadline es 15/05 Se puede pasar alumnos del área de teleco al área de bio sin pasarse del número total de alumnos | AW7: No envían ToR en papel y su ToR no es verificable. Aceptamos el ToR si lo envía Ugent | AX7: GENT-2 | AY7: Departamental | AZ7: Electrical Engineering y Biomedical Engineering | BA7: Electrical Engineering y Biomedical Engineering | BC7: ETSIT | BE7: =VLOOKUP(B7,'TEAMS_30-09-2021'!$D:$AG,30,FALSE) -> 0 | BF7: =VLOOKUP(B7,'ENCUESTAS JUN-2021'!I:I,1,FALSE) -> Universiteit Gent | BG7: =VLOOKUP(B7,'TEAMS_30-09-2021'!D:D,1,FALSE) -> Universiteit Gent | BL7: =VLOOKUP(E7,#REF!,1,FALSE) -> #REF!
A8: 7 | B8: Katholike Universiteit Leuven | C8: KU Leuven | D8: Leuven | E8: B LEUVEN01 | F8: BE | H8: 30 de abril | I8: 04.15 | J8: 04.30 | K8: 1 de octubre | L8: 10.01 | N8: ER | P8: SÍ | R8: SÍ | S8: Electrical Engineering (Electronics and Automation) / Biomedical Engineering (Medical Diagnosticand Treatment Technology) | T8: Sí | U8: 2 | V8: 12 | W8: viktoriia.pukhyr@kuleuven.be | X8: Viktoriia Pukhyr | Y8: SI | Z8: SI | AA8: SI | AB8: NO | AC8: SI | AD8: =_xlfn.TEXTJOIN("/",TRUE,IF(OfertaPlazas[[#This Row],[GITST]]="SI","GITST",""),IF(OfertaPlazas[[#This Row],[GIB]]="SI","GIB",""),IF(OfertaPlazas[[#This Row],[GISD]]="SI","GISD",""),IF(OfertaPlazas[[#This Row],[MASTER]]="SI","MASTER","")) -> GITST/GIB/MASTER | AE8: NO | AF8: NO | AG8: NO | AH8: SI | AI8: SI | AJ8: SI | AK8: SI | AL8: SI | AM8: SI | AN8: SI | AO8: SI | AP8: SI | AQ8: SI | AR8: NO | AS8: INGLÉS B2 | AU8: courses available to exchange students can be found here: https://onderwijsaanbod.kuleuven.be/opleidingen/e/SC_51977178.htm#&bl=all OJO: solo se puede coger 2 asignaturas máximo en la facultad de business | AV8: Se puede dividir el número de meses / pasamos de 3*12 a 2*10 en 2022 / Movilidad a partir de 4º curso / se pide aumentar de 2 a 3 alumnos Indeed, we form agreements mentioning specific study fields (as you mentioned for example Electrical Engineering and Biomedical Engineering), but incoming exchange students are allowed to take courses from any of our Master's programmes at our Faculty | AW8: ToR verificable | AX8: ToR verificable | AY8: Departamental | AZ8: Electrical Engineering y Biomedical Engineering | BA8: Faculty of Engineering Science | BC8: ETSIT | BE8: =VLOOKUP(B8,'TEAMS_30-09-2021'!$D:$AG,30,FALSE) -> 0 | BF8: =VLOOKUP(B8,'ENCUESTAS JUN-2021'!I:I,1,FALSE) -> Katholike Universiteit Leuven | BG8: =VLOOKUP(B8,'TEAMS_30-09-2021'!D:D,1,FALSE) -> Katholike Universiteit Leuven | BL8: =VLOOKUP(E8,#REF!,1,FALSE) -> #REF!
A9: 8 | B9: Université de Liège | C9: Université de Liège | D9: Lieja | E9: B LIEGE01 | F9: BE | H9: 15 de mayo (nomination) - 31 de mayo (application) | I9: 05.15 | J9: 05.31 | K9: 1 de noviembre (online) - 15 de noviembre (impreso) | L9: 11.01 | M9: 11.15 | N9: ER | P9: SÍ | R9: SÍ | S9: Electrical Engineering (Electronics and Automation) / Biomedical Engineering (Medical Diagnosticand Treatment Technology) | T9: Sí | U9: 2 | V9: 12 | W9: mobil.in@uliege.be; marta.kucharska@uliege.be | X9: Marta KUCHARSKA | Y9: SI | Z9: SI | AA9: SI | AB9: NO | AC9: SI | AD9: =_xlfn.TEXTJOIN("/",TRUE,IF(OfertaPlazas[[#This Row],[GITST]]="SI","GITST",""),IF(OfertaPlazas[[#This Row],[GIB]]="SI","GIB",""),IF(OfertaPlazas[[#This Row],[GISD]]="SI","GISD",""),IF(OfertaPlazas[[#This Row],[MASTER]]="SI","MASTER","")) -> GITST/GIB/MASTER | AE9: SI | AF9: SI | AG9: SI | AH9: SI | AI9: SI | AJ9: SI | AK9: SI | AL9: SI | AM9: SI | AN9: SI | AO9: SI | AP9: SI | AQ9: SI | AR9: NO | AS9: FRANCÉS B1 o INGLÉS B2 | AY9: Institucional | AZ9: Electrical Engineering y Biomedical Engineering | BC9: ETSIT | BE9: =VLOOKUP(B9,'TEAMS_30-09-2021'!$D:$AG,30,FALSE) -> 0 | BF9: =VLOOKUP(B9,'ENCUESTAS JUN-2021'!I:I,1,FALSE) -> Université de Liège | BG9: =VLOOKUP(B9,'TEAMS_30-09-2021'!D:D,1,FALSE) -> Université de Liège | BL9: =VLOOKUP(E9,#REF!,1,FALSE) -> #REF!
A10: 9 | B10: Université Catholique de Louvain - EPL | C10: Université Catholique de Louvain | D10: Louvain-la-Neuve | E10: B LOUVAIN01 | F10: BE | H10: 1 de abril (nomination) - 15 de abril (application) | I10: 04.01 | J10: 04.15 | K10: 30 septiembre (nomination) - 31 octubre (application) | L10: 09.30 | M10: 10.31 | N10: ER | P10: SÍ | S10: Electrical Engineering (Electronics and Automation) | T10: Sí | U10: 2 | V10: 12 | W10: emmanuelle.brun@uclouvain.be | X10: Emmanuelle Brun | Y10: SI | Z10: SI | AA10: NO | AB10: NO | AC10: SI | AD10: =_xlfn.TEXTJOIN("/",TRUE,IF(OfertaPlazas[[#This Row],[GITST]]="SI","GITST",""),IF(OfertaPlazas[[#This Row],[GIB]]="SI","GIB",""),IF(OfertaPlazas[[#This Row],[GISD]]="SI","GISD",""),IF(OfertaPlazas[[#This Row],[MASTER]]="SI","MASTER","")) -> GITST/MASTER | AE10: SI | AF10: SI | AG10: SI | AH10: SI | AI10: SI | AJ10: NO | AK10: NO | AL10: SI | AM10: NO | AN10: NO | AO10: SI | AP10: SI | AQ10: SI | AR10: NO | AS10: FRANCÉS B2 o INGLÉS B2 | AT10: FRANCÉS B2 (DELF - DALF) o INGLÉS B2 (TOEFL - IEALTS - CAP - CPE o statement of English language teacher) | AU10: El acuerdo es con EPL (École Polytechnique de Louvain). Bachelor en francés. Máster en inglés. | AY10: Institucional | AZ10: Electronics Engineering | BC10: UPM (varias Escuelas) | BE10: =VLOOKUP(B10,'TEAMS_30-09-2021'!$D:$AG,30,FALSE) -> 0 | BF10: =VLOOKUP(B10,'ENCUESTAS JUN-2021'!I:I,1,FALSE) -> #N/A | BG10: =VLOOKUP(B10,'TEAMS_30-09-2021'!D:D,1,FALSE) -> Université Catholique de Louvain - EPL
A11: 10 | B11: Angel Kanchev University of Ruse | C11: Rusenski Universitet Angel Kunchev | D11: Ruse | E11: BG ROUSSE01 | F11: BG | H11: 30 de junio (application) | I11: 06.30 | J11: 06.30 | K11: 30 de noviembre (application) | L11: 11.30 | M11: 11.30 | N11: ER | P11: SÍ | S11: Electrical Engineering (Electronics and Automation) | T11: Sí | U11: 1 | V11: 12 | W11: tiliev@uni-ruse.bg | X11: Teodor Iliev | Y11: SI | Z11: SI | AA11: NO | AB11: NO | AC11: SI | AD11: =_xlfn.TEXTJOIN("/",TRUE,IF(OfertaPlazas[[#This Row],[GITST]]="SI","GITST",""),IF(OfertaPlazas[[#This Row],[GIB]]="SI","GIB",""),IF(OfertaPlazas[[#This Row],[GISD]]="SI","GISD",""),IF(OfertaPlazas[[#This Row],[MASTER]]="SI","MASTER","")) -> GITST/MASTER | AE11: SI | AF11: SI | AG11: SI | AH11: SI | AI11: SI | AJ11: SI | AK11: SI | AL11: NO | AM11: NO | AN11: SI | AO11: SI | AP11: NO | AQ11: SI | AR11: NO | AS11: INGLÉS B1 | AU11: Posibilidad de cursar asignaturas del Bachelor degree: Information and Communication Technology en inglés | AV11: se puede desdoblar nº de meses | AY11: Departamental | AZ11: Electrical Engineering | BA11: Telecommuncations Department | BC11: ETSIT | BE11: =VLOOKUP(B11,'TEAMS_30-09-2021'!$D:$AG,30,FALSE) -> 0 | BF11: =VLOOKUP(B11,'ENCUESTAS JUN-2021'!I:I,1,FALSE) -> #N/A | BG11: =VLOOKUP(B11,'TEAMS_30-09-2021'!D:D,1,FALSE) -> Angel Kanchev University of Ruse | BL11: =VLOOKUP(E11,#REF!,1,FALSE) -> #REF!
A12: 11 | B12: Technical University of Sofia | C12: Tehnicheski Universitet Sofia | D12: Sofia | E12: BG SOFIA16 | F12: BG | H12: 15 de junio | I12: 06.15 | J12: 06.15 | K12: 15 de noviembre | L12: 11.15 | N12: ER | P12: SÍ | S12: Electrical Engineering (Electronics and Automation) | T12: Sí | U12: 2 | V12: 12 | W12: vkp@tu-sofia.bg | X12: Vladimir Poulkov | Y12: SI | Z12: SI | AA12: NO | AB12: NO | AC12: SI | AD12: =_xlfn.TEXTJOIN("/",TRUE,IF(OfertaPlazas[[#This Row],[GITST]]="SI","GITST",""),IF(OfertaPlazas[[#This Row],[GIB]]="SI","GIB",""),IF(OfertaPlazas[[#This Row],[GISD]]="SI","GISD",""),IF(OfertaPlazas[[#This Row],[MASTER]]="SI","MASTER","")) -> GITST/MASTER | AE12: SI | AF12: SI | AG12: SI | AH12: SI | AI12: SI | AJ12: SI | AK12: SI | AL12: SI | AM12: SI | AN12: SI | AO12: SI | AP12: SI | AQ12: SI | AR12: NO | AS12: INGLÉS B1 | AV12: se puede desdoblar nº de meses | AY12: Departamental | AZ12: Electrical Engineering | BA12: Faculty of Telecommunications | BC12: ETSIT | BE12: =VLOOKUP(B12,'TEAMS_30-09-2021'!$D:$AG,30,FALSE) -> 0 | BF12: =VLOOKUP(B12,'ENCUESTAS JUN-2021'!I:I,1,FALSE) -> #N/A | BG12: =VLOOKUP(B12,'TEAMS_30-09-2021'!D:D,1,FALSE) -> Technical University of Sofia | BL12: =VLOOKUP(E12,#REF!,1,FALSE) -> #REF!
A13: 12 | B13: HES-SO Haute École Spécialisée de Suisse Occidentale - hepia | C13: HES-SO Haute École Spécialisée de Suisse Occidentale | D13: Ginebra | E13: CH DELEMONT03 | F13: CH | H13: 31 de marzo | I13: 03.31 | J13: 03.31 | L13: 03.31 | N13: AB | P13: SÍ | Q13: SÍ | S13: Electrical Engineering (Electronics and Automation) / Computer Science (Information and CommunicationTechnologies) | T13: Sí (beca gobierno Suizo) | U13: 6 | V13: 6 | W13: ri.hepia@hesge.ch; | X13: international office | Y13: SI | Z13: SI | AA13: NO | AB13: SI | AC13: SI | AD13: =_xlfn.TEXTJOIN("/",TRUE,IF(OfertaPlazas[[#This Row],[GITST]]="SI","GITST",""),IF(OfertaPlazas[[#This Row],[GIB]]="SI","GIB",""),IF(OfertaPlazas[[#This Row],[GISD]]="SI","GISD",""),IF(OfertaPlazas[[#This Row],[MASTER]]="SI","MASTER","")) -> GITST/GISD/MASTER | AE13: SI | AF13: SI | AG13: SI | AH13: SI | AI13: SI | AJ13: NO | AK13: NO | AL13: SI | AM13: NO | AN13: NO | AO13: SI | AP13: NO | AQ13: NO | AR13: NO | AS13: FRANCÉS B1 | AT13: (asignaturas de grado SOLO en francés; en master algunas asignaturas en inglés) | AU13: HES-SO Campus en Lausanne y HEPIA campus en Ginebra / 3 alumnos en el área 714 Electronics Engineering Telecommunications y 3 alumnos en el área 611 Informatics, Computer Science. No se puede cursar TFT, solo asignaturas. 30 ECTS por semestre | AY13: Departamental | AZ13: Computer Science | BA13: Engineering of lnformation Technology | BB13: sac-exchange-in@epfl.ch | BC13: ETSIT | BF13: =VLOOKUP(B13,'ENCUESTAS JUN-2021'!I:I,1,FALSE) -> #N/A | BG13: [Universidad suiza, no Erasmus] | BL13: =VLOOKUP(E13,#REF!,1,FALSE) -> #REF!
A14: 13 | B14: École Polytechnique Fédérale de Lausanne - EPFL | C14: École Polytechnique Fédérale (EPF) Lausanne | D14: Lausana | E14: CH LAUSANN06 | F14: CH | H14: 15 de abril | I14: 04.15 | J14: 04.15 | K14: 15 de octubre | L14: 10.15 | N14: AB | O14: Sí | Q14: SÍ | R14: SÍ | S14: Computer Science (Information and CommunicationTechnologies) / Electrical Engineering (Electronics and Automation) / Biomedical Engineering (Medical Diagnosticand Treatment Technology) | T14: Sí (beca gobierno Suizo) | U14: 3 | V14: 10 | W14: sac-exchange-out@epfl.ch, sac-exchange-in@epfl.ch | X14: international office | Y14: SI | Z14: SI | AA14: SI | AB14: SI | AC14: SI | AD14: =_xlfn.TEXTJOIN("/",TRUE,IF(OfertaPlazas[[#This Row],[GITST]]="SI","GITST",""),IF(OfertaPlazas[[#This Row],[GIB]]="SI","GIB",""),IF(OfertaPlazas[[#This Row],[GISD]]="SI","GISD",""),IF(OfertaPlazas[[#This Row],[MASTER]]="SI","MASTER","")) -> GITST/GIB/GISD/MASTER | AE14: SI | AF14: SI | AG14: SI | AH14: SI | AI14: SI | AJ14: SI | AK14: SI | AL14: SI | AM14: SI | AN14: SI | AO14: SI | AP14: SI | AQ14: SI | AR14: NO | AS14: FRANCÉS B2 o INGLÉS B2 | AU14: Nota mínima expediente académico: 7. Bachelor en francés. Master programm en inglés y francés. El alumno debe registrar entre 20/30 créditos ECTS por semestre. Para el TFG, debe solicitar "semester Project" (programa de Máster). No se permite cursar asignaturas en el mismo semestre que se realiza el TFM. The access to courses in our College of Management of Technology (Management of Technology and Entrepreneurship, and Financial Engineering) is not open to exchange students. Asignaturas NO disponibles para alumnos de movilidad: https://www.epfl.ch/education/international/fr/venir-etudier-a-l-epfl/semestres-cours/conditions/ | AV14: se añade el área de bio empezando en 22/23 | AY14: Institucional | AZ14: Electrical Engineering, Computer Science y Biomedical Engineering | BC14: UPM (varias Escuelas) | BD14: Se añade el área biomedical engineering | BF14: =VLOOKUP(B14,'ENCUESTAS JUN-2021'!I:I,1,FALSE) -> #N/A | BG14: [Universidad suiza, no Erasmus] | BL14: =VLOOKUP(E14,#REF!,1,FALSE) -> #REF!
A15: 14 | B15: Zürcher Hochschule für Angewandte Wissenschaften ZHAW | C15: Zürcher Hochschule für Angewandte Wissenschaften | D15: Winterthur | E15: CH WINTERT03 | F15: CH | H15: 15 de marzo (nomination) - 1 de abril (application) | I15: 03.15 | J15: 04.01 | K15: 15 de octubre (nomination) - 1 de noviembre (application) | L15: 10.15 | M15: 11.01 | N15: AB | P15: SÍ | Q15: SÍ | S15: Electrical Engineering (Electronics and Automation) / Computer Science (Information and CommunicationTechnologies) | T15: Sí (beca gobierno Suizo) | U15: 2 | V15: 10 | W15: international.engineering@zhaw.ch; exchange.engineering@zhaw.ch | X15: Sabrina Meizinger | Y15: SI | Z15: SI | AA15: NO | AB15: SI | AC15: SI | AD15: =_xlfn.TEXTJOIN("/",TRUE,IF(OfertaPlazas[[#This Row],[GITST]]="SI","GITST",""),IF(OfertaPlazas[[#This Row],[GIB]]="SI","GIB",""),IF(OfertaPlazas[[#This Row],[GISD]]="SI","GISD",""),IF(OfertaPlazas[[#This Row],[MASTER]]="SI","MASTER","")) -> GITST/GISD/MASTER | AE15: SI | AF15: SI | AG15: SI | AH15: SI | AI15: SI | AJ15: SI | AK15: SI | AL15: SI | AM15: SI | AN15: SI | AO15: SI | AP15: SI | AQ15: SI | AR15: NO | AS15: ALEMÁN B2 o INGLÉS B2 o INGLÉS C1 | AT15: GRADO:ALEMÁN B2 o INGLÉS B2 (TOEFL 550/213/79 o TOEIC 700 o IELTS 6.0 o CAE) / MASTER: INGLÉS C1 forma parte de EELISA | AV15: dic 2022: se renueva el acuerdo con las mismas condiciones | AY15: Departamental | AZ15: Engineering and trade | BA15: Applied mathematics, Physics, Systems and Operations | BC15: ETSIT | BF15: =VLOOKUP(B15,'ENCUESTAS JUN-2021'!I:I,1,FALSE) -> #N/A | BG15: [Universidad suiza, no Erasmus] | BL15: =VLOOKUP(E15,#REF!,1,FALSE) -> #REF!
A16: 15 | B16: Czech Technical University CTU | C16: Ceské Vysoké Uceni Technické v Praze | D16: Prague | E16: CZ PRAHA10 | F16: CZ | H16: 15 de abril(nomination) - 30 abril (application) | I16: 04.15 | J16: 04.30 | K16: 15 noviembre (nomination ) -30 de noviembre (application) | L16: 11.15 | M16: 11.30 | N16: ER | P16: SÍ | S16: Electrical Engineering (Electronics and Automation) | T16: Sí | U16: 2 | V16: 12 | W16: Lucie.Bilova@cvut.cz | X16: Bilova, Lucie | Y16: SI | Z16: SI | AA16: NO | AB16: NO | AC16: SI | AD16: =_xlfn.TEXTJOIN("/",TRUE,IF(OfertaPlazas[[#This Row],[GITST]]="SI","GITST",""),IF(OfertaPlazas[[#This Row],[GIB]]="SI","GIB",""),IF(OfertaPlazas[[#This Row],[GISD]]="SI","GISD",""),IF(OfertaPlazas[[#This Row],[MASTER]]="SI","MASTER","")) -> GITST/MASTER | AE16: SI | AF16: SI | AG16: SI | AH16: SI | AI16: SI | AJ16: SI | AK16: SI | AL16: SI | AM16: SI | AN16: SI | AO16: SI | AP16: SI | AQ16: SI | AR16: NO | AS16: INGLÉS B2 o ALEMÁN B1 | AT16: INGLÉS B2 (se acepta el certificado del departamento de lingüística) | AU16: incoming students are required to collect at least 15 ECTS credits/semester | AV16: se puede desdoblar nº de meses | AW16: 01/03/2023 "We don't post hard copies for sure. The students are many times informed about it. In the case you really need a hard copy and the scanned one sent by the international office isn't enough, I hope the student has some friends here to pick up the hard copy in my office and send it" | AY16: Departamental | AZ16: Electrical Engineering | BA16: Faculty of Electrical Engineering | BC16: ETSIT | BE16: =VLOOKUP(B16,'TEAMS_30-09-2021'!$D:$AG,30,FALSE) -> 0 | BF16: =VLOOKUP(B16,'ENCUESTAS JUN-2021'!I:I,1,FALSE) -> #N/A | BG16: =VLOOKUP(B16,'TEAMS_30-09-2021'!D:D,1,FALSE) -> Czech Technical University CTU | BL16: =VLOOKUP(E16,#REF!,1,FALSE) -> #REF!
A17: 16 | B17: RWTH - Aachen | C17: Rheinisch-Westfälische Technische Hochschule Aachen | D17: Aachen | E17: D AACHEN01 | F17: DE | H17: 31 de marzo (nomination) - 31 de mayo (application) | I17: 03.31 | J17: 05.31 | K17: 31 de octubre (nomination)-31 de diciembre (application) | L17: 10.31 | M17: 12.31 | N17: ER | P17: SÍ | S17: Electrical Engineering (Electronics and Automation) | T17: Sí | U17: 4 | V17: 5 | W17: incomings@rwth-aachen.de | X17: International Office | Y17: SI | Z17: SI | AA17: NO | AB17: NO | AC17: SI | AD17: =_xlfn.TEXTJOIN("/",TRUE,IF(OfertaPlazas[[#This Row],[GITST]]="SI","GITST",""),IF(OfertaPlazas[[#This Row],[GIB]]="SI","GIB",""),IF(OfertaPlazas[[#This Row],[GISD]]="SI","GISD",""),IF(OfertaPlazas[[#This Row],[MASTER]]="SI","MASTER","")) -> GITST/MASTER | AE17: SI | AF17: SI | AG17: SI | AH17: SI | AI17: SI | AJ17: SI | AK17: SI | AL17: SI | AM17: SI | AN17: SI | AO17: SI | AP17: SI | AQ17: SI | AR17: NO | AS17: INGLÉS B2 o ALEMÁN B1 | AT17: INGLÉS B2 (TOEFL 90 IBT o IELTS 5.5 o CAE) y/o ALEMÁN B1 (TestDaF - Level 4 in all four examination areas- o Deutsche Sprachprüfung für den Hochschulzugang - Test of German Language Ability for International Students - (DSH, Level 2 or 3) o Deutsches Sprachdiplom der Kultusministerkonferenz - German Language Certificate of the Standing Conference of the German Ministers of Education and Cultural Affairs – Level 2 (KMK II) o The Kleines Deutsches Sprachdiplom - KDS- Großes Deutsches Sprachdiplom, or Zentrale Oberstufenprüfung - ZOP - (German language certificates of the Goethe Institute) o Deutsche Sprachprüfung II of the Sprachen- und Dolmetscher Institut München - German Language Examination II of the Language and Translators' Institute, Munich) | AU17: Bachelor en alemán. Master programm en inglés. El TFM se incluye en el LA cuando el alumno tenga un Supervisor en destino. Se puede agrupar meses | AY17: Institucional | AZ17: Electrical Engineering | BA17: Faculty of electrical Engineering and Information Technology | BC17: UPM (varias Escuelas) | BE17: =VLOOKUP(B17,'TEAMS_30-09-2021'!$D:$AG,30,FALSE) -> 0 | BF17: =VLOOKUP(B17,'ENCUESTAS JUN-2021'!I:I,1,FALSE) -> RWTH - Aachen | BG17: =VLOOKUP(B17,'TEAMS_30-09-2021'!D:D,1,FALSE) -> RWTH - Aachen | BL17: =VLOOKUP(E17,#REF!,1,FALSE) -> #REF!
A18: 17 | B18: Technische Universität Berlin (Faculty IV) | C18: Technische Universität Berlin | D18: Berlín | E18: D BERLIN02 | F18: DE | H18: 30 de abril (nomination) - 1 de junio (application) | I18: 04.30 | J18: 06.01 | K18: 31 de octubre (nomination) - 1 de diciembre (application) | L18: 10.31 | M18: 12.01 | N18: ER | P18: SÍ | Q18: SÍ | S18: Electrical Engineering (Electronics and Automation) / Computer Science (Information and CommunicationTechnologies) | T18: Sí | U18: 2 | V18: 12 | W18: exchange.programmes@tu-berlin.de | X18: Julia Fluthwedel, Laura Timmermann | Y18: SI | Z18: SI | AA18: NO | AB18: SI | AC18: SI | AD18: =_xlfn.TEXTJOIN("/",TRUE,IF(OfertaPlazas[[#This Row],[GITST]]="SI","GITST",""),IF(OfertaPlazas[[#This Row],[GIB]]="SI","GIB",""),IF(OfertaPlazas[[#This Row],[GISD]]="SI","GISD",""),IF(OfertaPlazas[[#This Row],[MASTER]]="SI","MASTER","")) -> GITST/GISD/MASTER | AE18: SI | AF18: SI | AG18: SI | AH18: SI | AI18: SI | AJ18: SI | AK18: SI | AL18: SI | AM18: SI | AN18: SI | AO18: SI | AP18: SI | AQ18: SI | AR18: NO | AS18: INGLÉS B2 (para TFM-TFG) o ALEMÁN A2 y B1 antes del comienzo del semestre (para asignaturas) | AT18: El Máster Elektrotechnik (Ingeniería Electrónica) se imparte en alemán y se precisa de un A2 en alemán para completar la Aplicación de destino.El Máster Computer Science (Informática) se imparte en inglés y no se precisa certificado de alemán. Ver información detallada en la web de la oficina internacional. .nivel ALEMÁN B1 requerido antes del comienzo del semestre para programas académicos en alemán. OJO: Anything above (B1, B2, C1, C2) can’t be older than 3 years at the time of the application deadline. Comprobad los requisitos de idiomas en la web de la TU Berlin según la titulación solicitada | AU18: Mínimo 160-180 ECTS superados para cursar asignaturas de Máster | AW18: No envían ToR en papel y su ToR no es verificable. Aceptamos el ToR si lo envía TU Berlín | AY18: Institucional | AZ18: Electrical Engineering | BA18: Institut für Teschniche Informatik and Mikroelectronik | BC18: UPM (varias Escuelas) | BD18: 20/1/2020 Narciso ha informado que en esta Universidad hay un profesor que ha estado con ellos en el GTI, para que los alumnos interesados sepan que pueden tener un contacto en la universidad de destino. | BE18: =VLOOKUP(B18,'TEAMS_30-09-2021'!$D:$AG,30,FALSE) -> #N/A | BF18: =VLOOKUP(B18,'ENCUESTAS JUN-2021'!I:I,1,FALSE) -> #N/A | BG18: =VLOOKUP(B18,'TEAMS_30-09-2021'!D:D,1,FALSE) -> #N/A
A19: 18 | B19: Rheinish Friedrich-Wilhems-Universität Bonn | C19: Rheinische Friedrich-Wilhelms-Universität Bonn | D19: Bonn | E19: D BONN01 | F19: DE | H19: 1 de mayo | I19: 05.01 | J19: 05.01 | K19: 1 de noviembre | L19: 11.01 | N19: ER | Q19: SÍ | S19: Computer Science (Information and CommunicationTechnologies) | T19: Sí | U19: 3 | V19: 12 | W19: erasmus-incoming@uni-bonn.de;programme-assist@uni-bonn.de; elmar.langetepe@informatik.uni-bonn.de | X19: Susanne Gittel-Avehounkpan; Elmar Langetepe . Manuela Meraner | Y19: SI | Z19: SI | AA19: NO | AB19: SI | AC19: SI | AD19: =_xlfn.TEXTJOIN("/",TRUE,IF(OfertaPlazas[[#This Row],[GITST]]="SI","GITST",""),IF(OfertaPlazas[[#This Row],[GIB]]="SI","GIB",""),IF(OfertaPlazas[[#This Row],[GISD]]="SI","GISD",""),IF(OfertaPlazas[[#This Row],[MASTER]]="SI","MASTER","")) -> GITST/GISD/MASTER | AE19: SI | AF19: SI | AG19: SI | AH19: SI | AI19: SI | AJ19: SI | AK19: SI | AL19: SI | AM19: SI | AN19: SI | AO19: SI | AP19: SI | AQ19: SI | AR19: NO | AS19: INGLÉS B2 o ALEMÁN B1 | AU19: Máster en inglés | AV19: Para el TFT hay que buscar y tener tutor en destino antes de iniciar la movilidad | AY19: Departamental | AZ19: Physics | BA19: Faculty of Natural Sciences: Physikalisches Institüt | BC19: ETSIT | BE19: =VLOOKUP(B19,'TEAMS_30-09-2021'!$D:$AG,30,FALSE) -> 0 | BF19: =VLOOKUP(B19,'ENCUESTAS JUN-2021'!I:I,1,FALSE) -> #N/A | BG19: =VLOOKUP(B19,'TEAMS_30-09-2021'!D:D,1,FALSE) -> Rheinish Friedrich-Wilhems-Universität Bonn
A20: 19 | B20: Technische Universität Braunschweig | C20: Technische Universität Braunschweig | E20: D BRAUNSC01 | F20: DE | H20: 30 de abril (nomination) - 31 de mayo (application) | I20: 04.30 | J20: 05.31 | K20: 31 de octubre (nomination) - 30 de noviembre (application) | L20: 10.31 | M20: 11.30 | N20: ER | P20: SÍ | S20: Electrical Engineering (Electronics and Automation) | T20: Sí | U20: 2 | V20: 12 | W20: exchange@tu-braunschweig.de | X20: Anne-Kathrin Kaiser | Y20: SI | Z20: SI | AA20: NO | AB20: NO | AC20: SI | AD20: =_xlfn.TEXTJOIN("/",TRUE,IF(OfertaPlazas[[#This Row],[GITST]]="SI","GITST",""),IF(OfertaPlazas[[#This Row],[GIB]]="SI","GIB",""),IF(OfertaPlazas[[#This Row],[GISD]]="SI","GISD",""),IF(OfertaPlazas[[#This Row],[MASTER]]="SI","MASTER","")) -> GITST/MASTER | AE20: SI | AF20: SI | AG20: SI | AH20: SI | AI20: SI | AJ20: SI | AK20: SI | AL20: SI | AM20: SI | AN20: SI | AO20: SI | AP20: SI | AQ20: SI | AR20: NO | AS20: ALEMÁN B1 o INGLÉS B1 | AU20: Mínimo 180 ECTS superados para cursar asignaturas de Máster | AV20: sube el número de alumnos de 1*12 a 2*12 15/01/2025 | AY20: Institucional | AZ20: Electronics Engineering | BC20: UPM (varias Escuelas) | BE20: =VLOOKUP(B20,'TEAMS_30-09-2021'!$D:$AG,30,FALSE) -> 0 | BF20: =VLOOKUP(B20,'ENCUESTAS JUN-2021'!I:I,1,FALSE) -> #N/A | BG20: =VLOOKUP(B20,'TEAMS_30-09-2021'!D:D,1,FALSE) -> Technische Universität Braunschweig
A21: 20 | B21: Technische Universität Darmstadt | C21: Technische Universität Darmstadt | D21: Darmstadt | E21: D DARMSTA01 | F21: DE | G21: 18 Meses | H21: 31 de marzo (nomination) - 30 de abril (application) | I21: 03.31 | J21: 04.30 | K21: 30 de septiembre (nomination) - 31 de octubre (application) | L21: 09.30 | M21: 10.31 | N21: ER | P21: SÍ | S21: Electrical Engineering (Electronics and Automation) | T21: Sí | U21: 4 | V21: 12 | W21: europe-incomings@pvw.tu-darmstadt.de | X21: Tanja Torres | Y21: SI | Z21: SI | AA21: NO | AB21: NO | AC21: SI | AD21: =_xlfn.TEXTJOIN("/",TRUE,IF(OfertaPlazas[[#This Row],[GITST]]="SI","GITST",""),IF(OfertaPlazas[[#This Row],[GIB]]="SI","GIB",""),IF(OfertaPlazas[[#This Row],[GISD]]="SI","GISD",""),IF(OfertaPlazas[[#This Row],[MASTER]]="SI","MASTER","")) -> GITST/MASTER | AE21: SI | AF21: SI | AG21: SI | AH21: SI | AI21: SI | AJ21: SI | AK21: SI | AL21: SI | AM21: SI | AN21: SI | AO21: SI | AP21: SI | AQ21: SI | AR21: SI | AS21: ALEMÁN A2 o INGLÉS B2 | AT21: + intensive German language course Para alumnos DT Inglés B2 Para alumnos DT Alemán: Goethe Certificate C1 | AU21: Para DT 90 ECTS (60ECTS de asignaturas y 30 de TFM). El Master de TU Darmstadt en inglés es: Master iCE (MICE = Master in Information and Communication Engineering). Duración 1año y medio + prorroga de max 1 año. El Máster en alemán: Master in Elektrotechnik und Informationstechnik / English courses: https://www.tucan.tu-darmstadt.de/scripts/mgrqcgi?APPNAME=CampusNet&PRGNAME=ACTION&ARGUMENTS=-ArRbQdVLqES91bsx53bxh1nfz5Sc3fPdqO2LhUfD4HVUxTtzHuqoJHc7CJmS6nO2o088NXhvM02sBmu5wKMaBzuB4gCU0ez5SiTxsNp50HT9SD9dB3t4Y7gLEDBa= | AY21: Institucional | AZ21: Electrical Engineering | BC21: UPM (varias Escuelas) | BE21: =VLOOKUP(B21,'TEAMS_30-09-2021'!$D:$AG,30,FALSE) -> 0 | BF21: =VLOOKUP(B21,'ENCUESTAS JUN-2021'!I:I,1,FALSE) -> #N/A | BG21: =VLOOKUP(B21,'TEAMS_30-09-2021'!D:D,1,FALSE) -> Technische Universität Darmstadt
A22: 21 | B22: Friedrich-Alexander Universität FAU | C22: Friedrich-Alexander-Universität Erlangen-Nürnberg | D22: Erlangen | E22: D ERLANGE01 | F22: DE | H22: 30 de abril (nomination) - 15 de mayo (application) | I22: 04.30 | J22: 05.15 | K22: 31 de octubre (application) - 15 de noviembre (nomination) | L22: 10.31 | M22: 11.15 | N22: ER | P22: SÍ | R22: SÍ | S22: Electrical Engineering (Electronics and Automation) / Biomedical Engineering (Medical Diagnosticand Treatment Technology) | T22: Sí | U22: 4 | V22: 10 | W22: mobility@fau.de | X22: international office | Y22: SI | Z22: SI | AA22: SI | AB22: NO | AC22: SI | AD22: =_xlfn.TEXTJOIN("/",TRUE,IF(OfertaPlazas[[#This Row],[GITST]]="SI","GITST",""),IF(OfertaPlazas[[#This Row],[GIB]]="SI","GIB",""),IF(OfertaPlazas[[#This Row],[GISD]]="SI","GISD",""),IF(OfertaPlazas[[#This Row],[MASTER]]="SI","MASTER","")) -> GITST/GIB/MASTER | AE22: SI | AF22: SI | AG22: SI | AH22: SI | AI22: SI | AJ22: SI | AK22: SI | AL22: SI | AM22: SI | AN22: SI | AO22: SI | AP22: SI | AQ22: SI | AR22: NO | AS22: ALEMÁN A2 o INGLÉS B2 o ALEMÁN B1 | AT22: Bachelor: ALEMÁN A2 o Inglés B2 // Master: Alemán B1 o Inglés B2 Official certificates (TOEFL, IELTS, DAF, etc.) or confirmations issued by a professional language teacher with stamp and signature are accepted. - for English: www.fau.de/files/2014/08/Programmstudierende_aus_dem_Ausland- Nachweis-Englischkenntnisse.pdf | AU22: Para hacer TFG en inglés es necesario buscar un tutor y consensuar con él el idioma. ENG para el Master "Communications and Multimedia Engineering (CME)" se requiere un nivel minimo de alemán A2 o es obligado hacer el curso intensivo de alemán en septiembre / 2*10 plazas en el area biomedical engineering y 2*10 plazas en el area Electronica engineering / Forma parte de EELISA | AY22: Departamental | AZ22: Electrical Engineering and Biomedical engineering | BA22: Hoch frenquenzentechnick and Zentralinstitüt für Medizintechnik | BC22: ETSIT | BE22: =VLOOKUP(B22,'TEAMS_30-09-2021'!$D:$AG,30,FALSE) -> ok | BF22: =VLOOKUP(B22,'ENCUESTAS JUN-2021'!I:I,1,FALSE) -> Friedrich-Alexander Universität FAU | BG22: =VLOOKUP(B22,'TEAMS_30-09-2021'!D:D,1,FALSE) -> Friedrich-Alexander Universität FAU
A23: 22 | B23: Hamburg University of Technology - TUHH | C23: Technische Universität Hamburg-Harburg | D23: Hamburg | E23: D HAMBURG03 | F23: DE | H23: 20 de abril (nomination) - 15 de junio (application) | I23: 04.20 | J23: 06.15 | K23: 20 de octubre (nomination) 15 de diciembre (application) | L23: 10.20 | M23: 12.15 | N23: ER | P23: SÍ | R23: SÍ | S23: Electrical Engineering (Electronics and Automation) / Biomedical Engineering (Medical Diagnosticand Treatment Technology) | T23: Sí | U23: 6 | V23: 12 | W23: internationaloffice@tuhh.de | X23: international office | Y23: SI | Z23: SI | AA23: SI | AB23: NO | AC23: SI | AD23: =_xlfn.TEXTJOIN("/",TRUE,IF(OfertaPlazas[[#This Row],[GITST]]="SI","GITST",""),IF(OfertaPlazas[[#This Row],[GIB]]="SI","GIB",""),IF(OfertaPlazas[[#This Row],[GISD]]="SI","GISD",""),IF(OfertaPlazas[[#This Row],[MASTER]]="SI","MASTER","")) -> GITST/GIB/MASTER | AE23: SI | AF23: SI | AG23: SI | AH23: SI | AI23: SI | AJ23: SI | AK23: SI | AL23: SI | AM23: SI | AN23: SI | AO23: SI | AP23: SI | AQ23: SI | AR23: NO | AS23: INGLÉS B2 o ALEMÁN B1 | AT23: (se acepta atestación firmada del departamento de lingüística) | AU23: asignaturas de Máster en inglés y Bachelor Engineering Science / 2 estudiantes en el área bio y 4 estudiantes en el área teleco | AY23: Departamental | AZ23: Electronics Automation and Biomedical Engineering | BA23: School of Electrical Engineering, Computer Sciences and Mathematic and School of Mechanical Engineering | BC23: ETSIT | BE23: =VLOOKUP(B23,'TEAMS_30-09-2021'!$D:$AG,30,FALSE) -> #N/A | BF23: =VLOOKUP(B23,'ENCUESTAS JUN-2021'!I:I,1,FALSE) -> #N/A | BG23: =VLOOKUP(B23,'TEAMS_30-09-2021'!D:D,1,FALSE) -> #N/A
A24: 23 | B24: Universität Kassel | C24: Universität Kassel | D24: Kassel | E24: D KASSEL01 | F24: DE | H24: 31 de mayo (nomination-application) | I24: 05.31 | J24: 05.31 | K24: 30 de noviembre (nomination-application) | L24: 11.30 | M24: 11.30 | N24: ER | O24: SÍ | P24: SÍ | Q24: SÍ | S24: Electrical Engineering: (Electricity and Energy); (Electronics and Automation) / ComputerScience (Information and CommunicationTechnologies) | T24: Sí | U24: 1 | V24: 12 | W24: exchange@uni-kassel.de | X24: international office | Y24: SI | Z24: SI | AA24: NO | AB24: SI | AC24: SI | AD24: =_xlfn.TEXTJOIN("/",TRUE,IF(OfertaPlazas[[#This Row],[GITST]]="SI","GITST",""),IF(OfertaPlazas[[#This Row],[GIB]]="SI","GIB",""),IF(OfertaPlazas[[#This Row],[GISD]]="SI","GISD",""),IF(OfertaPlazas[[#This Row],[MASTER]]="SI","MASTER","")) -> GITST/GISD/MASTER | AE24: SI | AF24: SI | AG24: SI | AH24: SI | AI24: SI | AJ24: SI | AK24: SI | AL24: SI | AM24: SI | AN24: SI | AO24: SI | AP24: SI | AQ24: SI | AR24: NO | AS24: INGLÉS B2 o ALEMÁN B1 | AU24: Algunas asignaturas en inglés, especialmete en el área 061 / posibilidad de TFM y TFG en inglés: la unviersidad aceptará las solicitudes "caso por caso" | AY24: Departamental | AZ24: Electronics Automation and Computer Science | BA24: Electrotechnik | BC24: ETSIT | BE24: =VLOOKUP(B24,'TEAMS_30-09-2021'!$D:$AG,30,FALSE) -> 0 | BF24: =VLOOKUP(B24,'ENCUESTAS JUN-2021'!I:I,1,FALSE) -> #N/A | BG24: =VLOOKUP(B24,'TEAMS_30-09-2021'!D:D,1,FALSE) -> Universität Kassel
A25: 24 | B25: Mannheim University of Applied Sciences | C25: Hochschule Mannheim | D25: Mannheim | E25: D MANNHEI03 | F25: DE | H25: 30 de abril(nomination)-31 de mayo(application) | I25: 04.30 | J25: 05.31 | K25: 30 septiembre (nomination) - 15 noviembre (application) | L25: 09.30 | M25: 11.15 | N25: ER | P25: SÍ | R25: SÍ | S25: Electrical Engineering (Electronics and Automation) / Biomedical Engineering (Medical Diagnosticand Treatment Technology) | T25: Sí | U25: 2 | V25: 12 | W25: erasmus.io@hs-mannheim.de;incoming.io@hs-mannheim.de | X25: Ms. Maria Mann | Y25: SI | Z25: SI | AA25: SI | AB25: NO | AC25: SI | AD25: =_xlfn.TEXTJOIN("/",TRUE,IF(OfertaPlazas[[#This Row],[GITST]]="SI","GITST",""),IF(OfertaPlazas[[#This Row],[GIB]]="SI","GIB",""),IF(OfertaPlazas[[#This Row],[GISD]]="SI","GISD",""),IF(OfertaPlazas[[#This Row],[MASTER]]="SI","MASTER","")) -> GITST/GIB/MASTER | AE25: SI | AF25: SI | AG25: SI | AH25: SI | AI25: SI | AJ25: NO | AK25: NO | AL25: NO | AM25: NO | AN25: SI | AO25: SI | AP25: NO | AQ25: SI | AR25: NO | AS25: ALEMÁN B1 o ALEMÁN A2 o INGLÉS B2 | AT25: + curso intensivo de alemán en septiembre | AU25: Biomédical engineering sólo en Departamento Tecnologías de la Información (NO con Departamento de Biotecnología) /Alemán para Bioingeniería médica / Inglés o Alemán para Electronics /Alemán para Bachelor y demás programas de Máster. Mínimo 180 ECTS superados para cursar asignaturas de Máster. | AV25: No se puede dividir el número de plazas | BE25: =VLOOKUP(B25,'TEAMS_30-09-2021'!$D:$AG,30,FALSE) -> #N/A | BF25: =VLOOKUP(B25,'ENCUESTAS JUN-2021'!I:I,1,FALSE) -> #N/A | BG25: =VLOOKUP(B25,'TEAMS_30-09-2021'!D:D,1,FALSE) -> #N/A
A26: 25 | B26: Technische Universität München | C26: Technische Universität München (TUM) | D26: München | E26: D MUNCHEN02 | F26: DE | H26: 30 de abril (nomination) - 10 de mayo (application) | I26: 04.30 | J26: 05.10 | K26: 17 de octubre (nomination) 31 de octubre (application) | L26: 10.17 | N26: ER | O26: SÍ | S26: Electrical Engineering (Electricity and Energy) | T26: Sí | U26: 3 | V26: 12 | W26: larissa.meier@tum.de | X26: Larissa Meier | Y26: SI | Z26: SI | AA26: NO | AB26: NO | AC26: SI | AD26: =_xlfn.TEXTJOIN("/",TRUE,IF(OfertaPlazas[[#This Row],[GITST]]="SI","GITST",""),IF(OfertaPlazas[[#This Row],[GIB]]="SI","GIB",""),IF(OfertaPlazas[[#This Row],[GISD]]="SI","GISD",""),IF(OfertaPlazas[[#This Row],[MASTER]]="SI","MASTER","")) -> GITST/MASTER | AE26: SI | AF26: SI | AG26: SI | AH26: SI | AI26: SI | AJ26: SI | AK26: SI | AL26: SI | AM26: SI | AN26: SI | AO26: SI | AP26: SI | AQ26: SI | AR26: NO | AS26: ALEMÁN B1 o INGLÉS B2 | AT26: (una atestación del departmento de lingüística es aceptada) | AU26: Se pueden cursar asignaturas de varios departamentos pero la mayoría deben ser de Electrical and Computer Engineering (at least 60%). Para movilidad de 1 semestre, solo hay un periodo de examinación. | AV26: Please only nominate students within the existing agreements between your university and TUM! Do not change the number of students or the TUM department, as we could not accept such nominations! - Al tratarse de un acuerdo en el marco de Electrical Engineering, al menos un 60% de los créditos a cursar deben corresponder a esta rama. No se puede dividir el número de plazas. RETOMAR ACUERDO INCLUIR 061 y 914 EN MAYO 2024 | AY26: Departamental | AZ26: Electrical Engineering | BA26: Faculty of Electrical Engineering and Information Technology | BC26: UPM (varias Escuelas) | BE26: =VLOOKUP(B26,'TEAMS_30-09-2021'!$D:$AG,30,FALSE) -> 0 | BF26: =VLOOKUP(B26,'ENCUESTAS JUN-2021'!I:I,1,FALSE) -> #N/A | BG26: =VLOOKUP(B26,'TEAMS_30-09-2021'!D:D,1,FALSE) -> Technische Universität München
A27: 26 | B27: Universität des Saarlandes | C27: Universität des Saarlandes | D27: Saarbruecken | E27: D SAARBRU01 | F27: DE | H27: 15 de junio (nomination)- 30 junio (application) | I27: 06.15 | J27: 06.30 | K27: 15 de diciembre (nomination) - 30 de diciembre (application) | L27: 12.15 | M27: 12.30 | N27: ER | P27: SÍ | Q27: SÍ | R27: Sí | S27: Electrical Engineering (Electronics and Automation) / Computer Science (Information and CommunicationTechnologies) / Biomedical Engineering | T27: Sí | U27: 2 | V27: 12 | W27: erasmus@io.uni-saarland.de; international@uni-saarland.de (IIA) | X27: Luis Lidon | Y27: SI | Z27: SI | AA27: SI | AB27: SI | AC27: SI | AD27: =_xlfn.TEXTJOIN("/",TRUE,IF(OfertaPlazas[[#This Row],[GITST]]="SI","GITST",""),IF(OfertaPlazas[[#This Row],[GIB]]="SI","GIB",""),IF(OfertaPlazas[[#This Row],[GISD]]="SI","GISD",""),IF(OfertaPlazas[[#This Row],[MASTER]]="SI","MASTER","")) -> GITST/GIB/GISD/MASTER | AE27: SI | AF27: SI | AG27: SI | AH27: SI | AI27: SI | AJ27: SI | AK27: SI | AL27: SI | AM27: SI | AN27: SI | AO27: SI | AP27: SI | AQ27: NO | AR27: NO | AS27: ALEMÁN B1 o INGLÉS B2 | AU27: asignaturas de Máster "Computer and Communication Technology" en inglés / 2 plazas para computer science / acuerdo con su UDS Systems Engineering. course catalogue: https://www.lsf.uni-saarland.de/qisserver/rds?state=wtree&search=1&trex=step&root120242=396627%7C397868%7C394098&P.vx=kurz uy acuerdo con UDS Computer Science | AY27: Departamental | AZ27: Electrical Engineering, Medical Technology and Computer Science | BA27: Mechatronik and Mathematics&Informatik | BC27: ETSIT | BE27: =VLOOKUP(B27,'TEAMS_30-09-2021'!$D:$AG,30,FALSE) -> 0 | BF27: =VLOOKUP(B27,'ENCUESTAS JUN-2021'!I:I,1,FALSE) -> Universität des Saarlandes | BG27: =VLOOKUP(B27,'TEAMS_30-09-2021'!D:D,1,FALSE) -> Universität des Saarlandes | BL27: =VLOOKUP(E27,#REF!,1,FALSE) -> #REF!
A28: 27 | B28: Universität Stuttgart | C28: Universität Stuttgart | D28: Stuttgart | E28: D STUTTGA01 | F28: DE | H28: 1 de abril (nomination) 1 de mayo (registration) 1 de junio (application) | I28: 04.01 | J28: 05.01 | K28: 1 de octubre (nomination) - 1 de noviembre (registration) - 1 de diciembre (application) | L28: 10.01 | M28: 11.01 | N28: ER | P28: SÍ | R28: SÍ | S28: Electrical Engineering (Electronics and Automation) / Biomedical Engineering (Medical Diagnosticand Treatment Technology) | T28: Sí | U28: 4 | V28: 12 | W28: incoming@ia.uni-stuttgart.de | X28: Rebecca Schwenger Silvia Cornacchiari | Y28: SI | Z28: SI | AA28: SI | AB28: NO | AC28: SI | AD28: =_xlfn.TEXTJOIN("/",TRUE,IF(OfertaPlazas[[#This Row],[GITST]]="SI","GITST",""),IF(OfertaPlazas[[#This Row],[GIB]]="SI","GIB",""),IF(OfertaPlazas[[#This Row],[GISD]]="SI","GISD",""),IF(OfertaPlazas[[#This Row],[MASTER]]="SI","MASTER","")) -> GITST/GIB/MASTER | AE28: SI | AF28: SI | AG28: SI | AH28: SI | AI28: SI | AJ28: SI | AK28: SI | AL28: SI | AM28: SI | AN28: SI | AO28: SI | AP28: SI | AQ28: SI | AR28: NO | AS28: INGLÉS B2 o ALEMÁN B2 | AT28: Junto con cursos intensivos de alemán | AU28: Para realizar e TFG o TFM el alumno deberá solicitar el curso entero y cursar asignaturas en el 1er semestre mientras el Proyecto se realizará en el 2ndo semestre / Mínimo 180 ECTS superados para cursar asignaturas de Máster /2 alumnos para 714 y 2 alumos para 914. | AY28: Institucional y Departamental | AZ28: Electrical Engineering and Information Technology, Biomedical Engineering | BC28: UPM (varias Escuelas) + ETSIT | BE28: =VLOOKUP(B28,'TEAMS_30-09-2021'!$D:$AG,30,FALSE) -> ok | BF28: =VLOOKUP(B28,'ENCUESTAS JUN-2021'!I:I,1,FALSE) -> Universität Stuttgart | BG28: =VLOOKUP(B28,'TEAMS_30-09-2021'!D:D,1,FALSE) -> Universität Stuttgart | BL28: =VLOOKUP(E28,#REF!,1,FALSE) -> #REF!
A29: 28 | B29: Aalborg University | C29: Aalborg Universitet | D29: Aalborg | E29: DK ALBORG01 | F29: DK | H29: 1 de abril (nomination) 15 de abril (application) | I29: 04.01 | J29: 04.15 | K29: 1 de octubre (nomination) - 15 de octubre (application) | L29: 10.10 | M29: 10.15 | N29: ER | P29: SÍ | S29: Electrical Engineering (Electronics and Automation) | T29: Sí | U29: 1 | V29: 12 | W29: internationaloffice@aau.dk; incoming-student@aau.dk; outgoing-student@adm.aau.dk | X29: Rikke Hougaard | Y29: SI | Z29: SI | AA29: NO | AB29: NO | AC29: SI | AD29: =_xlfn.TEXTJOIN("/",TRUE,IF(OfertaPlazas[[#This Row],[GITST]]="SI","GITST",""),IF(OfertaPlazas[[#This Row],[GIB]]="SI","GIB",""),IF(OfertaPlazas[[#This Row],[GISD]]="SI","GISD",""),IF(OfertaPlazas[[#This Row],[MASTER]]="SI","MASTER","")) -> GITST/MASTER | AE29: SI | AF29: SI | AG29: SI | AH29: SI | AI29: SI | AJ29: SI | AK29: SI | AL29: SI | AM29: SI | AN29: SI | AO29: SI | AP29: SI | AQ29: SI | AR29: NO | AS29: INGLÉS B2 | AT29: (IELTS 6.5 / TOEFL 85 with a minimum score of 20 in each section / Cambridge ESOL C1) | AU29: Campus en Aalborg y en Copenhagen. Mínimo 180 ECTS superados para cursar asignaturas de Máster. Se requiere cursar 30 ECTS/semestre. Para asignaturas de Electronics y IT, escoger asignaturas de "Innovative Communication Technologies and Entrepreneurship", "Signal Processing and Acoustics" y "Control and Automation" /Students can only choose course packages with the study board(s) that are covered by the exchange agreement with you as an exchange partner | AV29: En cuanto al TOEFL se podría hacer una excepción si una de las competencias tiene un 19 pero la suma general cumple con los requisitos | BE29: =VLOOKUP(B29,'TEAMS_30-09-2021'!$D:$AG,30,FALSE) -> 0 | BF29: =VLOOKUP(B29,'ENCUESTAS JUN-2021'!I:I,1,FALSE) -> #N/A | BG29: =VLOOKUP(B29,'TEAMS_30-09-2021'!D:D,1,FALSE) -> Aalborg University | BL29: =VLOOKUP(E29,#REF!,1,FALSE) -> #REF!
A30: 29 | B30: Technical University of Denmark - DTU | C30: Danmarks Tekniske Universitet | D30: Lyngby (Copenhague) | E30: DK LYNGBY01 | F30: DK | H30: 15 de abril | I30: 04.15 | J30: 04.15 | K30: 1 de noviembre | L30: 11.01 | N30: ER | P30: SÍ | Q30: SÍ | R30: SÍ | S30: Electrical Engineering (Electronics and Automation) / Biomedical Engineering / Computer Science | T30: Sí | U30: 2 | V30: 12 | W30: asmae@dtu.dk | X30: Astrid Marie Christiansen | Y30: SI | Z30: SI | AA30: SI | AB30: SI | AC30: SI | AD30: =_xlfn.TEXTJOIN("/",TRUE,IF(OfertaPlazas[[#This Row],[GITST]]="SI","GITST",""),IF(OfertaPlazas[[#This Row],[GIB]]="SI","GIB",""),IF(OfertaPlazas[[#This Row],[GISD]]="SI","GISD",""),IF(OfertaPlazas[[#This Row],[MASTER]]="SI","MASTER","")) -> GITST/GIB/GISD/MASTER | AE30: SI | AF30: SI | AG30: SI | AH30: SI | AI30: SI | AJ30: SI | AK30: SI | AL30: SI | AM30: SI | AN30: SI | AO30: SI | AP30: SI | AQ30: SI | AR30: NO | AS30: INGLÉS B2 | AT30: (atestación del departamento de lingüística válida) | AU30: Bachelor en Danés. Master en inglés. No se puede comenzar la Master's Thesis hasta Febrero y el periodo de realización es 5 meses. Min 20 ECTS por semestre http://www.dtu.dk/english/Education/Incoming-students/Exchange. | BE30: =VLOOKUP(B30,'TEAMS_30-09-2021'!$D:$AG,30,FALSE) -> #N/A | BF30: =VLOOKUP(B30,'ENCUESTAS JUN-2021'!I:I,1,FALSE) -> #N/A | BG30: =VLOOKUP(B30,'TEAMS_30-09-2021'!D:D,1,FALSE) -> #N/A
A31: 30 | B31: Université Marie et Louis Pasteur | C31: Université de Franche-Comté | D31: Besançon | E31: F BESANCO01 | F31: FR | H31: 15 de mayo (nomination)- 1 de junio (application) | I31: 05.15 | J31: 06.01 | K31: 15 de octubre (nomination) - 1 de noviembre (application) | L31: 10.15 | M31: 11.01 | N31: ER | R31: SÍ | S31: Biomedical Engineering (Medical Diagnosticand Treatment Technology) | T31: Sí | U31: 1 | V31: 12 | W31: michelle.parrenin@univ-fcomte.fr | X31: Michelle PARRENIN | Y31: SI | Z31: NO | AA31: SI | AB31: NO | AC31: SI | AD31: =_xlfn.TEXTJOIN("/",TRUE,IF(OfertaPlazas[[#This Row],[GITST]]="SI","GITST",""),IF(OfertaPlazas[[#This Row],[GIB]]="SI","GIB",""),IF(OfertaPlazas[[#This Row],[GISD]]="SI","GISD",""),IF(OfertaPlazas[[#This Row],[MASTER]]="SI","MASTER","")) -> GIB/MASTER | AE31: SI | AF31: SI | AG31: SI | AH31: SI | AI31: SI | AJ31: SI | AK31: SI | AL31: SI | AM31: SI | AN31: SI | AO31: SI | AP31: SI | AQ31: SI | AR31: NO | AS31: FRANCÉS B1 | AU31: Medical Technology | AV31: cambió el nombre universidad en marzo 2025 | AY31: Departamental | AZ31: 914 Biomedical Engineering | BA31: Medical diagnostic and treatmente technology | BB31: Jean-Marie CROLET - jean-marie.crolet@univ-fcmote.fr | BC31: UPM (varias Escuelas) | BE31: =VLOOKUP(B31,'TEAMS_30-09-2021'!$D:$AG,30,FALSE) -> #N/A | BF31: =VLOOKUP(B31,'ENCUESTAS JUN-2021'!I:I,1,FALSE) -> #N/A | BG31: =VLOOKUP(B31,'TEAMS_30-09-2021'!D:D,1,FALSE) -> #N/A
A32: 31 | B32: École pour l'Informatique et les Techniques Avancées - EPITA | C32: Ecole pour l'Informatique et les Techniques Avancées (EPITA) | D32: Paris | E32: F BICETRE02 | F32: FR | H32: 15 de mayo (nomination) - 30 de mayo (application) | I32: 05.15 | J32: 05.30 | K32: 15 de octubre (nomination) - 31 de octubre (application) | L32: 10.15 | M32: 10.31 | N32: ER | P32: SÍ | Q32: SÍ | S32: Electrical Engineering (Electronics and Automation) / Computer Science (Information and Communication Technologies) | T32: Sí | U32: 2 | V32: 12 | W32: international@epita.fr ; camille-chloe.moussa@epita.fr | X32: Camille-Chloé MOUSSA | Y32: SI | Z32: SI | AA32: NO | AB32: SI | AC32: SI | AD32: =_xlfn.TEXTJOIN("/",TRUE,IF(OfertaPlazas[[#This Row],[GITST]]="SI","GITST",""),IF(OfertaPlazas[[#This Row],[GIB]]="SI","GIB",""),IF(OfertaPlazas[[#This Row],[GISD]]="SI","GISD",""),IF(OfertaPlazas[[#This Row],[MASTER]]="SI","MASTER","")) -> GITST/GISD/MASTER | AE32: SI | AF32: SI | AG32: SI | AH32: SI | AI32: SI | AJ32: SI | AK32: SI | AL32: SI | AM32: SI | AN32: SI | AO32: SI | AP32: SI | AQ32: SI | AR32: NO | AS32: FRANCÉS B1 o INGLÉS B2 | AT32: INGLÉS B2(TOEFL (minimum score 550 ITP, 80 IBT) TOEIC (minimum score 750) IELTS (minimum score 6.0) Cambridge ESOL Examinations BULATS (B2) | AU32: Master degrees in English: https://www.epita.fr/en/degree-programs-english/ | AY32: Institucional | AZ32: 610 Computer Science | BB32: Eramus+ Coordinator: Ms Maria Hutler maria.hulter@epita.fr/Ms Nazima Canda mazima.canda@epifa.fr | BC32: UPM (varias Escuelas) | BD32: Acuerdo: 0610 Information and Communication Technologies | BE32: =VLOOKUP(B32,'TEAMS_30-09-2021'!$D:$AG,30,FALSE) -> #N/A | BF32: =VLOOKUP(B32,'ENCUESTAS JUN-2021'!I:I,1,FALSE) -> #N/A | BG32: =VLOOKUP(B32,'TEAMS_30-09-2021'!D:D,1,FALSE) -> #N/A
A33: 32 | B33: ENSEIRB MATMECA / IPB | C33: Bordeaux INP – Ecole Nationale Supérieure d’Electronique, Informatique, Télécommunications, Mathématiques et Mécanique (ENSEIRB-MATMECA) | D33: Bordeaux | E33: F BORDEAU54 | F33: FR | H33: 1 de mayo (nomination) 15 de mayo (application) | I33: 05.01 | J33: 05.15 | K33: 1 de noviemrbe (nomination) - 15 noviembre (application) | L33: 11.01 | M33: 11.15 | N33: ER | P33: SÍ | Q33: SÍ | S33: Electrical Engineering (Electronics and Automation) /Computer Science (Information and Communication Technologies) | T33: Sí | U33: 2 | V33: 12 | W33: iro@enseirb-matmeca.fr | X33: international office | Y33: SI | Z33: SI | AA33: NO | AB33: SI | AC33: SI | AD33: =_xlfn.TEXTJOIN("/",TRUE,IF(OfertaPlazas[[#This Row],[GITST]]="SI","GITST",""),IF(OfertaPlazas[[#This Row],[GIB]]="SI","GIB",""),IF(OfertaPlazas[[#This Row],[GISD]]="SI","GISD",""),IF(OfertaPlazas[[#This Row],[MASTER]]="SI","MASTER","")) -> GITST/GISD/MASTER | AE33: SI | AF33: SI | AG33: SI | AH33: SI | AI33: SI | AJ33: NO | AK33: SI | AL33: SI | AM33: SI | AN33: SI | AO33: SI | AP33: SI | AQ33: SI | AR33: NO | AS33: FRANCÉS B2 | AU33: • Programs taught in English are only available at Master level (Master 2): Automatic and Mecatronics in Automotive, Aeronautic and Space Industry Electronic systems for biomedical engineering Radio & Telecommunication Systems Advanced Modelling of Materials and Structures | AY33: Institucional | AZ33: ¿713 Electronics Engineering /y/o 714 Electrical Engineering ? | BB33: International Officer: Ms Marie-Odile Vasconcelos -iro@enseirb-matmeca.fr | BC33: ETSIT | BD33: Acuerdo: 071 Electronics and automation/Telecomunication- Aparece el área 725 Medical Tecnology sin plazas -Para teacher area 071 Electrical and Telecom Engin | BE33: =VLOOKUP(B33,'TEAMS_30-09-2021'!$D:$AG,30,FALSE) -> se añade el área 610 ICTs acordado con ENSEIRB | BF33: =VLOOKUP(B33,'ENCUESTAS JUN-2021'!I:I,1,FALSE) -> #N/A | BG33: =VLOOKUP(B33,'TEAMS_30-09-2021'!D:D,1,FALSE) -> ENSEIRB MATMECA / IPB
A34: 33 | B34: École Nationale d’Ingénieurs de Brest ENIB | C34: Ecole Nationale d'Ingénieurs de Brest | D34: Brest | E34: F BREST07 | F34: FR | H34: 15 de mayo | I34: 05.15 | J34: 05.15 | K34: 15 de noviembre | L34: 11.15 | M34: 11.15 | N34: ER | P34: SÍ | Q34: Sí | S34: Electrical Engineering (Electronics and Automation) / Computer Science (Information and Communication Technologies) | T34: Sí | U34: 3 | V34: 12 | W34: international@enib.fr; | X34: Katy LE BRIS | Y34: SI | Z34: SI | AA34: NO | AB34: SI | AC34: SI | AD34: =_xlfn.TEXTJOIN("/",TRUE,IF(OfertaPlazas[[#This Row],[GITST]]="SI","GITST",""),IF(OfertaPlazas[[#This Row],[GIB]]="SI","GIB",""),IF(OfertaPlazas[[#This Row],[GISD]]="SI","GISD",""),IF(OfertaPlazas[[#This Row],[MASTER]]="SI","MASTER","")) -> GITST/GISD/MASTER | AE34: SI | AF34: SI | AG34: SI | AH34: SI | AI34: SI | AJ34: SI | AK34: SI | AL34: SI | AM34: SI | AN34: SI | AO34: SI | AP34: SI | AQ34: SI | AR34: NO | AS34: FRANCÉS B2 o INGLÉS B2 | AT34: INGLÉS B2 (for project or bachelor/master thesis) | AU34: Every international student must attend a French language course throughout the year (a placement test will determine your group) | AY34: Institucional | AZ34: 714 Electrical Engineering | BB34: Institutional coordinator: Anne Pierre-Duplessix-anne.pierre-duplessix@telecom:bretagne.eu | BC34: ETSIT | BE34: =VLOOKUP(B34,'TEAMS_30-09-2021'!$D:$AG,30,FALSE) -> 0 | BF34: =VLOOKUP(B34,'ENCUESTAS JUN-2021'!I:I,1,FALSE) -> #N/A | BG34: =VLOOKUP(B34,'TEAMS_30-09-2021'!D:D,1,FALSE) -> École Nationale d’Ingénieurs de Brest ENIB
A35: 34 | B35: ISEN Yncréa Ouest | C35: Institut Supérieur de l'Electronique et du Numérique - Brest : ISEN-Brest | D35: Brest | E35: F BREST26 | F35: FR | H35: 1 de mayo (nomination) - 30 de mayo (application) | I35: 05.01 | J35: 05.30 | K35: 1 de octubre (nomination) - 30 de octubre (application) | L35: 10.01 | M35: 10.30 | N35: ER | P35: Sí | Q35: Sí | R35: SÍ | S35: Electrical Engineering (Electronics and Automation) / Biomedical Engineering (Medical Diagnosticand Treatment Technology) / Computer Science ICTs | T35: Sí | U35: 4 | V35: 6 | W35: susan.gibbs@isen-ouest.yncrea.fr | X35: Susan Gibbs | Y35: SI | Z35: SI | AA35: SI | AB35: SI | AC35: SI | AD35: =_xlfn.TEXTJOIN("/",TRUE,IF(OfertaPlazas[[#This Row],[GITST]]="SI","GITST",""),IF(OfertaPlazas[[#This Row],[GIB]]="SI","GIB",""),IF(OfertaPlazas[[#This Row],[GISD]]="SI","GISD",""),IF(OfertaPlazas[[#This Row],[MASTER]]="SI","MASTER","")) -> GITST/GIB/GISD/MASTER | AE35: SI | AF35: SI | AG35: SI | AH35: SI | AI35: SI | AJ35: SI | AK35: SI | AL35: SI | AM35: SI | AN35: SI | AO35: SI | AP35: SI | AQ35: SI | AR35: NO | AS35: INGLÉS B2 o FRANCÉS B2 | AT35: INGLÉS B2 (TOEIC (min. 785), TOEFL-IBT (min . 72) or equivalent test (Cambridge, Duolingo)) | AU35: Subjects in English given in the fall semester (they are working to extend them to the spring semester): https://isen-nantes.fr/international-accueil/exchange-students/ | AV35: acuerdo firmado en agosto 2023 | BB35: Ms Susan Gibbs: susan.gibbs@isen-ouest.yncrea.fr (Institutionnal Coordinator); anne-marie.miras@isen-ouest.yncrea.fr (Coordinator incoming students)
A36: 35 | B36: École Nationale Supérieure d'Ingénieurs de Caen ENSICAEN | C36: Ecole Nationale Supérieure d'Ingénieurs de Caen (ENSICAEN) | D36: Caen | E36: F CAEN05 | F36: FR | H36: 30 de abril (nomination) - 1 de julio (Application) | I36: 04.30 | J36: 07.01 | K36: 15 de octubre (nomination) - 1 de diciembre (application) | L36: 10.15 | M36: 12.01 | N36: ER | P36: SÍ | Q36: Sí | R36: SÍ | S36: Electrical Engineering (Electronics and Automation) / Biomedical Engineering (Medical Diagnosticand Treatment Technology) / Computer Science ICTs | T36: Sí | U36: 2 | V36: 12 | W36: international@ensicaen.fr | Y36: SI | Z36: SI | AA36: NO | AB36: SI | AC36: SI | AD36: =_xlfn.TEXTJOIN("/",TRUE,IF(OfertaPlazas[[#This Row],[GITST]]="SI","GITST",""),IF(OfertaPlazas[[#This Row],[GIB]]="SI","GIB",""),IF(OfertaPlazas[[#This Row],[GISD]]="SI","GISD",""),IF(OfertaPlazas[[#This Row],[MASTER]]="SI","MASTER","")) -> GITST/GISD/MASTER | AE36: SI | AF36: SI | AG36: SI | AH36: SI | AI36: SI | AJ36: SI | AK36: SI | AL36: SI | AM36: SI | AN36: SI | AO36: SI | AP36: SI | AQ36: SI | AR36: SI | AS36: FRANCÉS B1 o INGLÉS B2 | AU36: DT 2 opciones: 1. 4º curso de grado + 2º de MUIT o 2. 2º curso de MUIT (2 años) | AV36: DT válido hasta 2022/23 | AY36: Institucional | AZ36: 610 Computer Science / 713 Electronics Engineering | BB36: Erasmus Institutional Coordinator: Cantal Gunther- chantal.gunther@ensicaenfr | BC36: ETSIT | BD36: Acuerdo: 0481 Computer Sciences/ 0714 Electronics Telecommunication Engineering/ Se añade 914 Bio | BE36: =VLOOKUP(B36,'TEAMS_30-09-2021'!$D:$AG,30,FALSE) -> se añade el área de bio acordado con ENSICAEN | BF36: =VLOOKUP(B36,'ENCUESTAS JUN-2021'!I:I,1,FALSE) -> École Nationale Supérieure d'Ingénieurs de Caen ENSICAEN | BG36: =VLOOKUP(B36,'TEAMS_30-09-2021'!D:D,1,FALSE) -> École Nationale Supérieure d'Ingénieurs de Caen ENSICAEN
A37: 36 | B37: EURECOM | C37: Eurecom | D37: Sophia Antipolis | E37: F CANNES09 | F37: FR | G37: 18 Meses | H37: 1 de mayo (nomination) - 15 de mayo (application) | I37: 05.01 | J37: 05.15 | K37: 1 de noviembre (nomination) - 15 de noviembre (application) | L37: 11.01 | M37: 11.15 | N37: ER | P37: SÍ | Q37: Sí | S37: Electrical Engineering (Electronics and Automation) / Computer Science (Information and CommunicationTechnologies) | T37: Sí | U37: 3 | V37: 10 | W37: pascale.castaing@eurecom.fr; Stephanie.Marmion@eurecom.fr; Admission@eurecom.fr | X37: Pascale Castaing; Stéphanie Marmion; Guillaume de Lemos | Y37: SI | Z37: SI | AA37: NO | AB37: SI | AC37: SI | AD37: =_xlfn.TEXTJOIN("/",TRUE,IF(OfertaPlazas[[#This Row],[GITST]]="SI","GITST",""),IF(OfertaPlazas[[#This Row],[GIB]]="SI","GIB",""),IF(OfertaPlazas[[#This Row],[GISD]]="SI","GISD",""),IF(OfertaPlazas[[#This Row],[MASTER]]="SI","MASTER","")) -> GITST/GISD/MASTER | AE37: SI | AF37: SI | AG37: SI | AH37: SI | AI37: SI | AJ37: SI | AK37: SI | AL37: SI | AM37: SI | AN37: SI | AO37: SI | AP37: SI | AQ37: SI | AR37: SI | AS37: INGLÉS B1 | AT37: (recomendado FRANCÉS A2 una vez inscritos) | AU37: https://www.eurecom.fr/index.php/en/teaching/engineering-studies-exchange-students / Para alumnos de DT: 18 meses ( 1 curso asignaturas y 1 semestre TFM TOTAL: 90 ECTS) | AV37: nuevo acuerdo + DT octubre 2022 / 2 alumnos para electricalengineering y 1 alumno para computer science / Philipe s'en va juillet 2023
A38: 37 | B38: Ecole Nationale Supérieure de l'Electronique et de ses Applications (ENSEA) | C38: Ecole Nationale Supérieure de l'Electronique et de ses Applications | D38: Cergy (Paris) | E38: F CERGY01 | F38: FR | H38: 1 de junio(nomination)- 15 de junio(application) | I38: 06.01 | J38: 06.15 | K38: 15 de octubre (nomination) - 31 de octubre (application) | L38: 10.15 | M38: 10.31 | N38: ER | P38: SÍ | R38: SÍ | S38: Electrical Engineering (Electronics and Automation) / Biomedical Engineering (Medical Diagnosticand Treatment Technology) | T38: Sí | U38: 4 | V38: 12 | W38: ri@ensea.fr | X38: Ms Manuela Insana | Y38: SI | Z38: SI | AA38: SI | AB38: NO | AC38: SI | AD38: =_xlfn.TEXTJOIN("/",TRUE,IF(OfertaPlazas[[#This Row],[GITST]]="SI","GITST",""),IF(OfertaPlazas[[#This Row],[GIB]]="SI","GIB",""),IF(OfertaPlazas[[#This Row],[GISD]]="SI","GISD",""),IF(OfertaPlazas[[#This Row],[MASTER]]="SI","MASTER","")) -> GITST/GIB/MASTER | AE38: SI | AF38: SI | AG38: SI | AH38: SI | AI38: SI | AJ38: NO | AK38: NO | AL38: SI | AM38: SI | AN38: SI | AO38: SI | AP38: SI | AQ38: SI | AR38: SI | AS38: FRANCÉS B1 o INGLÉS B2 | AU38: new English-taught programs starting in September 2022 in the following fields of study: Physical Engineering and Embedded Systems, Materials and Chemistry, Computer Science | AV38: DT firmado octubre 2020 válido hasta 2024/25 | AY38: Institucional | AZ38: 714 Electrical Engineering / 914 Biomedical Engineering | BB38: Head of International Relations: Prof. Christina Faye-faye@ensea.fr | BC38: ETSIT | BD38: Acuerdo: 065 Electrical&Telecom Engin/725 Medical Technology | BE38: =VLOOKUP(B38,'TEAMS_30-09-2021'!$D:$AG,30,FALSE) -> 0 | BF38: =VLOOKUP(B38,'ENCUESTAS JUN-2021'!I:I,1,FALSE) -> Ecole Nationale Supérieure de l'Electronique et de ses Applications (ENSEA) | BG38: =VLOOKUP(B38,'TEAMS_30-09-2021'!D:D,1,FALSE) -> Ecole Nationale Supérieure de l'Electronique et de ses Applications (ENSEA)
A39: 38 | B39: Telecom Sud Paris | C39: Télécom SudParis | D39: Evry (Paris) | E39: F EVRY11 | F39: FR | H39: 1 de abril (nomination) - 1 de mayo (application)- 1 de abril application DT | I39: 04.01 | J39: 05.01 | K39: 15 de octubre (nomination) - 1 de noviembre (application) | L39: 10.15 | M39: 11.01 | N39: ER | O39: Sí | P39: SÍ | Q39: SÍ | S39: Electrical Engineering (Electronics and Automation) / Computer Science ICTs | T39: Sí | U39: 2 | V39: 12 | W39: international@telecom-sudparis.eu | X39: Isabelle TOUFFET | Y39: SI | Z39: SI | AA39: NO | AB39: SI | AC39: SI | AD39: =_xlfn.TEXTJOIN("/",TRUE,IF(OfertaPlazas[[#This Row],[GITST]]="SI","GITST",""),IF(OfertaPlazas[[#This Row],[GIB]]="SI","GIB",""),IF(OfertaPlazas[[#This Row],[GISD]]="SI","GISD",""),IF(OfertaPlazas[[#This Row],[MASTER]]="SI","MASTER","")) -> GITST/GISD/MASTER | AE39: SI | AF39: SI | AG39: SI | AH39: SI | AI39: SI | AJ39: NO | AK39: SI | AL39: SI | AM39: NO | AN39: NO | AO39: SI | AP39: SI | AQ39: SI | AR39: NO | AS39: FRANCÉS B2 o INGLÉS B2 | AT39: INGLÉS B2 (TOEFL Ibt - 95; Cambridge CAE; IELTS - 7.00; Cambridge: CAE; TOEIC: 945) | AU39: Decidirán caso por caso la posibilidad de hacer TFG / Master of Engineering (in French or in English). /No pueden mezclar asignaturas de diferentes majors or Master of Science / No se puede coger asignaturas de diferentes cursos / TSP offers more than 11 Master’s programs fully in English. http://www.telecom-sudparis.eu/p_en_formations_ingenieur-generaliste_approfondissement_1054.html | AY39: Institucional | AZ39: 714 Electrical Engineering | BB39: Institutional coordinator: Ms Roisin Donhoe-roisin.donohoe@telecom-sudparis.eu/ Administrive contact: Ms Laura Landes-laura.landes@telecom-sudparis.eur | BC39: ETSIT | BD39: Acuerdo: 071 Engineering and Enginerring trades: Electrical Engineering | BE39: =VLOOKUP(B39,'TEAMS_30-09-2021'!$D:$AG,30,FALSE) -> 0 | BF39: =VLOOKUP(B39,'ENCUESTAS JUN-2021'!I:I,1,FALSE) -> Telecom Sud Paris | BG39: =VLOOKUP(B39,'TEAMS_30-09-2021'!D:D,1,FALSE) -> Telecom Sud Paris
A40: 39 | B40: Centrale SUPELEC | C40: CentraleSupélec | D40: Paris Saclay - Metz - Rennes | E40: F GIF-YVE03 | F40: FR | G40: 24 Meses para in and out | H40: Exchange programme: 22 de marzo (nomination) - 22 de abril (application) Double Degree programme: 15 de abril (nomination) - 15 de mayo (application) | I40: 03.22 | J40: 04.22 / 05.15 | K40: 10 de octubre (nomination) - 10 de noviembre (application) | L40: 10.10 | M40: 11.10 | N40: ER | P40: SÍ | R40: SÍ | S40: Electrical Engineering (Electronics and Automation) / Biomedical Engineering (Medical Diagnosticand Treatment Technology) | T40: Sí | U40: 6 | V40: 10 | W40: carine.morotti-delorme@centralesupelec.fr; julie.castel@centralesupelec.fr; marisol.verstraete@centralesupelec.fr | X40: Carine Morotti-Delorme (promotion); Julie Castel (exchange programs); Marisol Verstraete (DD incoming) | Y40: SI | Z40: SI | AA40: SI | AB40: NO | AC40: SI | AD40: =_xlfn.TEXTJOIN("/",TRUE,IF(OfertaPlazas[[#This Row],[GITST]]="SI","GITST",""),IF(OfertaPlazas[[#This Row],[GIB]]="SI","GIB",""),IF(OfertaPlazas[[#This Row],[GISD]]="SI","GISD",""),IF(OfertaPlazas[[#This Row],[MASTER]]="SI","MASTER","")) -> GITST/GIB/MASTER | AE40: SI | AF40: SI | AG40: SI | AH40: SI | AI40: SI | AJ40: SI | AK40: SI | AL40: SI | AM40: SI | AN40: SI | AO40: SI | AP40: SI | AQ40: SI | AR40: SI | AS40: FRANCÉS B1 o INGLÉS B2 | AU40: 3 students for the double degree programme (3 campus: Paris Saclay, Metz and Rennes) y 3 alumnos para programa de movilidad. For non degree students, the spring semester may be fully taught in English. Para exchange students, se puede escoger asignaturas de 2º curso en Centrale Supelec: https://www.centralesupelec.fr/sites/default/files/cat_2024_-_2a_-_en_v1.pdf. Nota media: minimum 7.0 | AY40: Institucional | AZ40: 714 Electrical Engineering | BB40: Institutional coordinator: Jocelyn Fiorina-jocelyn.fiorina@centralsupelec.fr /Admnistrtive contact: Ms Xaviére Marcy-xaviere.marcy@supelec.fr | BC40: ETSIT | BD40: Acuerdo: 714 Electrical & Telecom Engin | BE40: =VLOOKUP(B40,'TEAMS_30-09-2021'!$D:$AG,30,FALSE) -> 0 | BF40: =VLOOKUP(B40,'ENCUESTAS JUN-2021'!I:I,1,FALSE) -> Centrale SUPELEC | BG40: =VLOOKUP(B40,'TEAMS_30-09-2021'!D:D,1,FALSE) -> Centrale SUPELEC
A41: 40 | B41: INP Grenoble, Institute of Engineering and Management | C41: Grenoble INP - UGA | D41: Grenoble | E41: F GRENOBL22 | F41: FR | H41: 15 de abril | I41: 04.15 | J41: 04.15 | L41: 04.15 | N41: ER | P41: SÍ | S41: Electrical Engineering (Electronics and Automation) | T41: Sí | U41: 2 | V41: 12 | W41: international.welcomeservices@grenoble-inp.fr | X41: Runchen LIU | Y41: SI | Z41: SI | AA41: NO | AB41: NO | AC41: SI | AD41: =_xlfn.TEXTJOIN("/",TRUE,IF(OfertaPlazas[[#This Row],[GITST]]="SI","GITST",""),IF(OfertaPlazas[[#This Row],[GIB]]="SI","GIB",""),IF(OfertaPlazas[[#This Row],[GISD]]="SI","GISD",""),IF(OfertaPlazas[[#This Row],[MASTER]]="SI","MASTER","")) -> GITST/MASTER | AE41: SI | AF41: SI | AG41: SI | AH41: SI | AI41: SI | AJ41: NO | AK41: NO | AL41: SI | AM41: NO | AN41: NO | AO41: SI | AP41: SI | AQ41: SI | AR41: NO | AS41: FRANCÉS B1 o INGLÉS B2 | AU41: 1 alumno en el dpto. PHELMA, 2 alumnos en el dpto. ENSE3, 2 alumnos en el dpto. ENSIMAG | AW41: "En Phelma, todas las transcripciones de calificaciones se envían en versión digital, no las imprimimos ni las firmamos manualmente" | AY41: Institucional | AZ41: 714 Electrical Engineering | BB41: Administrateur General: Prof. Brigite PlateauI/International Office: Ms Virginie Klasser-virginie.klasser@grenoble-inp.fr | BC41: ETSIT | BD41: Acuerdo: 523 Electronic & Automation | BE41: =VLOOKUP(B41,'TEAMS_30-09-2021'!$D:$AG,30,FALSE) -> 0 | BF41: =VLOOKUP(B41,'ENCUESTAS JUN-2021'!I:I,1,FALSE) -> #N/A | BG41: =VLOOKUP(B41,'TEAMS_30-09-2021'!D:D,1,FALSE) -> INP Grenoble, Institute of Engineering and Management
A42: 41 | B42: Université Grenoble Alpes - UGA | C42: Université Grenoble Alpes | D42: Grenoble | E42: F GRENOBL55 | F42: FR | H42: 30 de abril (nomination) - 30 de mayo (application) | I42: 04.30 | J42: 05.30 | K42: 30 de septiembre (nomination) - 18 de octubre (application) | L42: 09.30 | M42: 10.18 | N42: ER | P42: SÍ | R42: SÍ | S42: Biomedical Engineering (Medical Diagnosticand Treatment Technology) / Electrical Engineering (Electronics and Automation) | T42: Sí | U42: 3 | V42: 12 | W42: partnerships@univ-grenoble-alpes.fr; valerie.guieu@univ-grenoble-alpes.fr; | X42: Pauline Aubry, Valérie Guieu | Y42: SI | Z42: SI | AA42: SI | AB42: NO | AC42: SI | AD42: =_xlfn.TEXTJOIN("/",TRUE,IF(OfertaPlazas[[#This Row],[GITST]]="SI","GITST",""),IF(OfertaPlazas[[#This Row],[GIB]]="SI","GIB",""),IF(OfertaPlazas[[#This Row],[GISD]]="SI","GISD",""),IF(OfertaPlazas[[#This Row],[MASTER]]="SI","MASTER","")) -> GITST/GIB/MASTER | AE42: SI | AF42: SI | AG42: SI | AH42: SI | AI42: SI | AJ42: SI | AK42: SI | AL42: SI | AM42: SI | AN42: SI | AO42: SI | AP42: SI | AQ42: SI | AR42: NO | AS42: FRANCÉS B2 o INGLÉS B2 | AT42: (certificado del departamento de lingüística aceptado) | AU42: Para MTiH, solo un semestre. Para estudiantes de MUIB y GIB: el acuerdo es con la facultad de farmacia de la UGA. Inglés para asignaturas de Máster. Although most of the courses are in French, our Faculty proposes course enterly in English in master 2 programs: http://formations.univ-grenoble-alpes.fr/fr/catalogue/master-XB/sciences-technologies-sante-STS/master-ingenierie-de-la-sante-program-master-ingenierie-de-la-sante.html?search-keywords=sant%E9 / 2nd cycle (máster) Mobility to UGA is only possible in the 1st semester. | BE42: =VLOOKUP(B42,'TEAMS_30-09-2021'!$D:$AG,30,FALSE) -> #N/A | BF42: =VLOOKUP(B42,'ENCUESTAS JUN-2021'!I:I,1,FALSE) -> #N/A | BG42: =VLOOKUP(B42,'TEAMS_30-09-2021'!D:D,1,FALSE) -> #N/A
A43: 42 | B43: HEC | C43: HEC School of Management | D43: Paris | E43: F JOUY-JO02 | F43: FR | G43: 24 Meses | H43: 27 de febrero (3rd round) | I43: 02.27 | J43: 02.27 | L43: 02.27 | N43: ER | P43: SÍ | S43: Electrical Engineering (Electronics and Automation) | T43: Sí | U43: 3 | V43: 12 | W43: admissionsmasters@hec.fr | X43: Zoey Crabb | Y43: NO | Z43: NO | AA43: NO | AB43: NO | AC43: SI | AD43: =_xlfn.TEXTJOIN("/",TRUE,IF(OfertaPlazas[[#This Row],[GITST]]="SI","GITST",""),IF(OfertaPlazas[[#This Row],[GIB]]="SI","GIB",""),IF(OfertaPlazas[[#This Row],[GISD]]="SI","GISD",""),IF(OfertaPlazas[[#This Row],[MASTER]]="SI","MASTER","")) -> MASTER | AE43: NO | AF43: NO | AG43: NO | AH43: NO | AI43: NO | AJ43: NO | AK43: NO | AL43: NO | AM43: NO | AN43: NO | AO43: NO | AP43: NO | AQ43: NO | AR43: SI | AS43: INGLÉS B2 o INGLÉS B1 + FRANCÉS A2 | AU43: Se abona matrícula para la DT | AV43: DT válido hasta 2021/2022 / Si los alumnos van a hacer fuera el gap year, deben solicitar la correspondiente aceptación y su inclusión en el PF. Es un cambio que deben hacer cuando ya están en destino. Es recomendable nominar al lumnado en el 3er round | BE43: =VLOOKUP(B43,'TEAMS_30-09-2021'!$D:$AG,30,FALSE) -> 0 | BF43: =VLOOKUP(B43,'ENCUESTAS JUN-2021'!I:I,1,FALSE) -> HEC | BG43: =VLOOKUP(B43,'TEAMS_30-09-2021'!D:D,1,FALSE) -> HEC | BL43: =VLOOKUP(E43,#REF!,1,FALSE) -> #REF!
A44: 43 | B44: Université des Sciences et Technologies de Lille - Polytech Lille | C44: Université de Lille | D44: Lille | E44: F LILLE103 | F44: FR | H44: 1 de mayo (nommination)- 10 de mayo (application) | I44: 05.01 | J44: 05.10 | K44: 15 de octubre (nommination) -1 de noviembre (application) | L44: 10.15 | M44: 11.01 | N44: ER | O44: Sí | P44: SÍ | Q44: Si | S44: Electrical Engineering (Electronics and Automation) | T44: Sí | U44: 3 | V44: 10 | W44: Blandine.Kowalski@polytech-lille.fr | X44: Blandine Kowalski | Y44: SI | Z44: SI | AA44: NO | AB44: SI | AC44: SI | AD44: =_xlfn.TEXTJOIN("/",TRUE,IF(OfertaPlazas[[#This Row],[GITST]]="SI","GITST",""),IF(OfertaPlazas[[#This Row],[GIB]]="SI","GIB",""),IF(OfertaPlazas[[#This Row],[GISD]]="SI","GISD",""),IF(OfertaPlazas[[#This Row],[MASTER]]="SI","MASTER","")) -> GITST/GISD/MASTER | AE44: SI | AF44: SI | AG44: SI | AH44: SI | AI44: SI | AJ44: SI | AK44: SI | AL44: SI | AM44: SI | AN44: SI | AO44: SI | AP44: SI | AQ44: SI | AR44: NO | AS44: FRANCÉS B1 o INGLÉS B1 | AU44: Polytech Lille: We recommend that students who intend to come for a study period of one semester apply for the autumn Semester. An important part of the Spring semester is dedicated to the industrial placement or to projects in laboratories (particularly during the fourth and fifth year). Students who come for the full academic year will combine study period with placements in research laboratories or in industry. The best period to carry out a project is from the beginning of February to the end of June // You cannot combine lectures from different engineering degree courses or semesters because of incompatible timetables. Master in English (para alumnado MUIT): INSPIRE (https://www.polytech-lille.fr/english/inspire/) INternational semester of Sustainable Practices, Innovation, Resilience and Energy. Master’s level, autumn semester only. | AV44: se añade el código 0610 en diciembre 2025 | BE44: =VLOOKUP(B44,'TEAMS_30-09-2021'!$D:$AG,30,FALSE) -> 0 | BF44: =VLOOKUP(B44,'ENCUESTAS JUN-2021'!I:I,1,FALSE) -> #N/A | BG44: =VLOOKUP(B44,'TEAMS_30-09-2021'!D:D,1,FALSE) -> Université des Sciences et Technologies de Lille - Polytech Lille | BL44: =VLOOKUP(E44,#REF!,1,FALSE) -> #REF!
A45: 44 | B45: Centrale Lille | C45: Centrale Lille Institut | D45: Lille | E45: F LILLE14 | F45: FR | G45: 24 Meses para in and out | H45: 15 de abril (nommination)- 30 de abril (application) | I45: 04.15 | J45: 04.30 | K45: 15 de octubre (nommination) -31 de octubre (application) | L45: 10.15 | M45: 10.31 | N45: ER | P45: SÍ | S45: Electrical Engineering (Electronics and Automation) | T45: Sí | U45: 2 | V45: 12 | W45: christophe.sueur@centralelille.fr ; international.mobility@centralelille.fr (for nomination & application purposes) | X45: Christophe Sueur | Y45: SI | Z45: SI | AA45: NO | AB45: NO | AC45: SI | AD45: =_xlfn.TEXTJOIN("/",TRUE,IF(OfertaPlazas[[#This Row],[GITST]]="SI","GITST",""),IF(OfertaPlazas[[#This Row],[GIB]]="SI","GIB",""),IF(OfertaPlazas[[#This Row],[GISD]]="SI","GISD",""),IF(OfertaPlazas[[#This Row],[MASTER]]="SI","MASTER","")) -> GITST/MASTER | AE45: SI | AF45: SI | AG45: SI | AH45: SI | AI45: SI | AJ45: SI | AK45: SI | AL45: SI | AM45: SI | AN45: SI | AO45: SI | AP45: SI | AQ45: SI | AR45: SI | AS45: FRANCÉS B1 o INGLÉS B1 | AU45: 3 students for the double degree programme | AY45: NUEVO! | BF45: =VLOOKUP(B45,'ENCUESTAS JUN-2021'!I:I,1,FALSE) -> Centrale Lille | BG45: =VLOOKUP(B45,'TEAMS_30-09-2021'!D:D,1,FALSE) -> Centrale Lille | BL45: =VLOOKUP(E45,#REF!,1,FALSE) -> #REF!
A46: 45 | B46: IMT Nord Europe | C46: IMT Lille Douai | D46: Lille | E46: F LILLE91 | F46: FR | H46: 30 de abril (nomination) - 31 de mayo (application) | I46: 04.30 | J46: 05.31 | L46: 04.30 | N46: ER | P46: SÍ | S46: Electrical Engineering (Electronics and Automation) | T46: Sí | U46: 1 | V46: 12 | W46: laurent.baudry@imt-lille-douai.fr | X46: Laurent Baudry | Y46: SI | Z46: SI | AA46: NO | AB46: NO | AC46: SI | AD46: =_xlfn.TEXTJOIN("/",TRUE,IF(OfertaPlazas[[#This Row],[GITST]]="SI","GITST",""),IF(OfertaPlazas[[#This Row],[GIB]]="SI","GIB",""),IF(OfertaPlazas[[#This Row],[GISD]]="SI","GISD",""),IF(OfertaPlazas[[#This Row],[MASTER]]="SI","MASTER","")) -> GITST/MASTER | AE46: SI | AF46: SI | AG46: SI | AH46: SI | AI46: SI | AJ46: SI | AK46: SI | AL46: SI | AM46: SI | AN46: SI | AO46: SI | AP46: SI | AQ46: SI | AR46: NO | AS46: FRANCÉS B1 o INGLÉS B1 | AU46: Posibilidad de cursar 30 ECTS en inglés en el 2ndo semestre en la especialidad Embedded Systems and Information Systems: http://imt-lille-douai.fr/formations/toutes-les-formations/semester-for-exchange-students/advanced-construction-materials-in-their-environment-acme/ Cybersecurity engineering: semestre de otoño se imparte totalmente en inglés | AY46: Institucional | AZ46: 714 Electrical Engineering | BB46: International Coordinator: Karine Kominiarz-karine.kominiarz@imt-lille-douai.fr | BC46: ESIT | BE46: =VLOOKUP(B46,'TEAMS_30-09-2021'!$D:$AG,30,FALSE) -> #N/A | BF46: =VLOOKUP(B46,'ENCUESTAS JUN-2021'!I:I,1,FALSE) -> #N/A | BG46: =VLOOKUP(B46,'TEAMS_30-09-2021'!D:D,1,FALSE) -> #N/A | BL46: =VLOOKUP(E46,#REF!,1,FALSE) -> #REF!
A47: 46 | B47: Université Claude Bernard Lyon 1 - Polytech Lyon | C47: Université Claude Bernard Lyon 1 | D47: Lyon | E47: F LYON01 | F47: FR | H47: 1 de mayo (nomination) - 30 de mayo (application) | I47: 05.01 | J47: 05.30 | K47: 1 de octubre (nomination) - 30 de octubre (application) | L47: 10.01 | M47: 10.30 | N47: ER | P47: SÍ | Q47: SÍ | R47: SÍ | S47: Electrical Engineering (Electronics and Automation) / Biomedical Engineering (Medical Diagnosticand Treatment Technology) / Computer Science ICTs | T47: Sí | U47: 1 | V47: 12 | W47: benedicte.marti@univ-lyon1.fr | X47: Bénédicte MARTI | Y47: SI | Z47: SI | AA47: SI | AB47: SI | AC47: SI | AD47: =_xlfn.TEXTJOIN("/",TRUE,IF(OfertaPlazas[[#This Row],[GITST]]="SI","GITST",""),IF(OfertaPlazas[[#This Row],[GIB]]="SI","GIB",""),IF(OfertaPlazas[[#This Row],[GISD]]="SI","GISD",""),IF(OfertaPlazas[[#This Row],[MASTER]]="SI","MASTER","")) -> GITST/GIB/GISD/MASTER | AE47: SI | AF47: SI | AG47: SI | AH47: SI | AI47: SI | AJ47: SI | AK47: SI | AL47: SI | AM47: SI | AN47: SI | AO47: SI | AP47: SI | AQ47: SI | AR47: NO | AS47: FRANCÉS B2 | AV47: nuevo acuerdo firmado junio 2022 | BL47: =VLOOKUP(E47,#REF!,1,FALSE) -> #REF!
A48: 47 | B48: Centrale Lyon | C48: Ecole Centrale Lyon | D48: Lyon | E48: F LYON11 | F48: FR | G48: 24 Meses para in and out | H48: 27 de marzo | I48: 03.27 | J48: 03.27 | K48: 30 de octubre | L48: 10.30 | M48: 10.30 | N48: ER | P48: SÍ | Q48: SÍ | R48: SÍ | S48: Electrical Engineering (Electronics and Automation) / Biomedical Engineering (Medical Diagnosticand Treatment Technology) / Computer Science ICTs | T48: Sí | U48: 2 | V48: 12 | W48: julia.esline@ec-lyon.fr | X48: Julia ESLINE | Y48: SI | Z48: SI | AA48: SI | AB48: SI | AC48: SI | AD48: =_xlfn.TEXTJOIN("/",TRUE,IF(OfertaPlazas[[#This Row],[GITST]]="SI","GITST",""),IF(OfertaPlazas[[#This Row],[GIB]]="SI","GIB",""),IF(OfertaPlazas[[#This Row],[GISD]]="SI","GISD",""),IF(OfertaPlazas[[#This Row],[MASTER]]="SI","MASTER","")) -> GITST/GIB/GISD/MASTER | AE48: SI | AF48: SI | AG48: SI | AH48: SI | AI48: SI | AJ48: SI | AK48: SI | AL48: SI | AM48: SI | AN48: SI | AO48: SI | AP48: SI | AQ48: SI | AR48: SI | AS48: FRANCÉS B1 o INGLÉS B2 | AT48: INGLÉS B2 (TOEFL 96 / TOEIC 825 / IELTS 7 / Cambridge 173 / Duolinguo 120) | AU48: 3 students for the double degree programme / Los alumnos deben tener 180 ECTS aprobados (mobilidad a partir de 4º curso) | AV48: nuevo acuerdo octubre 2022 | BL48: =VLOOKUP(E48,#REF!,1,FALSE) -> #REF!
A49: 48 | B49: INSA Lyon | C49: Institut National des Sciences Appliquées de Lyon | D49: Lyon | E49: F LYON12 | F49: FR | H49: 21 de abril (nomination) - 28 abril (application) | I49: 04.21 | J49: 04.28 | K49: 16 de octubre (nomination) - 27 de octubre (application) | L49: 10.16 | M49: 10.27 | N49: ER | P49: SÍ | Q49: SÍ | R49: SÍ | S49: Electrical Engineering (Electronics and Automation) / Biomedical Engineering (Medical Diagnosticand Treatment Technology) / Computer Science ICTs | T49: Sí | U49: 6 | V49: 10 | W49: welcome3@insa-lyon.fr | X49: Merve TEMEL/ Amina Bertrand | Y49: SI | Z49: SI | AA49: SI | AB49: SI | AC49: SI | AD49: =_xlfn.TEXTJOIN("/",TRUE,IF(OfertaPlazas[[#This Row],[GITST]]="SI","GITST",""),IF(OfertaPlazas[[#This Row],[GIB]]="SI","GIB",""),IF(OfertaPlazas[[#This Row],[GISD]]="SI","GISD",""),IF(OfertaPlazas[[#This Row],[MASTER]]="SI","MASTER","")) -> GITST/GIB/GISD/MASTER | AE49: SI | AF49: SI | AG49: SI | AH49: SI | AI49: SI | AJ49: NO | AK49: NO | AL49: SI | AM49: NO | AN49: NO | AO49: SI | AP49: SI | AQ49: SI | AR49: NO | AS49: FRANCÉS B1 o INGLÉS B2 | AU49: http://www.insa-lyon.fr/en/exchange-students / English course catalogue: https://www.insa-lyon.fr/en/information-science-technology-semester-ist 2 alumnos/as para teleco - 2 alumnos/as para bio - 2 alumnos/as para datos | AY49: Institucional | AZ49: 713 Electronics Engineering | BA49: Institutional Erasmus Coordinator: Dr Marie Pierre Favre: erasmus@insa-lyon.fr | BB49: Institutional Erasmus Coordinator: Dr Marie Pierre Favre: erasmus@insa-lyon.fr | BC49: UPM | BD49: Acuerdo: con ETSII:Electrical Engineering/ ETSInf: Computers Sciences | BE49: =VLOOKUP(B49,'TEAMS_30-09-2021'!$D:$AG,30,FALSE) -> se añade el área de bio 914 | BF49: =VLOOKUP(B49,'ENCUESTAS JUN-2021'!I:I,1,FALSE) -> #N/A | BG49: =VLOOKUP(B49,'TEAMS_30-09-2021'!D:D,1,FALSE) -> INSA Lyon | BL49: =VLOOKUP(E49,#REF!,1,FALSE) -> #REF!
A50: 49 | B50: Centrale Méditerranée | C50: Ecole Centrale Marseille | D50: Marseille | E50: F MARSEIL11 | F50: FR | G50: 24 Meses para in and out | H50: 1 de mayo | I50: 05.01 | J50: 05.01 | K50: 1 de diciembre | L50: 12.01 | M50: 12.01 | N50: ER | P50: SÍ | S50: Electrical Engineering (Electronics and Automation) | T50: Sí | U50: 2 | V50: 12 | W50: incoming@centrale-marseille.fr | X50: Ms. Séverine Lumeau | Y50: SI | Z50: SI | AA50: NO | AB50: NO | AC50: SI | AD50: =_xlfn.TEXTJOIN("/",TRUE,IF(OfertaPlazas[[#This Row],[GITST]]="SI","GITST",""),IF(OfertaPlazas[[#This Row],[GIB]]="SI","GIB",""),IF(OfertaPlazas[[#This Row],[GISD]]="SI","GISD",""),IF(OfertaPlazas[[#This Row],[MASTER]]="SI","MASTER","")) -> GITST/MASTER | AE50: SI | AF50: SI | AG50: SI | AH50: SI | AI50: SI | AJ50: SI | AK50: SI | AL50: SI | AM50: SI | AN50: SI | AO50: SI | AP50: SI | AQ50: SI | AR50: SI | AS50: FRANCÉS B1 | AU50: 3 students for the double degree programme | AV50: nuevo acuerdo octubre 2022 | BL50: =VLOOKUP(E50,#REF!,1,FALSE) -> #REF!
A51: 50 | B51: Université de Lorraine - École des Mines de Nancy - Telecom Nancy | C51: [no longer existing] Université de Lorraine | D51: Nancy | E51: F NANCY43 | F51: FR | H51: Mines Nancy 30 de marzo (nomination) 13 de abril (application) / Telecom Nancy 15 de mayo (nomination) 31 de mayo (application) | I51: 03.30 | J51: 04.13 | K51: Mines Nancy: 30 de octubre (nomination) 9 de noviembre (application) | L51: 10.30 | M51: 11.09 | N51: ER | P51: SÍ | Q51: Sí | R51: SÍ | S51: Electrical Engineering (Electronics and Automation) / Biomedical Engineering (Medical Diagnosticand Treatment Technology) / Computer Science ICTs | T51: Sí | U51: 6 | V51: 12 | W51: marie-christine.viry@univ-lorraine.fr | X51: Marie-Christine VIRY | Y51: SI | Z51: SI | AA51: SI | AB51: SI | AC51: SI | AD51: =_xlfn.TEXTJOIN("/",TRUE,IF(OfertaPlazas[[#This Row],[GITST]]="SI","GITST",""),IF(OfertaPlazas[[#This Row],[GIB]]="SI","GIB",""),IF(OfertaPlazas[[#This Row],[GISD]]="SI","GISD",""),IF(OfertaPlazas[[#This Row],[MASTER]]="SI","MASTER","")) -> GITST/GIB/GISD/MASTER | AE51: SI | AF51: SI | AG51: SI | AH51: SI | AI51: SI | AJ51: SI | AK51: SI | AL51: SI | AM51: SI | AN51: SI | AO51: SI | AP51: SI | AQ51: SI | AR51: NO | AS51: FRANCÉS B1 o INGLÉS B2 | AU51: 3 plazas para Telecom Nancy y 3 plazas para Écoles des Mines de Nancy. Écoles des Mines de Nancy: MSc in Security of Computer Systems and Big Data and Data Science : http://mines-nancy.univ-lorraine.fr/content/master-science-msc-security-computer-systems. http://www.mines-nancy.univ-lorraine.fr/node/242 Telecom Nancy: solo área 0610 (ICTs) para estudiantes de teleco y datos | AY51: Departamental | AZ51: 610 Computer Science/ 713 Electronics Engineering/ 714 Electrical Engineering/ 914 Biomedical Engineering | BA51: TELECOM - ECOLE DE MINES DE NANCY | BB51: TELECOM: Hervé Panetto, Head of Telecom's international relations: contact-international@telecommancy.eu/ ECOLE DES MINES DE NANCY: Dr. Alexandre Nominé, Directerur de L'action internationale: mines-nancy-dai@univ-lorraine.fr | BC51: ETSIT | BD51: Acuerdo: 0714 Electrical and Electronic Engineering | BE51: =VLOOKUP(B51,'TEAMS_30-09-2021'!$D:$AG,30,FALSE) -> 0 | BF51: =VLOOKUP(B51,'ENCUESTAS JUN-2021'!I:I,1,FALSE) -> Université de Lorraine - École des Mines de Nancy - Telecom Nancy | BG51: =VLOOKUP(B51,'TEAMS_30-09-2021'!D:D,1,FALSE) -> Université de Lorraine - École des Mines de Nancy - Telecom Nancy | BL51: =VLOOKUP(E51,#REF!,1,FALSE) -> #REF!
A52: 51 | B52: Université de Nantes - Polytech Nantes | C52: Nantes Université | D52: Nantes | E52: F NANTES01 | F52: FR | H52: 30 de abril (nomination ) 15 de mayo (application) | I52: 04.30 | J52: 05.15 | K52: 31 de octubre (nomination) - 15 de noviembre (application) | L52: 10.31 | M52: 11.15 | N52: ER | O52: SÍ | S52: Electrical Engineering (Electronics and Automation) | T52: Sí | U52: 1 | V52: 12 | W52: international.accueil@univ-nantes.fr | X52: international office | Y52: SI | Z52: SI | AA52: NO | AB52: NO | AC52: SI | AD52: =_xlfn.TEXTJOIN("/",TRUE,IF(OfertaPlazas[[#This Row],[GITST]]="SI","GITST",""),IF(OfertaPlazas[[#This Row],[GIB]]="SI","GIB",""),IF(OfertaPlazas[[#This Row],[GISD]]="SI","GISD",""),IF(OfertaPlazas[[#This Row],[MASTER]]="SI","MASTER","")) -> GITST/MASTER | AE52: SI | AF52: SI | AG52: SI | AH52: SI | AI52: SI | AJ52: SI | AK52: SI | AL52: SI | AM52: SI | AN52: NO | AO52: SI | AP52: SI | AQ52: SI | AR52: NO | AS52: FRANCÉS B1 o INGLÉS B2 | AU52: Se puede desdoblar el número de meses | AY52: Departamental | AZ52: Electricity and Energy (713) / Electronics and Automation (714) | BA52: Electrical Engineering | BB52: Mr Luc Loron (Departmental Coordinator) | BC52: firma: AA // UPM (varias Escuelas) | BE52: =VLOOKUP(B52,'TEAMS_30-09-2021'!$D:$AG,30,FALSE) -> 0 | BF52: =VLOOKUP(B52,'ENCUESTAS JUN-2021'!I:I,1,FALSE) -> #N/A | BG52: =VLOOKUP(B52,'TEAMS_30-09-2021'!D:D,1,FALSE) -> Université de Nantes - Polytech Nantes | BL52: =VLOOKUP(E52,#REF!,1,FALSE) -> #REF!
A53: 52 | B53: Centrale Nantes | C53: Ecole Centrale Nantes | D53: Nantes | E53: F NANTES07 | F53: FR | G53: 24 Meses para in and out | H53: 1 de mayo (nomination) - 15 de mayo (application) | I53: 05.01 | J53: 05.15 | K53: 15 de octubre (nomination) 30 de octubre (application) | L53: 10.15 | M53: 10.30 | N53: ER | P53: SÍ | R53: SÍ | S53: Electrical Engineering (Electronics and Automation) / Biomedical Engineering (Medical Diagnosticand Treatment Technology) | T53: Sí | U53: 1 | V53: 12 | W53: international@ec-nantes.fr | X53: Clémentine Houssais | Y53: SI | Z53: SI | AA53: SI | AB53: NO | AC53: SI | AD53: =_xlfn.TEXTJOIN("/",TRUE,IF(OfertaPlazas[[#This Row],[GITST]]="SI","GITST",""),IF(OfertaPlazas[[#This Row],[GIB]]="SI","GIB",""),IF(OfertaPlazas[[#This Row],[GISD]]="SI","GISD",""),IF(OfertaPlazas[[#This Row],[MASTER]]="SI","MASTER","")) -> GITST/GIB/MASTER | AE53: SI | AF53: SI | AG53: SI | AH53: SI | AI53: SI | AJ53: SI | AK53: SI | AL53: SI | AM53: SI | AN53: SI | AO53: SI | AP53: SI | AQ53: SI | AR53: SI | AS53: FRANCÉS B1 o INGLÉS B1 | AU53: 3 students for the double degree programme / Asignaturas de Master en inglés | AV53: 26/08/2024: se modifica plazas erasmus de 2 movilidades a 1 movilidad student | AY53: Institucional | AZ53: Electronic Engineering, Telecommunication (06.5 (523)) | BC53: firmas: AA + MPG | BE53: =VLOOKUP(B53,'TEAMS_30-09-2021'!$D:$AG,30,FALSE) -> #N/A | BF53: =VLOOKUP(B53,'ENCUESTAS JUN-2021'!I:I,1,FALSE) -> #N/A | BG53: =VLOOKUP(B53,'TEAMS_30-09-2021'!D:D,1,FALSE) -> #N/A | BL53: =VLOOKUP(E53,#REF!,1,FALSE) -> #REF!
A54: 53 | B54: IMT Atlantique | C54: IMT Atlantique | D54: Brest-Nantes-Rennes | E54: F NANTES80 | F54: FR | H54: 1 de mayo (nomination) - 15 de mayo (application) | I54: 05.15 | J54: 05.15 | K54: 1 de noviembre (nomination) - 15 de noviembre (application) | L54: 11.01 | M54: 11.15 | N54: ER | P54: SÍ | S54: Electrical Engineering (Electronics and Automation) | T54: Sí | U54: 5 | V54: 12 | W54: mob-out-europe@imt-atlantique.fr | X54: Françoise GUELENNOC | Y54: SI | Z54: SI | AA54: NO | AB54: NO | AC54: SI | AD54: =_xlfn.TEXTJOIN("/",TRUE,IF(OfertaPlazas[[#This Row],[GITST]]="SI","GITST",""),IF(OfertaPlazas[[#This Row],[GIB]]="SI","GIB",""),IF(OfertaPlazas[[#This Row],[GISD]]="SI","GISD",""),IF(OfertaPlazas[[#This Row],[MASTER]]="SI","MASTER","")) -> GITST/MASTER | AE54: SI | AF54: SI | AG54: SI | AH54: SI | AI54: SI | AJ54: NO | AK54: NO | AL54: SI | AM54: NO | AN54: NO | AO54: SI | AP54: SI | AQ54: SI | AR54: NO | AS54: FRANCÉS B1 o INGLÉS B2 | AY54: no está? | BE54: =VLOOKUP(B54,'TEAMS_30-09-2021'!$D:$AG,30,FALSE) -> 0 | BF54: =VLOOKUP(B54,'ENCUESTAS JUN-2021'!I:I,1,FALSE) -> #N/A | BG54: =VLOOKUP(B54,'TEAMS_30-09-2021'!D:D,1,FALSE) -> IMT Atlantique | BL54: =VLOOKUP(E54,#REF!,1,FALSE) -> #REF!
A55: 54 | B55: Institut d'Optique Théorique et Appliquée | C55: Institut d'Optique Théorique et Appliquée | D55: Palaiseau | E55: F ORSAY02 | F55: FR | H55: 15 de mayo | I55: 05.15 | J55: 05.15 | K55: 1 de octubre | L55: 10.01 | N55: ER | P55: SÍ | S55: Electrical Engineering (Electronics and Automation) | T55: Sí | U55: 2 | V55: 12 | W55: eirini.papagiannouli@institutoptique.fr | X55: Eirini Papagiannouli | Y55: SI | Z55: SI | AA55: NO | AB55: NO | AC55: SI | AD55: =_xlfn.TEXTJOIN("/",TRUE,IF(OfertaPlazas[[#This Row],[GITST]]="SI","GITST",""),IF(OfertaPlazas[[#This Row],[GIB]]="SI","GIB",""),IF(OfertaPlazas[[#This Row],[GISD]]="SI","GISD",""),IF(OfertaPlazas[[#This Row],[MASTER]]="SI","MASTER","")) -> GITST/MASTER | AE55: SI | AF55: SI | AG55: SI | AH55: SI | AI55: SI | AJ55: SI | AK55: SI | AL55: SI | AM55: SI | AN55: SI | AO55: SI | AP55: SI | AQ55: SI | AR55: NO | AS55: FRANCÉS B1 o FRANCÉS B2 o INGLÉS B2 | AV55: Se puede dividir el número de meses | AY55: Institucional | AZ55: Electrical and Electronics Engineering (714) | BC55: firmas: AA + LSA | BE55: =VLOOKUP(B55,'TEAMS_30-09-2021'!$D:$AG,30,FALSE) -> 0 | BF55: =VLOOKUP(B55,'ENCUESTAS JUN-2021'!I:I,1,FALSE) -> Institut d'Optique Théorique et Appliquée | BG55: =VLOOKUP(B55,'TEAMS_30-09-2021'!D:D,1,FALSE) -> Institut d'Optique Théorique et Appliquée | BL55: =VLOOKUP(E55,#REF!,1,FALSE) -> #REF!
A56: 55 | B56: ENSTA Paris | C56: Ecole Nationale Supérieure de Techniques Avancées | D56: Paris | E56: F PARIS080 | F56: FR | G56: 24 Meses | H56: 15 de abril (nomination- application) | I56: 04.15 | J56: 04.15 | K56: 31 de octubre | L56: 10.31 | N56: ER | P56: SÍ | S56: Electrical Engineering (Electronics and Automation) | T56: Sí | U56: 3 | V56: 12 | W56: annika.godefroy@ensta.fr | X56: Annika GODEFROY | Y56: SI | Z56: SI | AA56: NO | AB56: NO | AC56: SI | AD56: =_xlfn.TEXTJOIN("/",TRUE,IF(OfertaPlazas[[#This Row],[GITST]]="SI","GITST",""),IF(OfertaPlazas[[#This Row],[GIB]]="SI","GIB",""),IF(OfertaPlazas[[#This Row],[GISD]]="SI","GISD",""),IF(OfertaPlazas[[#This Row],[MASTER]]="SI","MASTER","")) -> GITST/MASTER | AE56: SI | AF56: SI | AG56: SI | AH56: SI | AI56: SI | AJ56: SI | AK56: SI | AL56: SI | AM56: SI | AN56: SI | AO56: SI | AP56: SI | AQ56: SI | AR56: SI | AS56: FRANCÉS B1 | AU56: Para TFG o TFM, una vez asignada la plaza, el alumno debe buscar un tutor | AV56: DT válido hasta 2019-2020 - Se puede dividir el número de meses | AY56: Institucional | AZ56: Electronics Engineering (523) | BC56: firma: AA // UPM (varias Escuelas) | BE56: =VLOOKUP(B56,'TEAMS_30-09-2021'!$D:$AG,30,FALSE) -> 0 | BF56: =VLOOKUP(B56,'ENCUESTAS JUN-2021'!I:I,1,FALSE) -> #N/A | BG56: =VLOOKUP(B56,'TEAMS_30-09-2021'!D:D,1,FALSE) -> ENSTA Paris | BL56: =VLOOKUP(E56,#REF!,1,FALSE) -> #REF!
A57: 56 | B57: Mines Paris - PSL University | C57: Ecole des Mines de Paris | D57: Paris | E57: F PARIS081 | F57: FR | H57: 15 abril (nomination )- 30 de abril (application) (exchange prog) | I57: 04.15 | J57: 04.30 | K57: 19 de septiembre(nomination)- 29 de septiembre (application) | L57: 09.19 | M57: 09.29 | N57: ER | P57: SÍ | Q57: SÍ | S57: Electrical Engineering (Electronics and Automation) / Computer Science ICTs | T57: Sí | U57: 2 | V57: 12 | W57: international@minesparis.psl.eu; cooperation@minesparis.psl.eu | X57: Manon Tissier, Victoire Hazoumé | Y57: SI | Z57: SI | AA57: NO | AB57: SI | AC57: SI | AD57: =_xlfn.TEXTJOIN("/",TRUE,IF(OfertaPlazas[[#This Row],[GITST]]="SI","GITST",""),IF(OfertaPlazas[[#This Row],[GIB]]="SI","GIB",""),IF(OfertaPlazas[[#This Row],[GISD]]="SI","GISD",""),IF(OfertaPlazas[[#This Row],[MASTER]]="SI","MASTER","")) -> GITST/GISD/MASTER | AE57: NO | AF57: NO | AG57: NO | AH57: SI | AI57: SI | AJ57: SI | AK57: SI | AL57: SI | AM57: SI | AN57: SI | AO57: SI | AP57: SI | AQ57: SI | AR57: SI | AS57: FRANCÉS B1 o INGLÉS B1 | AT57: FRANCÉS B1 (TEF (204); DELF (A2); TCF (200) or certificate from hom University) o INGLÉS B1 (TOEIC, TOEFL, Cambridge and those provided by partner universities). For Double Degree students, a B1 in French is required. | AU57: Para el Máster de Science and Executive Engineering se precisa Francés B1. No se puede solicitar para irse en 3er curso de grado. Para doble titulación: students have to choose a minor through their application and validate 120 ECTS (including 90 ECTS for courses, 6 ECTS for the compulsory internship and 24 ECTS for the minor final project) / forma parte de EELISA (Paris Sciences et Lettres - PSL) | AV57: DT válido hasta 2022-2023 / se va Alma Catalá abril 2024 / Se quita el área de bio /Se firma un joint degree en el marco de EELISA con ESPCI | AY57: Institucional | AZ57: Electrical and Telecommunications Engineering (06.5), Medical Technology (725) | BC57: firmas: AA + MPG | BE57: =VLOOKUP(B57,'TEAMS_30-09-2021'!$D:$AG,30,FALSE) -> #N/A | BF57: =VLOOKUP(B57,'ENCUESTAS JUN-2021'!I:I,1,FALSE) -> #N/A | BG57: =VLOOKUP(B57,'TEAMS_30-09-2021'!D:D,1,FALSE) -> #N/A
A58: 57 | B58: Telecom Paris | C58: TELECOM Paris | D58: Paris | E58: F PARIS083 | F58: FR | G58: 24 Meses | H58: 1 de abril (nomination) - 15 de abril (application) | I58: 04.01 | J58: 04.15 | K58: 1 de noviembre | L58: 11.01 | M58: 11.01 | N58: ER | P58: SÍ | Q58: SÍ | R58: SÍ | S58: Electrical Engineering: (Electricity and Energy); (Electronics and Automation) / Biomedical Engineering (Medical Diagnosticand TreatmentTechnology) / Computer Science ICTs | T58: Sí | U58: 3 | V58: 12 | W58: incoming@telecom-paris.fr | X58: international office | Y58: SI | Z58: SI | AA58: SI | AB58: SI | AC58: SI | AD58: =_xlfn.TEXTJOIN("/",TRUE,IF(OfertaPlazas[[#This Row],[GITST]]="SI","GITST",""),IF(OfertaPlazas[[#This Row],[GIB]]="SI","GIB",""),IF(OfertaPlazas[[#This Row],[GISD]]="SI","GISD",""),IF(OfertaPlazas[[#This Row],[MASTER]]="SI","MASTER","")) -> GITST/GIB/GISD/MASTER | AE58: NO | AF58: NO | AG58: NO | AH58: SI | AI58: SI | AJ58: SI | AK58: SI | AL58: SI | AM58: SI | AN58: SI | AO58: SI | AP58: SI | AQ58: SI | AR58: SI | AS58: FRANCÉS A2 o INGLÉS B2 | AT58: FRANCÉS A2 (Baccalaureat; TCF; TFI 255-400; DELF) o ENGLISH B2 (TOEFL; IELTS 5.5; TOEIC: 750; CAE) | AU58: Para alumnos de DT la nota media deberá ser mínimo 7.0. Solo se pueden elegir asignaturas que pertenecen al programa "Diplôme d'ingénieur" (Master of Science in Engineering). For non degree student, students must include a minimum of 20 ECTS per semester / Programas Internacionales VRI UPM 2026-27.pdf / No se puede ir en 3er curso | AV58: DT válido hasta 2018-19 / Claude Allafort, responsable incoming, se va de Telecom Paris en noviembre 2026 | AY58: Institucional | AZ58: Electronic, Computer, Information, Telecommunication, Telematics Engineering, Biomedical Engineering (713, 714, 914) | BC58: firmas: AA + MPG | BE58: =VLOOKUP(B58,'TEAMS_30-09-2021'!$D:$AG,30,FALSE) -> solicitan aumentar el nº de alumnos de 2 a 3. Estamos de acuerdo | BF58: =VLOOKUP(B58,'ENCUESTAS JUN-2021'!I:I,1,FALSE) -> Telecom Paris | BG58: =VLOOKUP(B58,'TEAMS_30-09-2021'!D:D,1,FALSE) -> Telecom Paris
A59: 58 | B59: ECE Engineering School | C59: Ecole Centrale d'Electronique | D59: Paris | E59: F PARIS222 | F59: FR | H59: 1 de mayo (nominatio) - 15 de mayo (application) | I59: 05.01 | J59: 05.15 | K59: 3 de octubre (nomination) - 10 de octubre (application) | L59: 10.03 | M59: 10.10 | N59: ER | P59: SÍ | Q59: SÍ | R59: SÍ | S59: Electrical Engineering (Electronics and Automation) / Biomedical Engineering (Medical Diagnosticand Treatment Technology) / Computer Science ICTs | T59: Sí | U59: 2 | V59: 10 | W59: international@ece.fr; fmahe@ece.fr | X59: François Mahé | Y59: SI | Z59: SI | AA59: SI | AB59: SI | AC59: SI | AD59: =_xlfn.TEXTJOIN("/",TRUE,IF(OfertaPlazas[[#This Row],[GITST]]="SI","GITST",""),IF(OfertaPlazas[[#This Row],[GIB]]="SI","GIB",""),IF(OfertaPlazas[[#This Row],[GISD]]="SI","GISD",""),IF(OfertaPlazas[[#This Row],[MASTER]]="SI","MASTER","")) -> GITST/GIB/GISD/MASTER | AE59: SI | AF59: NO | AG59: SI | AH59: SI | AI59: NO | AJ59: SI | AK59: NO | AL59: SI | AM59: SI | AN59: NO | AO59: SI | AP59: SI | AQ59: NO | AR59: NO | AS59: FRANCÉS B1 o INGLÉS B2 | AT59: INGLÉS B2 (IELTS 6.0; TOEFL 83; TOEIC 780) | AU59: Se puede solicitar para un curso completo o 1er semestre | AV59: nuevo acuerdo firmado en febrero 2022
A60: 59 | B60: Sorbonne Université | C60: Sorbonne Université | D60: Paris | E60: F PARIS468 | F60: FR | H60: 30 de abril | I60: 04.30 | J60: 04.30 | K60: 15 de mayo | L60: 05.15 | N60: ER/EIT HEALTH | P60: SÍ | R60: SÍ | S60: Electrical Engineering (Electronics and Automation) / Biomedical Engineering (Medical Diagnosticand Treatment Technology) | T60: Sí | U60: 5 | V60: 6 | W60: erasmus@upmc.fr | X60: Christine Ozouf | Y60: SI | Z60: SI | AA60: SI | AB60: NO | AC60: SI | AD60: =_xlfn.TEXTJOIN("/",TRUE,IF(OfertaPlazas[[#This Row],[GITST]]="SI","GITST",""),IF(OfertaPlazas[[#This Row],[GIB]]="SI","GIB",""),IF(OfertaPlazas[[#This Row],[GISD]]="SI","GISD",""),IF(OfertaPlazas[[#This Row],[MASTER]]="SI","MASTER","")) -> GITST/GIB/MASTER | AE60: SI | AF60: SI | AG60: SI | AH60: SI | AI60: SI | AJ60: SI | AK60: SI | AL60: SI | AM60: SI | AN60: SI | AO60: SI | AP60: SI | AQ60: SI | AR60: NO | AS60: INGLÉS B2 o FRANCÉS B1 | AT60: INGLÉS B2 (aceptan el certificado del departamento de lingüística) | AU60: PRIORIDAD ALUMNOS PROGRAMA EIT HEALTH | AV60: Se pueden juntar los meses | AY60: no está? | BE60: =VLOOKUP(B60,'TEAMS_30-09-2021'!$D:$AG,30,FALSE) -> 0 | BF60: =VLOOKUP(B60,'ENCUESTAS JUN-2021'!I:I,1,FALSE) -> Sorbonne Université | BG60: =VLOOKUP(B60,'TEAMS_30-09-2021'!D:D,1,FALSE) -> Sorbonne Université
A61: 60 | B61: Université de Strasbourg - Telecom physique | C61: Université de Strasbourg | D61: Strasbourg | E61: F STRASBO48 | F61: FR | H61: 4 de mayo (nomination) - 10 de mayo (application) | I61: 05.04 | J61: 05.10 | K61: 2 de noviembre (nomination) - 15 de noviembre (application) | L61: 11.02 | M61: 11.15 | N61: ER | P61: SÍ | Q61: SÍ | R61: SÍ | S61: Electrical Engineering (Electronics and Automation) / Biomedical Engineering (Medical Diagnosticand Treatment Technology) / Computer Science ICTs | T61: Sí | U61: 6 | V61: 10 | W61: dri-europe-incoming-students@unistra.fr | X61: Alicia KAEMMERLE | Y61: SI | Z61: SI | AA61: SI | AB61: SI | AC61: SI | AD61: =_xlfn.TEXTJOIN("/",TRUE,IF(OfertaPlazas[[#This Row],[GITST]]="SI","GITST",""),IF(OfertaPlazas[[#This Row],[GIB]]="SI","GIB",""),IF(OfertaPlazas[[#This Row],[GISD]]="SI","GISD",""),IF(OfertaPlazas[[#This Row],[MASTER]]="SI","MASTER","")) -> GITST/GIB/GISD/MASTER | AE61: SI | AF61: SI | AG61: SI | AH61: SI | AI61: SI | AJ61: SI | AK61: SI | AL61: SI | AM61: SI | AN61: SI | AO61: SI | AP61: SI | AQ61: SI | AR61: NO | AS61: FRANCÉS B1 o INGLÉS B2 | AV61: nuevo acuerdo 2024
A62: 61 | B62: École Nationale d'Ingénieurs de Tarbes | C62: Ecole Nationale d'Ingénieurs de Tarbes | D62: Tarbes | E62: F TARBES03 | F62: FR | H62: 15 de mayo | I62: 05.15 | J62: 05.15 | K62: 15 de diciembre | L62: 12.15 | N62: ER | P62: SÍ | S62: Electrical Engineering (Electronics and Automation) | T62: Sí | U62: 1 | V62: 12 | W62: dridir@enit.fr | X62: Carmen Martin | Y62: SI | Z62: SI | AA62: NO | AB62: NO | AC62: SI | AD62: =_xlfn.TEXTJOIN("/",TRUE,IF(OfertaPlazas[[#This Row],[GITST]]="SI","GITST",""),IF(OfertaPlazas[[#This Row],[GIB]]="SI","GIB",""),IF(OfertaPlazas[[#This Row],[GISD]]="SI","GISD",""),IF(OfertaPlazas[[#This Row],[MASTER]]="SI","MASTER","")) -> GITST/MASTER | AE62: SI | AF62: SI | AG62: SI | AH62: SI | AI62: SI | AJ62: NO | AK62: NO | AL62: NO | AM62: NO | AN62: SI | AO62: SI | AP62: NO | AQ62: SI | AR62: NO | AS62: FRANCÉS B1 o INGLÉS B1 | AY62: Institucional | AZ62: Electronic Engineering (714 (523)) | BC62: firma: AA // UPM (varias Escuelas) | BE62: =VLOOKUP(B62,'TEAMS_30-09-2021'!$D:$AG,30,FALSE) -> 0 | BF62: =VLOOKUP(B62,'ENCUESTAS JUN-2021'!I:I,1,FALSE) -> #N/A | BG62: =VLOOKUP(B62,'TEAMS_30-09-2021'!D:D,1,FALSE) -> École Nationale d'Ingénieurs de Tarbes
A63: 62 | B63: Institut National des Sciences Appliquées de Toulouse INSA Toulouse | C63: Institut National des Sciences Appliquees de Toulouse | D63: Toulouse | E63: F TOULOUS14 | F63: FR | H63: 28 de marzo (nomination) - 10 de abril (application) | I63: 03.28 | J63: 04.10 | K63: 7 de noviembre (nomination) - 10 de noviembre (application) | L63: 11.07 | M63: 11.10 | N63: ER | O63: SÍ | P63: SÍ | S63: Electrical Engineering: (Electricity and Energy); (Electronics and Automation) | T63: Sí | U63: 2 | V63: 12 | W63: relint.incoming@insa-toulouse.fr | X63: international office | Y63: SI | Z63: SI | AA63: NO | AB63: NO | AC63: SI | AD63: =_xlfn.TEXTJOIN("/",TRUE,IF(OfertaPlazas[[#This Row],[GITST]]="SI","GITST",""),IF(OfertaPlazas[[#This Row],[GIB]]="SI","GIB",""),IF(OfertaPlazas[[#This Row],[GISD]]="SI","GISD",""),IF(OfertaPlazas[[#This Row],[MASTER]]="SI","MASTER","")) -> GITST/MASTER | AE63: SI | AF63: SI | AG63: SI | AH63: SI | AI63: SI | AJ63: SI | AK63: SI | AL63: SI | AM63: SI | AN63: SI | AO63: SI | AP63: SI | AQ63: SI | AR63: SI | AS63: FRANCÉS B1 o INGLÉS B1 | AU63: Asignaturas principalmente en francés excepto algunos Master y asignaturas de grado del 2º semestre. http://www.insa-toulouse.fr/en/international/studying-at-insa-toulouse/programmes_in_english.html / DT (Diplôme d'ingénieur de l'INSA Toulouse) con 2 opciones: 1. 4º curso de grado + 2º de MUIT o 2. 2º curso de MUIT (2 años) | AV63: Para DT: 3 alumnos DT // En diciembre del 2025 nos comentó un alumno de DT que si se supende una asignatura en destino te hacen repetir todas las asignaturas el curso siguiente. | AY63: Departamental | AZ63: Electricity and Energy (713) / Electronics and Automation (714) | BA63: (no se indica) | BB63: Pierre-Emmanuel Hladik (Departmental Coordinator) | BC63: firmas: AA + MPG | BE63: =VLOOKUP(B63,'TEAMS_30-09-2021'!$D:$AG,30,FALSE) -> 0 | BF63: =VLOOKUP(B63,'ENCUESTAS JUN-2021'!I:I,1,FALSE) -> #N/A | BG63: =VLOOKUP(B63,'TEAMS_30-09-2021'!D:D,1,FALSE) -> Institut National des Sciences Appliquées de Toulouse INSA Toulouse
A64: 63 | B64: ISAE-SUPAERO | C64: Institut Supérieur de l’Aéronautique et de l’Espace (ISAE-SUPAERO) | D64: Toulouse | E64: F TOULOUS16 | F64: FR | G64: 24 Meses | H64: 1 de abril (nomination) - 15 de abril (application) | I64: 04.01 | J64: 04.15 | K64: 1 de octubre (nomination)-15 de octubre (application) | L64: 10.01 | M64: 10.15 | N64: ER | P64: SÍ | S64: Electrical Engineering (Electronics and Automation) | T64: Sí | U64: 2 | V64: 12 | W64: admission-ingenieur@isae-supaero.fr; outgoing.df@isae-supaero.fr; international@isae-supaero.fr | X64: international office | Y64: SI | Z64: SI | AA64: NO | AB64: NO | AC64: SI | AD64: =_xlfn.TEXTJOIN("/",TRUE,IF(OfertaPlazas[[#This Row],[GITST]]="SI","GITST",""),IF(OfertaPlazas[[#This Row],[GIB]]="SI","GIB",""),IF(OfertaPlazas[[#This Row],[GISD]]="SI","GISD",""),IF(OfertaPlazas[[#This Row],[MASTER]]="SI","MASTER","")) -> GITST/MASTER | AE64: SI | AF64: SI | AG64: SI | AH64: SI | AI64: NO | AJ64: SI | AK64: NO | AL64: SI | AM64: SI | AN64: SI | AO64: SI | AP64: SI | AQ64: SI | AR64: SI | AS64: FRANCÉS B1 | AT64: JUNTO CON Inglés B2 para alumnos DT | AU64: Para alumnos de grado, no es posible realizar asignaturas en el 2ndo semestre. Para alumnos de DT, es posible realizar asignaturas durante todo el año académico. La DT (4 semestres) se puede empezar en el segundo curso de MUIT o 4º de GITST (+ 2ndo de MUIT) | AV64: DT renovado en octubre 2020 válido hasta 2024/25 | AY64: Institucional | AZ64: Engineering & Engineering Trades (071) | BC64: firmas: AA + MPG | BE64: =VLOOKUP(B64,'TEAMS_30-09-2021'!$D:$AG,30,FALSE) -> ok | BF64: =VLOOKUP(B64,'ENCUESTAS JUN-2021'!I:I,1,FALSE) -> ISAE-SUPAERO | BG64: =VLOOKUP(B64,'TEAMS_30-09-2021'!D:D,1,FALSE) -> ISAE-SUPAERO
A65: 64 | B65: ENSICA | C65: Institut Supérieur de l’Aéronautique et de l’Espace (ISAE-SUPAERO) | D65: Toulouse | E65: F TOULOUS17 | F65: FR | H65: 15 de marzo (preincripción online) | I65: 03.15 | J65: 03.15 | K65: 30 de abril(nomination) | L65: 03.15 | N65: ER | P65: SÍ | S65: Electrical Engineering (Electronics and Automation) | T65: Sí | U65: 1 | V65: 12 | W65: chantal.dabrainville@isae.fr | X65: Chantal Dabrainville | Y65: SI | Z65: SI | AA65: NO | AB65: NO | AC65: SI | AD65: =_xlfn.TEXTJOIN("/",TRUE,IF(OfertaPlazas[[#This Row],[GITST]]="SI","GITST",""),IF(OfertaPlazas[[#This Row],[GIB]]="SI","GIB",""),IF(OfertaPlazas[[#This Row],[GISD]]="SI","GISD",""),IF(OfertaPlazas[[#This Row],[MASTER]]="SI","MASTER","")) -> GITST/MASTER | AE65: SI | AF65: SI | AG65: SI | AH65: SI | AI65: SI | AJ65: SI | AK65: SI | AL65: SI | AM65: SI | AN65: SI | AO65: SI | AP65: SI | AQ65: SI | AR65: NO | AS65: FRANCÉS B1 | AY65: Institucional | AZ65: Engineering & Engineering Trades (071) | BC65: firmas: AA + MPG | BE65: =VLOOKUP(B65,'TEAMS_30-09-2021'!$D:$AG,30,FALSE) -> ok | BF65: =VLOOKUP(B65,'ENCUESTAS JUN-2021'!I:I,1,FALSE) -> #N/A | BG65: =VLOOKUP(B65,'TEAMS_30-09-2021'!D:D,1,FALSE) -> Ensica
A66: 65 | B66: INPT Inst. Nat. Polytechnique de Toulouse ENSEEIHT | C66: Institut National Polytechnique de Toulouse | D66: Toulouse | E66: F TOULOUS28 | F66: FR | H66: 7 de abril (nomination) - 1 de mayo (application) | I66: 04.07 | J66: 05.01 | K66: 30 de octubre (nomination) 15 de noviembre (application) | L66: 10.30 | M66: 11.15 | N66: ER | P66: SÍ | S66: Electrical Engineering (Electronics and Automation) | T66: Sí | U66: 4 | V66: 12 | W66: international.enseeiht@toulouse-inp.fr; isabelle.simon@toulouse-inp.fr | X66: Isabelle SIMON | Y66: SI | Z66: SI | AA66: NO | AB66: NO | AC66: SI | AD66: =_xlfn.TEXTJOIN("/",TRUE,IF(OfertaPlazas[[#This Row],[GITST]]="SI","GITST",""),IF(OfertaPlazas[[#This Row],[GIB]]="SI","GIB",""),IF(OfertaPlazas[[#This Row],[GISD]]="SI","GISD",""),IF(OfertaPlazas[[#This Row],[MASTER]]="SI","MASTER","")) -> GITST/MASTER | AE66: SI | AF66: SI | AG66: SI | AH66: SI | AI66: SI | AJ66: SI | AK66: SI | AL66: SI | AM66: SI | AN66: SI | AO66: SI | AP66: SI | AQ66: SI | AR66: SI | AS66: INGLÉS B2 O FRANCÉS B1 | AU66: No aparece la calificación oficial del TFT en el transcript of records. Para DT el Master es Electronic systems for embedded communications and applications (en inglés) / courses catalogue: http://www.enseeiht.fr/fr/formation/formation-ingenieur-1/etudiant-1a-ou-2a.html / OJO: Un alumno de movilidad no puede realizar unas prácticas en una emprea extrerna, unicamente en un laboratorio de la ENSEEIHT. Esta norma no se aplica a alumnos de doble titulación / Posibilidad de hacer Máster ESECA de 1 año: tuition fees 5000€ / DT se puede empezar en el 4º curso GITST (no es el ESECA) | AV66: DT renovado en junio 2019 válido hasta 2023/24 | AY66: Institucional | AZ66: Electronics-Telecommunications (523) | BC66: firmas: AA + MPG | BE66: =VLOOKUP(B66,'TEAMS_30-09-2021'!$D:$AG,30,FALSE) -> 0 | BF66: =VLOOKUP(B66,'ENCUESTAS JUN-2021'!I:I,1,FALSE) -> #N/A | BG66: =VLOOKUP(B66,'TEAMS_30-09-2021'!D:D,1,FALSE) -> INPT Inst. Nat. Polytechnique de Toulouse ENSEEIHT
A67: 66 | B67: INSA - Université Polytechnique Hauts-de-France UPHF (GRADO) | C67: Université Polytechnique Hauts-de-France | D67: Valenciennes | E67: F VALENCI01 | F67: FR | H67: 15 de mayo (nomination) - 31 de mayo (application) | I67: 05.15 | J67: 05.31 | K67: 15 de noviembre (nomination) - 30 de noviembre (application) | L67: 11.15 | M67: 11.30 | N67: ER | P67: SÍ | Q67: SÍ | S67: Electrical Engineering (Electronics and Automation) / Computer Science ICTs | T67: Sí | U67: 2 | V67: 12 | W67: erasmus@uphf.fr | X67: Estelle Le Meur | Y67: SI | Z67: SI | AA67: NO | AB67: SI | AC67: NO | AD67: =_xlfn.TEXTJOIN("/",TRUE,IF(OfertaPlazas[[#This Row],[GITST]]="SI","GITST",""),IF(OfertaPlazas[[#This Row],[GIB]]="SI","GIB",""),IF(OfertaPlazas[[#This Row],[GISD]]="SI","GISD",""),IF(OfertaPlazas[[#This Row],[MASTER]]="SI","MASTER","")) -> GITST/GISD | AE67: SI | AF67: SI | AG67: SI | AH67: SI | AI67: SI | AJ67: SI | AK67: SI | AL67: SI | AM67: SI | AN67: SI | AO67: NO | AP67: NO | AQ67: NO | AR67: NO | AS67: FRANCÉS B1 o INGLÉS B1 | AU67: Bachelor https://formations.uphf.fr/cdm/cursus/licence3 | AV67: acuerdo erasmus para bachelor degree students | AY67: Departamental | AZ67: Engineering & Engineering Trades (071), Electrical Engineering (714) | BA67: (no se indica) | BB67: Pr. Dominique Deneux (Departmental Coordinator) | BC67: firmas: AA + LSA | BE67: =VLOOKUP(B67,'TEAMS_30-09-2021'!$D:$AG,30,FALSE) -> #N/A | BF67: =VLOOKUP(B67,'ENCUESTAS JUN-2021'!I:I,1,FALSE) -> #N/A | BG67: =VLOOKUP(B67,'TEAMS_30-09-2021'!D:D,1,FALSE) -> #N/A
A68: 67 | B68: INSA - Université Polytechnique Hauts-de-France UPHF (MASTER) | C68: Université Polytechnique Hauts-de-France | D68: Valenciennes | E68: F VALENCI21 | F68: FR | H68: 15 de mayo (nomination) - 31 de mayo (application) | I68: 05.15 | J68: 05.31 | K68: 1 de noviembre (nomination) - 15 de noviembre (application) | L68: 11.01 | M68: 11.15 | N68: ER | P68: SÍ | Q68: SÍ | S68: Electrical Engineering (Electronics and Automation) / Computer Science ICTs | T68: Sí | U68: 2 | V68: 12 | W68: erasmus@uphf.fr | X68: Estelle Le Meur | Y68: NO | Z68: NO | AA68: NO | AB68: NO | AC68: SI | AD68: =_xlfn.TEXTJOIN("/",TRUE,IF(OfertaPlazas[[#This Row],[GITST]]="SI","GITST",""),IF(OfertaPlazas[[#This Row],[GIB]]="SI","GIB",""),IF(OfertaPlazas[[#This Row],[GISD]]="SI","GISD",""),IF(OfertaPlazas[[#This Row],[MASTER]]="SI","MASTER","")) -> MASTER | AE68: NO | AF68: NO | AG68: NO | AH68: NO | AI68: NO | AJ68: NO | AK68: NO | AL68: NO | AM68: NO | AN68: NO | AO68: SI | AP68: SI | AQ68: SI | AR68: NO | AS68: FRANCÉS B1 o INGLÉS B1 | AU68: Master: https://formations.uphf.fr/cdm/cursus/master | AV68: acuerdo erasmus para master degree students | BL68: =VLOOKUP(E68,#REF!,1,FALSE) -> #REF!
A69: 68 | B69: University of West Attica | C69: University of West Attica | D69: Egaleo-Athina | E69: G EGALEO02 | F69: GR | H69: 31 de mayo | I69: 05.31 | J69: 05.31 | L69: 05.31 | N69: ER | R69: SÍ | S69: Biomedical Engineering (Medical Diagnosticand Treatment Technology) | T69: Sí | U69: 2 | V69: 12 | W69: erasmus_incomingstudents@uniwa.gr | X69: Nefeli Koniordou, Georgia Douma, Chrysa Konti | Y69: SI | Z69: NO | AA69: SI | AB69: NO | AC69: SI | AD69: =_xlfn.TEXTJOIN("/",TRUE,IF(OfertaPlazas[[#This Row],[GITST]]="SI","GITST",""),IF(OfertaPlazas[[#This Row],[GIB]]="SI","GIB",""),IF(OfertaPlazas[[#This Row],[GISD]]="SI","GISD",""),IF(OfertaPlazas[[#This Row],[MASTER]]="SI","MASTER","")) -> GIB/MASTER | AE69: SI | AF69: SI | AG69: SI | AH69: SI | AI69: SI | AJ69: NO | AK69: NO | AL69: SI | AM69: NO | AN69: NO | AO69: SI | AP69: SI | AQ69: SI | AR69: NO | AS69: INGLÉS B2 | AU69: https://erasmus.uniwa.gr/en/erasmus/course-catalogue/ ; https://erasmus.uniwa.gr/wp-content/uploads/sites/159/2021/02/FACT-SHEET-UNIWA.pd | AV69: El TFG no se hace porque es de 30 ECTS | BE69: =VLOOKUP(B69,'TEAMS_30-09-2021'!$D:$AG,30,FALSE) -> #N/A | BF69: =VLOOKUP(B69,'ENCUESTAS JUN-2021'!I:I,1,FALSE) -> #N/A | BG69: =VLOOKUP(B69,'TEAMS_30-09-2021'!D:D,1,FALSE) -> #N/A | BL69: =VLOOKUP(E69,#REF!,1,FALSE) -> #REF!
A70: 69 | B70: Politecnico di Bari | C70: Politecnico di Bari | D70: Bari | E70: I BARI05 | F70: IT | H70: 15 de junio | I70: 06.15 | J70: 06.15 | L70: 06.15 | N70: ER | P70: SÍ | S70: Electrical Engineering (Electronics and Automation) | T70: Sí | U70: 2 | V70: 12 | W70: luisa.nasta@poliba.it; rosilda.sammarco@poliba.it | X70: Luisa Nasta; Rosilda Sammarco | Y70: SI | Z70: SI | AA70: NO | AB70: NO | AC70: SI | AD70: =_xlfn.TEXTJOIN("/",TRUE,IF(OfertaPlazas[[#This Row],[GITST]]="SI","GITST",""),IF(OfertaPlazas[[#This Row],[GIB]]="SI","GIB",""),IF(OfertaPlazas[[#This Row],[GISD]]="SI","GISD",""),IF(OfertaPlazas[[#This Row],[MASTER]]="SI","MASTER","")) -> GITST/MASTER | AE70: SI | AF70: SI | AG70: SI | AH70: SI | AI70: SI | AJ70: SI | AK70: SI | AL70: SI | AM70: SI | AN70: SI | AO70: SI | AP70: SI | AQ70: SI | AR70: NO | AS70: ITALIANO B1 | BE70: =VLOOKUP(B70,'TEAMS_30-09-2021'!$D:$AG,30,FALSE) -> 0 | BF70: =VLOOKUP(B70,'ENCUESTAS JUN-2021'!I:I,1,FALSE) -> #N/A | BG70: =VLOOKUP(B70,'TEAMS_30-09-2021'!D:D,1,FALSE) -> Politecnico di Bari | BL70: =VLOOKUP(E70,#REF!,1,FALSE) -> #REF!
A71: 70 | B71: Università degli Studi di Cagliari | C71: Università degli Studi di Cagliari | D71: Cagliari | E71: I CAGLIAR01 | F71: IT | H71: 30 de junio | I71: 06.30 | J71: 06.30 | K71: 31 de octubre | L71: 10.31 | M71: 10.31 | N71: ER | P71: Sí | Q71: Si | R71: SÍ | S71: Electrical Engineering (Electronics and Automation) / Biomedical Engineering (Medical Diagnosticand Treatment Technology) / Computer Science (Information and CommunicationTechnologies) | T71: Sí | U71: 2 | V71: 10 | W71: erasmus@unica.it | X71: Anna Maria Aloi | Y71: SI | Z71: SI | AA71: SI | AB71: SI | AC71: SI | AD71: =_xlfn.TEXTJOIN("/",TRUE,IF(OfertaPlazas[[#This Row],[GITST]]="SI","GITST",""),IF(OfertaPlazas[[#This Row],[GIB]]="SI","GIB",""),IF(OfertaPlazas[[#This Row],[GISD]]="SI","GISD",""),IF(OfertaPlazas[[#This Row],[MASTER]]="SI","MASTER","")) -> GITST/GIB/GISD/MASTER | AE71: SI | AF71: SI | AG71: SI | AH71: SI | AI71: SI | AJ71: SI | AK71: SI | AL71: SI | AM71: SI | AN71: SI | AO71: SI | AP71: SI | AQ71: SI | AR71: NO | AS71: INGLÉS B2
A72: 71 | B72: Università degli Studi di Firenze | C72: Università degli Studi di Firenze | D72: Florencia | E72: I FIRENZE01 | F72: IT | H72: 31 de mayo (nomination) - 30 de junio (application) | I72: 05.31 | J72: 06.30 | K72: 31 de octubre (nomination) - 30 de noviembre (application) | L72: 10.31 | M72: 11.30 | N72: ER | P72: SÍ | R72: SÍ | S72: Electrical Engineering (Electronics and Automation) / Biomedical Engineering (Medical Diagnosticand Treatment Technology) | T72: Sí | U72: 2 | V72: 12 | W72: international@ingegneria.unifi.it | X72: Laura Galli | Y72: SI | Z72: SI | AA72: NO | AB72: NO | AC72: SI | AD72: =_xlfn.TEXTJOIN("/",TRUE,IF(OfertaPlazas[[#This Row],[GITST]]="SI","GITST",""),IF(OfertaPlazas[[#This Row],[GIB]]="SI","GIB",""),IF(OfertaPlazas[[#This Row],[GISD]]="SI","GISD",""),IF(OfertaPlazas[[#This Row],[MASTER]]="SI","MASTER","")) -> GITST/MASTER | AE72: SI | AF72: SI | AG72: SI | AH72: SI | AI72: SI | AJ72: SI | AK72: SI | AL72: SI | AM72: SI | AN72: SI | AO72: SI | AP72: SI | AQ72: SI | AR72: NO | AS72: ITALIANO B1 o INGLÉS B2 | AU72: La defensa del TFG se realizará en la ETSIT respetando su normativa y proceso de matriculación. | AV72: Se puede dividir el número de meses | BE72: =VLOOKUP(B72,'TEAMS_30-09-2021'!$D:$AG,30,FALSE) -> 0 | BF72: =VLOOKUP(B72,'ENCUESTAS JUN-2021'!I:I,1,FALSE) -> #N/A | BG72: =VLOOKUP(B72,'TEAMS_30-09-2021'!D:D,1,FALSE) -> Università degli Studi di Firenze
A73: 72 | B73: Politecnico di Milano | C73: Politecnico di Milano | D73: Milán | E73: I MILANO02 | F73: IT | G73: 18 o 24 Meses | H73: 30 de abril - 21 de abril | I73: 04.30 | J73: 04.21 | K73: 21 de octubre | L73: 10.21 | N73: ER | O73: SÍ | P73: SÍ | Q73: SÍ | R73: SÍ | S73: Electrical Engineering (Electronics and Automation) / Biomedical Engineering (Medical Diagnosticand Treatment Technology) / Computer Science (Information and Communication Technologies) | T73: Sí | U73: 8 | V73: 12 | W73: erasmus-agreements@polimi.it | X73: Isabella Bontempi | Y73: SI | Z73: SI | AA73: SI | AB73: SI | AC73: SI | AD73: =_xlfn.TEXTJOIN("/",TRUE,IF(OfertaPlazas[[#This Row],[GITST]]="SI","GITST",""),IF(OfertaPlazas[[#This Row],[GIB]]="SI","GIB",""),IF(OfertaPlazas[[#This Row],[GISD]]="SI","GISD",""),IF(OfertaPlazas[[#This Row],[MASTER]]="SI","MASTER","")) -> GITST/GIB/GISD/MASTER | AE73: SI | AF73: SI | AG73: SI | AH73: SI | AI73: SI | AJ73: SI | AK73: SI | AL73: SI | AM73: SI | AN73: SI | AO73: SI | AP73: SI | AQ73: SI | AR73: SI | AS73: ITALIANO B1 o INGLÉS B2 | AT73: INGLÉS B2 / DT INGLÉS TOEFL IBT 78 (Special Home Edition aceptado) - TOEIC 720 (only listening and reading) - IELTS 6.0 - Cambridge FCE/CAE/PCE - Trinity College ISE II | AU73: INGLÉS para asignaturas de Master / Para DT típicamente 120 ECTS, pero permiten reconocer hasta 30 ECTS. Para DT con Master of Computer Science se requiere nota media de 24/30 (sistema de calificación italiano) = 7,5 UPM / Para el TFM/TFG, no hay calificación oficial en el transcript of records, se debe pedir al Profesor Supervisor que constituye un tribunal y se pide una evaluación final | AV73: No se puede dividir el número de plazas. Aumentamos plazas de movilidad de 4 a 8. Acuerdo DT renovado en 2024 | AW73: La OI lo descarga de la plataforma del PoliMi | BE73: =VLOOKUP(B73,'TEAMS_30-09-2021'!$D:$AG,30,FALSE) -> no se desdobla el número de plazas / se aumentó el número de alumnos en el curso 2020-21 pasando de 4 a 8 | BF73: =VLOOKUP(B73,'ENCUESTAS JUN-2021'!I:I,1,FALSE) -> Politecnico di Milano | BG73: =VLOOKUP(B73,'TEAMS_30-09-2021'!D:D,1,FALSE) -> Politecnico di Milano | BL73: =VLOOKUP(E73,#REF!,1,FALSE) -> #REF!
A74: 73 | B74: Universitá degli Studi di Napoli Federico II | C74: Università degli Studi di Napoli Federico II | D74: Napoles | E74: I NAPOLI01 | F74: IT | H74: 15 de junio (application) | I74: 06.15 | J74: 06.15 | K74: 15 de diciembre | L74: 12.15 | N74: ER | P74: SÍ | R74: SÍ | S74: Electrical Engineering (Electronics and Automation) / Biomedical Engineering (Medical Diagnosticand Treatment Technology) | T74: Sí | U74: 2 | V74: 12 | W74: international@unina.it; erasmus.dieti@unina.it; incoming@unina.it | X74: international office | Y74: SI | Z74: SI | AA74: SI | AB74: NO | AC74: SI | AD74: =_xlfn.TEXTJOIN("/",TRUE,IF(OfertaPlazas[[#This Row],[GITST]]="SI","GITST",""),IF(OfertaPlazas[[#This Row],[GIB]]="SI","GIB",""),IF(OfertaPlazas[[#This Row],[GISD]]="SI","GISD",""),IF(OfertaPlazas[[#This Row],[MASTER]]="SI","MASTER","")) -> GITST/GIB/MASTER | AE74: SI | AF74: SI | AG74: SI | AH74: SI | AI74: SI | AJ74: SI | AK74: SI | AL74: SI | AM74: SI | AN74: SI | AO74: SI | AP74: SI | AQ74: SI | AR74: NO | AS74: ITALIANO B1 o INGLÉS B2 | AU74: Posibilidad de hacer TFG en inglés. | BE74: =VLOOKUP(B74,'TEAMS_30-09-2021'!$D:$AG,30,FALSE) -> 0 | BF74: =VLOOKUP(B74,'ENCUESTAS JUN-2021'!I:I,1,FALSE) -> Universitá degli Studi di Napoli Federico II | BG74: =VLOOKUP(B74,'TEAMS_30-09-2021'!D:D,1,FALSE) -> Universitá degli Studi di Napoli Federico II | BL74: =VLOOKUP(E74,#REF!,1,FALSE) -> #REF!
A75: 74 | B75: Universitá degli Studi di Napoli "Parthenope" | C75: Università degli Studi di Napoli ‘Parthenope’ | D75: Napoles | E75: I NAPOLI03 | F75: IT | H75: 15 de mayo (nomination) - 30 de junio (application) | I75: 05.15 | J75: 06.30 | K75: 1 de septiembre (nomination) - 30 de noviembre (application) | L75: 09.01 | M75: 11.30 | N75: ER | P75: SÍ | Q75: SÍ | R75: SÍ | S75: Electrical Engineering (Electronics and Automation) / Biomedical Engineering (Medical Diagnosticand Treatment Technology) / Computer Science (Information and CommunicationTechnologies) | T75: Sí | U75: 2 | V75: 12 | W75: erasmus.incomingoffice@uniparthenope.it; erasmus.outgoingoffice@uniparthenope.it | X75: international office | Y75: SI | Z75: SI | AA75: SI | AB75: SI | AC75: SI | AD75: =_xlfn.TEXTJOIN("/",TRUE,IF(OfertaPlazas[[#This Row],[GITST]]="SI","GITST",""),IF(OfertaPlazas[[#This Row],[GIB]]="SI","GIB",""),IF(OfertaPlazas[[#This Row],[GISD]]="SI","GISD",""),IF(OfertaPlazas[[#This Row],[MASTER]]="SI","MASTER","")) -> GITST/GIB/GISD/MASTER | AE75: SI | AF75: SI | AG75: SI | AH75: SI | AI75: SI | AJ75: SI | AK75: SI | AL75: NO | AM75: NO | AN75: SI | AO75: SI | AP75: NO | AQ75: SI | AR75: NO | AS75: ITALIANO A2 o INGLÉS B2 | AU75: www.ingegnieria.uniparthenope.it/didattica | BE75: =VLOOKUP(B75,'TEAMS_30-09-2021'!$D:$AG,30,FALSE) -> 0 | BF75: =VLOOKUP(B75,'ENCUESTAS JUN-2021'!I:I,1,FALSE) -> #N/A | BG75: =VLOOKUP(B75,'TEAMS_30-09-2021'!D:D,1,FALSE) -> Universitá degli Studi di Napoli "Parthenope" | BL75: =VLOOKUP(E75,#REF!,1,FALSE) -> #REF!
A76: 75 | B76: Università La Sapienza | C76: Università degli Studi di Roma 'La Sapienza' | D76: Roma | E76: I ROMA01 | F76: IT | H76: 15 de mayo (nomination) - 15 de junio (application) | I76: 05.15 | J76: 06.15 | K76: 15 de octubre (nomination) - 15 de noviembre (application) | L76: 10.15 | M76: 11.15 | N76: ER | P76: SÍ | Q76: SÍ | S76: Electrical Engineering (Electronics and Automation) / Computer Science (Information and CommunicationTechnologies) | T76: Sí | U76: 4 | V76: 12 | W76: erasmusincoming@uniroma1.it | X76: Paola Vanorio | Y76: SI | Z76: SI | AA76: NO | AB76: SI | AC76: SI | AD76: =_xlfn.TEXTJOIN("/",TRUE,IF(OfertaPlazas[[#This Row],[GITST]]="SI","GITST",""),IF(OfertaPlazas[[#This Row],[GIB]]="SI","GIB",""),IF(OfertaPlazas[[#This Row],[GISD]]="SI","GISD",""),IF(OfertaPlazas[[#This Row],[MASTER]]="SI","MASTER","")) -> GITST/GISD/MASTER | AE76: SI | AF76: SI | AG76: SI | AH76: SI | AI76: SI | AJ76: NO | AK76: NO | AL76: SI | AM76: SI | AN76: NO | AO76: SI | AP76: SI | AQ76: SI | AR76: NO | AS76: ITALIANO B1 o INGLÉS B2 | AT76: (aceptan TOEIC con 2 competencias) | AU76: La defensa del TFG se realizará en la ETSIT respetando su normativa y proceso de matriculación. www.facebook.com/SapienzaExchangeStudents | AV76: 16/04/24: Se pide añadir el área de computer science (Manuel Gil) para 2 alumnos 12 meses. TOTAL: 2*12 714 + 2*12 610 | AW76: Certificado solo por email | BE76: =VLOOKUP(B76,'TEAMS_30-09-2021'!$D:$AG,30,FALSE) -> 0 | BF76: =VLOOKUP(B76,'ENCUESTAS JUN-2021'!I:I,1,FALSE) -> Università La Sapienza | BG76: =VLOOKUP(B76,'TEAMS_30-09-2021'!D:D,1,FALSE) -> Università La Sapienza | BL76: =VLOOKUP(E76,#REF!,1,FALSE) -> #REF!
A77: 76 | B77: Università degli Studi di Roma 'Tor Vergata' | C77: Università degli Studi di Roma ‘Tor Vergata’ | D77: Roma | E77: I ROMA02 | F77: IT | H77: 15 de junio (nomination) - 30 de junio (application) | I77: 06.15 | J77: 06.30 | K77: 15 de noviembre (nomination) - 30 de noviembre (application) | L77: 11.15 | M77: 11.30 | N77: ER | R77: SÍ | S77: Biomedical Engineering (Medical Diagnosticand Treatment Technology) | T77: Sí | U77: 1 | V77: 10 | X77: Daniela Mannino | Y77: SI | Z77: NO | AA77: SI | AB77: NO | AC77: SI | AD77: =_xlfn.TEXTJOIN("/",TRUE,IF(OfertaPlazas[[#This Row],[GITST]]="SI","GITST",""),IF(OfertaPlazas[[#This Row],[GIB]]="SI","GIB",""),IF(OfertaPlazas[[#This Row],[GISD]]="SI","GISD",""),IF(OfertaPlazas[[#This Row],[MASTER]]="SI","MASTER","")) -> GIB/MASTER | AE77: SI | AF77: SI | AG77: SI | AH77: SI | AI77: SI | AJ77: SI | AK77: SI | AL77: SI | AM77: SI | AN77: SI | AO77: SI | AP77: SI | AQ77: SI | AR77: NO | AS77: ITALIANO B1 o INGLÉS B2 | AV77: nuevo acuerdo firmado en febrero 2023 | BL77: =VLOOKUP(E77,#REF!,1,FALSE) -> #REF!
A78: 77 | B78: Università degli Studi di Padova | C78: Università degli Studi di Padova | D78: Padova | E78: I PADOVA01 | F78: IT | H78: 15 de marzo al 30 de abril (nomination ) - 15 de mayo (application step 1) y 15 de junio (application step 3) | I78: 15.03 | J78: 05.15 y 06.15 | K78: 1 de septiembre al 15 de octubre (nomination) -31 de octubre (step 1)- 30 de noviembre (application) | L78: 09.01 | M78: 11.30 | N78: ER | P78: SÍ | R78: SÍ | S78: Electrical Engineering (Electronics and Automation) / Biomedical Engineering (Medical Diagnosticand Treatment Technology) | T78: Sí | U78: 4 | V78: 12 | W78: erasmus.incoming@unipd.it; international@dei.unipd.it; mobility.in@unipd.it (DT) | X78: Caroline Sophie Witte, Sara Mazzoli | Y78: SI | Z78: SI | AA78: SI | AB78: NO | AC78: SI | AD78: =_xlfn.TEXTJOIN("/",TRUE,IF(OfertaPlazas[[#This Row],[GITST]]="SI","GITST",""),IF(OfertaPlazas[[#This Row],[GIB]]="SI","GIB",""),IF(OfertaPlazas[[#This Row],[GISD]]="SI","GISD",""),IF(OfertaPlazas[[#This Row],[MASTER]]="SI","MASTER","")) -> GITST/GIB/MASTER | AE78: SI | AF78: SI | AG78: SI | AH78: SI | AI78: SI | AJ78: SI | AK78: SI | AL78: SI | AM78: SI | AN78: SI | AO78: SI | AP78: SI | AQ78: SI | AR78: SI | AS78: ITALIANO A2 o INGLÉS B1 | AT78: for DT INGLÉS B2 (certificate from Lingüistic Department at ETSIT is accepted) INGLÉS B1 (certificate from Lingüistic Department at ETSIT is accepted) / | AU78: 2 alumnos para 914 - Biomedical Engineering y 2 alumnos para 714 - Electrical Engineering / Para alumnos de DT: 42 credits must be from technical subjects (subjects that are in the official study plan), the rest of credits (18 ECTS) may be chosen from other dpt of Padova University (may be language courses or internships) / 30 credits must be from "characterizing" ("caratterizzanti" in Italian) subjects. Those are the courses with one of the following label: - signal processing - telecommunications - electromagnetism - networks final project of track 005PD (international mobility) that is worth 30 credits (the standard final thesis of 18 ECTS credits is for Italian students that do not go abroad) | AV78: Para alumnos de doble título, nominar a elisa.zambon@unipd.it / Acuerdo DT renovado en diciembre 2024 | BE78: =VLOOKUP(B78,'TEAMS_30-09-2021'!$D:$AG,30,FALSE) -> #N/A | BF78: =VLOOKUP(B78,'ENCUESTAS JUN-2021'!I:I,1,FALSE) -> #N/A | BG78: =VLOOKUP(B78,'TEAMS_30-09-2021'!D:D,1,FALSE) -> #N/A | BL78: =VLOOKUP(E78,#REF!,1,FALSE) -> #REF!
A79: 78 | B79: University of Rome Campus Bio-Medico – UCBM | D79: Roma | E79: I ROMA14 | F79: IT | H79: 1 de mayo (nomination) - 1 de junio (application) | I79: 05.01 | J79: 06.01 | K79: 15 de octubre (nomination) - 15 de noviembre (application) | L79: 10.15 | M79: 11.15 | N79: ER | R79: SÍ | S79: Biomedical Engineering (Medical Diagnosticand Treatment Technology) | T79: Sí | U79: 1 | V79: 10 | W79: Erasmus@unicampus.it | X79: Claudia Zanetti | Y79: SI | Z79: NO | AA79: SI | AB79: NO | AC79: SI | AD79: =_xlfn.TEXTJOIN("/",TRUE,IF(OfertaPlazas[[#This Row],[GITST]]="SI","GITST",""),IF(OfertaPlazas[[#This Row],[GIB]]="SI","GIB",""),IF(OfertaPlazas[[#This Row],[GISD]]="SI","GISD",""),IF(OfertaPlazas[[#This Row],[MASTER]]="SI","MASTER","")) -> GIB/MASTER | AE79: SI | AF79: SI | AG79: SI | AH79: SI | AI79: SI | AJ79: SI | AK79: SI | AL79: SI | AM79: SI | AN79: SI | AO79: SI | AP79: SI | AQ79: SI | AR79: NO | AS79: ITALIANO B1 o INGLÉS B2 | AV79: nuevo acuerdo 2024 | BL79: =VLOOKUP(E79,#REF!,1,FALSE) -> #REF!
A80: 79 | B80: Universitá degli Studi di Pavia | C80: Università degli Studi di Pavia | D80: Pavia | E80: I PAVIA01 | F80: IT | H80: 15 de mayo (nomination) - 15 de junio (application) | I80: 05.15 | J80: 06.15 | K80: 15 de octubre (nomination) - 15 de noviembre (application) | L80: 10.15 | M80: 11.15 | N80: ER | O80: SÍ | Q80: SÍ | R80: SÍ | S80: Biomedical Engineering (Medical Diagnosticand Treatment Technology) / Electrical Engineering (Electricity and Energy) / Computer Science (Information and CommunicationTechnologies) | T80: Sí | U80: 4 | V80: 12 | W80: incoming.erasmus@unipv.it | X80: international office | Y80: SI | Z80: SI | AA80: SI | AB80: SI | AC80: SI | AD80: =_xlfn.TEXTJOIN("/",TRUE,IF(OfertaPlazas[[#This Row],[GITST]]="SI","GITST",""),IF(OfertaPlazas[[#This Row],[GIB]]="SI","GIB",""),IF(OfertaPlazas[[#This Row],[GISD]]="SI","GISD",""),IF(OfertaPlazas[[#This Row],[MASTER]]="SI","MASTER","")) -> GITST/GIB/GISD/MASTER | AE80: SI | AF80: SI | AG80: SI | AH80: SI | AI80: SI | AJ80: SI | AK80: SI | AL80: SI | AM80: SI | AN80: SI | AO80: SI | AP80: SI | AQ80: SI | AR80: NO | AS80: ITALIANO B1 o INGLÉS B2 | AU80: asignaturas de Máster en inglés | AV80: se añade el área de computer science en enero 2023 | BE80: =VLOOKUP(B80,'TEAMS_30-09-2021'!$D:$AG,30,FALSE) -> 0 | BF80: =VLOOKUP(B80,'ENCUESTAS JUN-2021'!I:I,1,FALSE) -> #N/A | BG80: =VLOOKUP(B80,'TEAMS_30-09-2021'!D:D,1,FALSE) -> Universitá degli Studi di Pavia | BL80: =VLOOKUP(E80,#REF!,1,FALSE) -> #REF!
A81: 80 | B81: Università degli studi Roma Tre | C81: Università degli Studi Roma Tre | D81: Roma | E81: I ROMA16 | F81: IT | H81: 1 de junio (nomination) - 15 de junio (application) | I81: 06.01 | J81: 06.15 | N81: ER | P81: SÍ | R81: SÍ | S81: Electrical Engineering (Electronics and Automation) / Biomedical Engineering (Medical Diagnosticand Treatment Technology) | T81: Sí | U81: 2 | V81: 10 | W81: incoming.students@uniroma3.it; outgoing.students@uniroma3.it; cristina.ponti@uniroma3.it | X81: Cristina Ponti | Y81: SI | Z81: SI | AA81: SI | AB81: NO | AC81: SI | AD81: =_xlfn.TEXTJOIN("/",TRUE,IF(OfertaPlazas[[#This Row],[GITST]]="SI","GITST",""),IF(OfertaPlazas[[#This Row],[GIB]]="SI","GIB",""),IF(OfertaPlazas[[#This Row],[GISD]]="SI","GISD",""),IF(OfertaPlazas[[#This Row],[MASTER]]="SI","MASTER","")) -> GITST/GIB/MASTER | AE81: SI | AF81: SI | AG81: SI | AH81: SI | AI81: SI | AJ81: SI | AK81: SI | AL81: SI | AM81: SI | AN81: SI | AO81: SI | AP81: NO | AQ81: NO | AR81: NO | AS81: ITALIANO B1 o INGLÉS B2 | AU81: En el OLA, poner el contacto de la persona responsable del departamento: para bio cristina.ponti@uniroma3.it | BD81: Se ha quitado el TFM de la Oferta porque en el 25/26 le han dicho a un alumno que no se oferta | BL81: =VLOOKUP(E81,#REF!,1,FALSE) -> #REF!
A82: 81 | B82: Politecnico di Torino | C82: Politecnico di Torino | D82: Turín | E82: I TORINO02 | F82: IT | G82: 18 Meses | H82: 4 de mayo - 8 de mayo | I82: 05.04 | J82: 05.08 | K82: 1 de diciembre | L82: 12.01 | M82: 12.01 | N82: ER | P82: SÍ | Q82: SÍ | R82: SÍ | S82: Electrical Engineering (Electronics and Automation) / Biomedical Engineering (Medical Diagnosticand Treatment Technology) / Computer Science (Information and Communication Technologies) | T82: Sí | U82: 8 | V82: 12 | W82: incoming.students@polito.it | X82: international office | Y82: SI | Z82: SI | AA82: SI | AB82: SI | AC82: SI | AD82: =_xlfn.TEXTJOIN("/",TRUE,IF(OfertaPlazas[[#This Row],[GITST]]="SI","GITST",""),IF(OfertaPlazas[[#This Row],[GIB]]="SI","GIB",""),IF(OfertaPlazas[[#This Row],[GISD]]="SI","GISD",""),IF(OfertaPlazas[[#This Row],[MASTER]]="SI","MASTER","")) -> GITST/GIB/GISD/MASTER | AE82: SI | AF82: SI | AG82: SI | AH82: SI | AI82: SI | AJ82: SI | AK82: SI | AL82: SI | AM82: SI | AN82: SI | AO82: SI | AP82: SI | AQ82: SI | AR82: SI | AS82: ITALIANO B2 o INGLÉS B2 | AT82: INGLÉS B2: IELTS 5.5 o TOEFL 72 IbT o TOEIC Listening: 400 Reading: 385 Speaking: 160 Writing: 150 o Cambridge ESOL examinations o PEARSON 59 / A declaration from the Home University is requested during the nomination process (certificate of the linguistic department is accepted) DOUBLE/JOINT DEGREE STUDENTS • DEGREE PROGRAMME (Bachelor/Master of Science) offered in Italian or partially in Italian/English: IELTS 5.5 or higher + PLIDA B1 or higher (All the language requirements are satisfied at the admission • DEGREE PROGRAMME (Bachelor/Master of Science) offered in English: IELTS 5.5 or higher (PLIDA A2 or passing Italian language level A2 at Polito) EXCHANGE STUDENTS (mobility for courses/courses and final project/final project/Research) Language of teaching of the courses/activities included in the proposal of Learning Agreement: ITALIAN (B2 level) / ENGLISH (B2 level) / ENGLISH AND ITALIAN (English-B2 level, Italian-B2 level) | AU82: DT con el Máster in Communications and computer networks engineering. Para DT - 90 ECTS. El segundo año de DT, los alumnos están exentos de tasas de matricula pero deben pagar tasas requeridas por el Gobierno italiano / No se puede cursar asignaturas del 1er año de grado / Mínimo 20 créditos ECTS por semestre/ 3 alumnos para la DT / 4 alumnos en el área Biomedical Engineering y 4 alumnos en el área Electronic Engineering o Computer Science / Para el TFM/TFG, no hay calificación oficial en el transcript of records, se debe pedir al Profesor Supervisor que constituya un tribunal y se pide una evaluación final / Define a proposal of Learning Agreement including at least 18 creditsECTS per semester from the Degree Course for which you have been nominated (el resto de ECTS pueden ser elegidos en otras titulaciones) | AV82: DT addedndum firmado 02/07/2026 / no se puede desdoblar plazas | BL82: =VLOOKUP(E82,#REF!,1,FALSE) -> #REF!
A83: 82 | B83: Università degli Studi di Trento | C83: Università degli Studi di Trento | D83: Trento | E83: I TRENTO01 | F83: IT | H83: 15 de mayo (nomination) - 31 de mayo (application) | I83: 05.15 | J83: 05.31 | K83: 15 de octubre (nomination) - 31 de octubre (application) | L83: 10.15 | M83: 10.31 | N83: ER | P83: SÍ | S83: Electrical Engineering (Electronics and Automation) | T83: Sí | U83: 1 | V83: 12 | W83: international@unitn.it | X83: international office | Y83: SI | Z83: SI | AA83: NO | AB83: NO | AC83: SI | AD83: =_xlfn.TEXTJOIN("/",TRUE,IF(OfertaPlazas[[#This Row],[GITST]]="SI","GITST",""),IF(OfertaPlazas[[#This Row],[GIB]]="SI","GIB",""),IF(OfertaPlazas[[#This Row],[GISD]]="SI","GISD",""),IF(OfertaPlazas[[#This Row],[MASTER]]="SI","MASTER","")) -> GITST/MASTER | AE83: SI | AF83: SI | AG83: SI | AH83: SI | AI83: SI | AJ83: SI | AK83: SI | AL83: SI | AM83: SI | AN83: SI | AO83: SI | AP83: SI | AQ83: SI | AR83: NO | AS83: ITALIANO A2 o INGLÉS B1 | AT83: INGLÉS B2 para algunos grados con asignaturas en inglés) - ITALIANO A2 (para asignaturas en italiano) | AU83: Algunas clases pueden pedir requisitos adicionales de idiomas:http://international.unitn.it/incoming/languagerequirements / Oferta académica en inglés: http://international.unitn.it/incoming/dss-academic-offer | AV83: Oferta académica en inglés: http://international.unitn.it/incoming/dss-academic-offer | BE83: =VLOOKUP(B83,'TEAMS_30-09-2021'!$D:$AG,30,FALSE) -> 0 | BF83: =VLOOKUP(B83,'ENCUESTAS JUN-2021'!I:I,1,FALSE) -> #N/A | BG83: =VLOOKUP(B83,'TEAMS_30-09-2021'!D:D,1,FALSE) -> Università degli Studi di Trento | BL83: =VLOOKUP(E83,#REF!,1,FALSE) -> #REF!
A84: 83 | B84: University of Limerick | C84: University of Limerick | D84: Limerick | E84: IRL LIMERIC01 | F84: IE | H84: 1 de mayo (nomination) - 31 de mayo (application) | I84: 05.01 | J84: 05.31 | K84: 1 de octubre (nomination) - 31 de octubre (application) | L84: 10.01 | M84: 10.31 | N84: ER | P84: SÍ | S84: Electrical Engineering (Electronics and Automation) | T84: Sí | U84: 1 | V84: 6 | W84: Incoming.erasmus@ul.ie | X84: Incoming Mobility Team | Y84: SI | Z84: SI | AA84: NO | AB84: NO | AC84: SI | AD84: =_xlfn.TEXTJOIN("/",TRUE,IF(OfertaPlazas[[#This Row],[GITST]]="SI","GITST",""),IF(OfertaPlazas[[#This Row],[GIB]]="SI","GIB",""),IF(OfertaPlazas[[#This Row],[GISD]]="SI","GISD",""),IF(OfertaPlazas[[#This Row],[MASTER]]="SI","MASTER","")) -> GITST/MASTER | AE84: SI | AF84: SI | AG84: NO | AH84: SI | AI84: SI | AJ84: SI | AK84: SI | AL84: NO | AM84: NO | AN84: SI | AO84: SI | AP84: NO | AQ84: NO | AR84: NO | AS84: INGLÉS B2 | AV84: febrero 2023: solicitado a UL extender el acuerdo a 1 curso académico y añadir 610 | AY84: Institucional | AZ84: Electrical & Telecommunications Engineering (06.5) | BC84: firmas: AA + MPG | BE84: =VLOOKUP(B84,'TEAMS_30-09-2021'!$D:$AG,30,FALSE) -> #N/A | BF84: =VLOOKUP(B84,'ENCUESTAS JUN-2021'!I:I,1,FALSE) -> #N/A | BG84: =VLOOKUP(B84,'TEAMS_30-09-2021'!D:D,1,FALSE) -> #N/A | BL84: =VLOOKUP(E84,#REF!,1,FALSE) -> #REF!
A85: 84 | B85: Ss. Cyril and Methodius University in Skopje | C85: Ss. Cyril and Methodius University | D85: Skopje | E85: MK SKOPJE01 | F85: MK | H85: 15 de mayo | I85: 05.15 | J85: 05.15 | L85: 05.15 | N85: ER | Q85: SÍ | S85: ComputerScience (Informationand Communication Technologies) | T85: Sí | U85: 2 | V85: 12 | W85: international@finki.ukim.mk | X85: international office | Y85: SI | Z85: SI | AA85: NO | AB85: SI | AC85: SI | AD85: =_xlfn.TEXTJOIN("/",TRUE,IF(OfertaPlazas[[#This Row],[GITST]]="SI","GITST",""),IF(OfertaPlazas[[#This Row],[GIB]]="SI","GIB",""),IF(OfertaPlazas[[#This Row],[GISD]]="SI","GISD",""),IF(OfertaPlazas[[#This Row],[MASTER]]="SI","MASTER","")) -> GITST/GISD/MASTER | AE85: SI | AF85: SI | AG85: SI | AH85: SI | AI85: SI | AJ85: SI | AK85: SI | AL85: SI | AM85: SI | AN85: SI | AO85: SI | AP85: SI | AQ85: SI | AR85: NO | AS85: INGLÉS B2 | AY85: Institucional | AZ85: Computer Science and Engineering (48) | BB85: Prof. Dr. Suzana Loshkovska (Departmental Coordinator) | BC85: firmas: AA + MPG | BE85: =VLOOKUP(B85,'TEAMS_30-09-2021'!$D:$AG,30,FALSE) -> 0 | BF85: =VLOOKUP(B85,'ENCUESTAS JUN-2021'!I:I,1,FALSE) -> #N/A | BG85: =VLOOKUP(B85,'TEAMS_30-09-2021'!D:D,1,FALSE) -> Ss. Cyril and Methodius University in Skopje | BL85: =VLOOKUP(E85,#REF!,1,FALSE) -> #REF!
A86: 85 | B86: UiT Norges Arctic university of Norway | C86: UNIVERSITETET I TROMSOE - NORGES ARKTISKE UNIVERSITET | D86: Narvik | E86: N TROMSO01 | F86: NO | H86: 1 de junio | I86: 06.01 | J86: 06.01 | K86: 15 de octubre | L86: 10.15 | N86: ER | P86: SÍ | S86: Electrical Engineering (Electronics and Automation) | T86: Sí | U86: 2 | V86: 12 | W86: admission@hjelp.uit.​no | X86: international office | Y86: SI | Z86: SI | AA86: NO | AB86: NO | AC86: SI | AD86: =_xlfn.TEXTJOIN("/",TRUE,IF(OfertaPlazas[[#This Row],[GITST]]="SI","GITST",""),IF(OfertaPlazas[[#This Row],[GIB]]="SI","GIB",""),IF(OfertaPlazas[[#This Row],[GISD]]="SI","GISD",""),IF(OfertaPlazas[[#This Row],[MASTER]]="SI","MASTER","")) -> GITST/MASTER | AE86: NO | AF86: NO | AG86: NO | AH86: NO | AI86: NO | AJ86: NO | AK86: NO | AL86: NO | AM86: NO | AN86: SI | AO86: SI | AP86: SI | AQ86: SI | AR86: NO | AS86: INGLÉS B1 | AT86: (IELTS or TOEFL preferIble) | AY86: Institucional | AZ86: Engineering/Technology (07) | BC86: firmas: AA + MPG | BE86: =VLOOKUP(B86,'TEAMS_30-09-2021'!$D:$AG,30,FALSE) -> #N/A | BF86: =VLOOKUP(B86,'ENCUESTAS JUN-2021'!I:I,1,FALSE) -> #N/A | BG86: =VLOOKUP(B86,'TEAMS_30-09-2021'!D:D,1,FALSE) -> #N/A | BL86: =VLOOKUP(E86,#REF!,1,FALSE) -> #REF!
A87: 86 | B87: Norwegian University of Science and Technology NTNU | C87: Norges Teknisk-Naturvitenskapelige Universitet | D87: Trondheim | E87: N TRONDHE01 | F87: NO | H87: 15 de abril (nomination) - 1 de mayo (application) | I87: 04.15 | J87: 05.01 | K87: 15 September (nomination) - 1 October (application) | L87: 09.15 | N87: ER | P87: SÍ | S87: Electrical Engineering (Electronics and Automation) | T87: Sí | U87: 2 | V87: 12 | W87: nominations@aud.ntnu.no | X87: international office | Y87: SI | Z87: SI | AA87: NO | AB87: NO | AC87: SI | AD87: =_xlfn.TEXTJOIN("/",TRUE,IF(OfertaPlazas[[#This Row],[GITST]]="SI","GITST",""),IF(OfertaPlazas[[#This Row],[GIB]]="SI","GIB",""),IF(OfertaPlazas[[#This Row],[GISD]]="SI","GISD",""),IF(OfertaPlazas[[#This Row],[MASTER]]="SI","MASTER","")) -> GITST/MASTER | AE87: SI | AF87: SI | AG87: SI | AH87: SI | AI87: SI | AJ87: SI | AK87: SI | AL87: SI | AM87: SI | AN87: SI | AO87: SI | AP87: SI | AQ87: SI | AR87: NO | AS87: INGLÉS B2 | AU87: Disponible solo asignaturas de Master en inglés | AV87: 2*6: 713 // 2*6: 714 | AY87: Institucional | AZ87: Electrical Engineering, Telecommunication (74) | BC87: firmas: AA + MPG | BE87: =VLOOKUP(B87,'TEAMS_30-09-2021'!$D:$AG,30,FALSE) -> 0 | BF87: =VLOOKUP(B87,'ENCUESTAS JUN-2021'!I:I,1,FALSE) -> #N/A | BG87: =VLOOKUP(B87,'TEAMS_30-09-2021'!D:D,1,FALSE) -> Norwegian University of Science and Technology NTNU | BL87: =VLOOKUP(E87,#REF!,1,FALSE) -> #REF!
A88: 87 | B88: Technische Universiteit Eindhoven | C88: Technische Universiteit Eindhoven | D88: Eindhoven | E88: NL EINDHOV17 | F88: NL | H88: 15 de abril (nomination) - 1 de mayo (application) | I88: 04.15 | J88: 05.01 | K88: 1 de septiembre (nomination) - 1 de octubre (application) | L88: 09.01 | M88: 10.01 | N88: ER | P88: SÍ | R88: SÍ | S88: Electrical Engineering (Electronics and Automation) / Biomedical Engineering (Medical Diagnosticand Treatment Technology) | T88: Sí | U88: 4 | V88: 6 | W88: exchange.bme@tue.nl; ee.exchange@tue.nl | X88: Jacqueline Hartold (biomedical engineering); Janneke Cohen (electrical engineering) | Y88: SI | Z88: SI | AA88: SI | AB88: NO | AC88: SI | AD88: =_xlfn.TEXTJOIN("/",TRUE,IF(OfertaPlazas[[#This Row],[GITST]]="SI","GITST",""),IF(OfertaPlazas[[#This Row],[GIB]]="SI","GIB",""),IF(OfertaPlazas[[#This Row],[GISD]]="SI","GISD",""),IF(OfertaPlazas[[#This Row],[MASTER]]="SI","MASTER","")) -> GITST/GIB/MASTER | AE88: SI | AF88: SI | AG88: SI | AH88: SI | AI88: SI | AJ88: SI | AK88: SI | AL88: SI | AM88: SI | AN88: SI | AO88: SI | AP88: SI | AQ88: SI | AR88: NO | AS88: INGLÉS C1/C2 TOEFL (Test of English as a Foreign Language) Overall band score of at least 90 AND a minimum score of 21 for each section We only accept the TOEFL internet-based test (iBT) We only accept all scores from 1 test date; we do not accept MyBest Scores For admission to the academic year 2023 - 2024 we do not accept the TOEFL iBT Special Home Edition test IELTS (academic version) Overall band score of at least 6.5 and a minimum of 6.0 for each section We do not accept the IELTS online test We only accept all scores from 1 test date; we do not accept IELTS One Skill Retake Cambridge certificates Proof that you have passed the C2 proficiency (formally known as Certificate of Proficiency in English CPE), with overall score 180 and a minimum of 169 in each section), or the C1 Advanced Certificate (formally known as the Certificate in Advanced English CAE) with overall score 176 and a minimum of 169 in each section https://www.tue.nl/en/education/exchange-programs/how-to-apply/language-requirements-for-exchange-students/ The language test results may not be older than 2 years. https://www.tue.nl/en/education/become-a-tue-student/admission-and-enrollment/language-proficiency-requirements | AU88: 2*6 en 914 y 2*6 en 714 Posibilidad de 1 alumno * 12 meses link para buscar supervisores para TFT: https://www.tue.nl/en/university/departments/electrical-engineering/research/ Para el área 714 (electrical engineering): el 50% de las asignaturas deben cursarse en Electrical Enginnering | AV88: 2x6: 714 (posibilidad de 1*12) // 2x6: 914 | AY88: Institucional | AZ88: Electrical & Telecommunications Engineering (714) / Medical Technology (914) | BC88: firmas: AA + LSA | BD88: hay que incluir el 1er ciclo en el acuerdo bio (y teleco si no está) | BE88: =VLOOKUP(B88,'TEAMS_30-09-2021'!$D:$AG,30,FALSE) -> 0 | BF88: =VLOOKUP(B88,'ENCUESTAS JUN-2021'!I:I,1,FALSE) -> #N/A | BG88: =VLOOKUP(B88,'TEAMS_30-09-2021'!D:D,1,FALSE) -> Technische Universiteit Eindhoven | BL88: =VLOOKUP(E88,#REF!,1,FALSE) -> #REF!
A89: 88 | B89: Instituto Politécnico de Bragança | C89: Instituto Politécnico de Bragança | D89: Bragança | E89: P BRAGANC01 | F89: PT | H89: 1 de julio | I89: 07.01 | J89: 07.1 | K89: 1 de diciembre | L89: 12.01 | M89: 12.01 | N89: ER | P89: SÍ | S89: Electrical Engineering (Electronics and Automation) | T89: Sí | U89: 1 | V89: 12 | W89: sylwia@ipb.pt | X89: Sylwia Solczak | Y89: SI | Z89: SI | AA89: NO | AB89: NO | AC89: SI | AD89: =_xlfn.TEXTJOIN("/",TRUE,IF(OfertaPlazas[[#This Row],[GITST]]="SI","GITST",""),IF(OfertaPlazas[[#This Row],[GIB]]="SI","GIB",""),IF(OfertaPlazas[[#This Row],[GISD]]="SI","GISD",""),IF(OfertaPlazas[[#This Row],[MASTER]]="SI","MASTER","")) -> GITST/MASTER | AE89: SI | AF89: SI | AG89: SI | AH89: SI | AI89: SI | AJ89: SI | AK89: SI | AL89: SI | AM89: SI | AN89: SI | AO89: SI | AP89: SI | AQ89: SI | AR89: NO | AS89: PORTUGUÉS B1 o INGLÉS B1 | AY89: Institucional | AZ89: 714 Electrical Engineering | BB89: Prof. Luis Manuel Santo Pais: pais@ipb.pt/Sylwia Solczak Melo: sylwia@ipb.pt | BC89: ETSIT | BD89: Acuerdo: Electrical & Telecom. Engin | BE89: =VLOOKUP(B89,'TEAMS_30-09-2021'!$D:$AG,30,FALSE) -> 0 | BF89: =VLOOKUP(B89,'ENCUESTAS JUN-2021'!I:I,1,FALSE) -> #N/A | BG89: =VLOOKUP(B89,'TEAMS_30-09-2021'!D:D,1,FALSE) -> Instituto Politécnico de Bragança | BL89: =VLOOKUP(E89,#REF!,1,FALSE) -> #REF!
A90: 89 | B90: Universidade da Beira Interior | C90: Universidade da Beira Interior | D90: Covilhas | E90: P COVILHA01 | F90: PT | H90: 1 de junio | I90: 06.01 | J90: 06.01 | K90: 15 de noviembre | L90: 10.15 | N90: ER | P90: SÍ | S90: Electrical Engineering (Electronics and Automation) | T90: Sí | U90: 1 | V90: 12 | W90: eramus.mobilidade@ubi.pt | X90: international office | Y90: SI | Z90: SI | AA90: NO | AB90: NO | AC90: SI | AD90: =_xlfn.TEXTJOIN("/",TRUE,IF(OfertaPlazas[[#This Row],[GITST]]="SI","GITST",""),IF(OfertaPlazas[[#This Row],[GIB]]="SI","GIB",""),IF(OfertaPlazas[[#This Row],[GISD]]="SI","GISD",""),IF(OfertaPlazas[[#This Row],[MASTER]]="SI","MASTER","")) -> GITST/MASTER | AE90: SI | AF90: SI | AG90: SI | AH90: SI | AI90: SI | AJ90: SI | AK90: SI | AL90: SI | AM90: SI | AN90: SI | AO90: SI | AP90: SI | AQ90: SI | AR90: NO | AS90: PORTUGUÉS B1 o INGLÉS B1 | BE90: =VLOOKUP(B90,'TEAMS_30-09-2021'!$D:$AG,30,FALSE) -> 0 | BF90: =VLOOKUP(B90,'ENCUESTAS JUN-2021'!I:I,1,FALSE) -> #N/A | BG90: =VLOOKUP(B90,'TEAMS_30-09-2021'!D:D,1,FALSE) -> Universidade da Beira Interior | BL90: =VLOOKUP(E90,#REF!,1,FALSE) -> #REF!
A91: 90 | B91: Polytechnic Institute of Leiria | C91: Instituto Politécnico de Leiria | D91: Leiria | E91: P LEIRIA01 | F91: PT | H91: 30 de junio | I91: 06.30 | J91: 06.30 | K91: 30 de noviembre | L91: 11.30 | N91: ER | O91: SÍ | P91: SÍ | S91: Electrical Engineering: (Electricity and Energy); (Electronics and Automation) | T91: Sí | U91: 1 | V91: 12 | W91: acecilia@ipleiria.pt | X91: international office | Y91: SI | Z91: SI | AA91: NO | AB91: NO | AC91: SI | AD91: =_xlfn.TEXTJOIN("/",TRUE,IF(OfertaPlazas[[#This Row],[GITST]]="SI","GITST",""),IF(OfertaPlazas[[#This Row],[GIB]]="SI","GIB",""),IF(OfertaPlazas[[#This Row],[GISD]]="SI","GISD",""),IF(OfertaPlazas[[#This Row],[MASTER]]="SI","MASTER","")) -> GITST/MASTER | AE91: SI | AF91: SI | AG91: SI | AH91: SI | AI91: SI | AJ91: NO | AK91: NO | AL91: NO | AM91: NO | AN91: SI | AO91: SI | AP91: NO | AQ91: SI | AR91: NO | AS91: PORTUGUÉS A2 o INGLÉS B1 | AY91: Institucional | AZ91: 714 Electrical Engineering / 713 Electronics Engineering | BB91: Erasmus Institutional Coordinator: Nuno André O. Mangas Pereira: gmci@ipleiria.pt/ Nadie Martins: student´s mobility International Cooperation and Mobility: nadie.martins@ipleiria.pto | BC91: ETSIT | BD91: Acuerdo: 713 Eletrical Engineering, 714 Electronics and Automation | BE91: =VLOOKUP(B91,'TEAMS_30-09-2021'!$D:$AG,30,FALSE) -> 0 | BF91: =VLOOKUP(B91,'ENCUESTAS JUN-2021'!I:I,1,FALSE) -> #N/A | BG91: =VLOOKUP(B91,'TEAMS_30-09-2021'!D:D,1,FALSE) -> Polytechnic Institute of Leiria | BL91: =VLOOKUP(E91,#REF!,1,FALSE) -> #REF!
A92: 91 | B92: Universidade de Lisboa* - Técnico de Lisboa | C92: Universidade de Lisboa | D92: Lisboa | E92: P LISBOA109 | F92: PT | H92: 14 de mayo | I92: 05.14 | J92: 06.15 | K92: 15 de noviembre | L92: 11.15 | M92: 11.15 | N92: ER/EIT HEALTH | P92: SÍ | Q92: SÍ | R92: SÍ | S92: Electrical Engineering (Electronics and Automation) / Biomedical Engineering (Medical Diagnosticand Treatment Technology) / Computer Science (Information and Communication Technologies) | T92: Sí | U92: 7 | V92: 12 | W92: paula.lopes@tecnico.ulisboa.pt; erasmus@tecnico.ulisboa.pt | X92: Paula Lopes | Y92: SI | Z92: SI | AA92: SI | AB92: SI | AC92: SI | AD92: =_xlfn.TEXTJOIN("/",TRUE,IF(OfertaPlazas[[#This Row],[GITST]]="SI","GITST",""),IF(OfertaPlazas[[#This Row],[GIB]]="SI","GIB",""),IF(OfertaPlazas[[#This Row],[GISD]]="SI","GISD",""),IF(OfertaPlazas[[#This Row],[MASTER]]="SI","MASTER","")) -> GITST/GIB/GISD/MASTER | AE92: SI | AF92: SI | AG92: SI | AH92: SI | AI92: SI | AJ92: NO | AK92: NO | AL92: SI | AM92: NO | AN92: NO | AO92: SI | AP92: SI | AQ92: SI | AR92: NO | AS92: PORTUGUÉS B2 o INGLÉS B2 | AU92: PRIORIDAD ALUMNOS PROGRAMA EIT HEALTH 2 plazas en Electrical Engineering y Computer Science + 5 plazas en Biomedical Engineering | AW92: ToR verificable | AX92: LISBOA-1 | AY92: Institucional | AZ92: ¿713 Electrical Engineering?/ 914 Biomedical Engineering | BA92: Institutional Erasmus Coordinator: Silvia Santos: silvia.snatos@tecnico.ulisboa.pt/ Stdent Mobility Coordinators: Cristina Sousa & Paula Lopez: cristina.sousa@tecnico.ulisboa.pt, paula.lopez@tecnico.ulisboa.pt | BC92: UPM (varias Escuelas) | BD92: Acuerdo: 0713 (522) Eletricity and Energy (Electrical and Computer Engineering) 0914(725) Health (Biomedical Engineering) | BE92: =VLOOKUP(B92,'TEAMS_30-09-2021'!$D:$AG,30,FALSE) -> Queremos renovar con el Técnico di Lisboa (IST) / MTIH 5 plazas* 6 meses / GIB 2 plazas*12 meses / GITST-MUIT: 2 plazas*12 meses | BF92: =VLOOKUP(B92,'ENCUESTAS JUN-2021'!I:I,1,FALSE) -> #N/A | BG92: =VLOOKUP(B92,'TEAMS_30-09-2021'!D:D,1,FALSE) -> Universidade de Lisboa* - Técnico de Lisboa | BL92: =VLOOKUP(E92,#REF!,1,FALSE) -> #REF!
A93: 92 | B93: Universidade de Lisboa* - Faculty of Sciences | C93: Universidade de Lisboa | D93: Lisboa | E93: P LISBOA109 | F93: PT | H93: 15 de junio | I93: 06.15 | J93: 06.15 | K93: 31 de octubre | L93: 10.31 | M93: 10.31 | N93: ER | O93: SÍ | R93: SÍ | S93: Electrical Engineering (Electricity and Energy) / BiomedicalEngineering (Medical Diagnosticand TreatmentTechnology) | T93: Sí | U93: 6 | V93: 12 | Y93: SI | Z93: SI | AA93: SI | AB93: NO | AC93: SI | AD93: =_xlfn.TEXTJOIN("/",TRUE,IF(OfertaPlazas[[#This Row],[GITST]]="SI","GITST",""),IF(OfertaPlazas[[#This Row],[GIB]]="SI","GIB",""),IF(OfertaPlazas[[#This Row],[GISD]]="SI","GISD",""),IF(OfertaPlazas[[#This Row],[MASTER]]="SI","MASTER","")) -> GITST/GIB/MASTER | AE93: SI | AF93: SI | AG93: SI | AH93: SI | AI93: SI | AJ93: NO | AK93: NO | AL93: SI | AM93: NO | AN93: NO | AO93: SI | AP93: SI | AQ93: SI | AR93: NO | AS93: PORTUGUÉS B2 | AU93: 2 plazas en Electrical Engineering + 2 plazas en Biomedical Engineering + 2 plazas en Earth Science | AX93: LISBOA-2 | AY93: Departamental (Facultad) | AZ93: 714 Electrical Engineering, 914 Biomedical Engineering | BA93: Faculty of Sciences: | BB93: The Director of the Faculty of Sciences: Prof. José Mauel Pinto Paixao / internacional@fc.ul.pt | BC93: ETSIT | BD93: Acuerdo: Eletrical Engineering, Biomedical Engineering, Earth Science | BF93: =VLOOKUP(B93,'ENCUESTAS JUN-2021'!I:I,1,FALSE) -> #N/A | BG93: [acuerdo fusionado con Universidade de Lisboa-Tecnico de Lisboa] | BL93: =VLOOKUP(E93,#REF!,1,FALSE) -> #REF!
A94: 93 | B94: University of Science and Technology - AGH | C94: Akademia Górniczo-Hutnicza im. Stanisława Staszica w Krakowie | D94: Cracovia | E94: PL KRAKOW02 | F94: PL | H94: 30 de abril (nomination) 17 de mayo (application) | I94: 04.30 | J94: 05.17 | L94: 05.30 | N94: ER | P94: SÍ | Q94: SÍ | R94: SÍ | S94: Electrical Engineering (Electronics and Automation) / Biomedical Engineering (Medical Diagnostic and Treatment Technology) | T94: Sí | U94: 2 | V94: 12 | W94: exchange@agh.edu.pl | X94: international office | Y94: SI | Z94: SI | AA94: SI | AB94: SI | AC94: SI | AD94: =_xlfn.TEXTJOIN("/",TRUE,IF(OfertaPlazas[[#This Row],[GITST]]="SI","GITST",""),IF(OfertaPlazas[[#This Row],[GIB]]="SI","GIB",""),IF(OfertaPlazas[[#This Row],[GISD]]="SI","GISD",""),IF(OfertaPlazas[[#This Row],[MASTER]]="SI","MASTER","")) -> GITST/GIB/GISD/MASTER | AE94: SI | AF94: SI | AG94: SI | AH94: SI | AI94: SI | AJ94: NO | AK94: NO | AL94: NO | AM94: NO | AN94: NO | AO94: SI | AP94: NO | AQ94: NO | AR94: NO | AS94: INGLÉS B2 | AT94: (certificado del departamento de lingüística aceptado) | AV94: Se añade el área 0610 Mayo 2025 para alumnos de GISD | BE94: =VLOOKUP(B94,'TEAMS_30-09-2021'!$D:$AG,30,FALSE) -> #N/A | BF94: =VLOOKUP(B94,'ENCUESTAS JUN-2021'!I:I,1,FALSE) -> #N/A | BG94: =VLOOKUP(B94,'TEAMS_30-09-2021'!D:D,1,FALSE) -> #N/A | BL94: =VLOOKUP(E94,#REF!,1,FALSE) -> #REF!
A95: 94 | B95: Cracow University of Technology- Politechnika Krakowska | C95: Politechnika Krakowska | D95: Cracovia | E95: PL KRAKOW03 | F95: PL | H95: 30 de abril (nomination) - 31 de mayo (application) | I95: 04.30 | J95: 05.31 | K95: 29 de septiembre (nomination) - 15 de noviembre (application) | L95: 09.29 | M95: 11.15 | N95: ER | P95: SÍ | S95: Electrical Engineering (Electronics and Automation) | T95: Sí | U95: 3 | V95: 12 | W95: erasmus@pk.edu.pl | X95: international office | Y95: SI | Z95: SI | AA95: NO | AB95: NO | AC95: SI | AD95: =_xlfn.TEXTJOIN("/",TRUE,IF(OfertaPlazas[[#This Row],[GITST]]="SI","GITST",""),IF(OfertaPlazas[[#This Row],[GIB]]="SI","GIB",""),IF(OfertaPlazas[[#This Row],[GISD]]="SI","GISD",""),IF(OfertaPlazas[[#This Row],[MASTER]]="SI","MASTER","")) -> GITST/MASTER | AE95: SI | AF95: SI | AG95: SI | AH95: SI | AI95: SI | AJ95: NO | AK95: NO | AL95: NO | AM95: NO | AN95: SI | AO95: SI | AP95: NO | AQ95: NO | AR95: NO | AS95: INGLÉS B1 | AT95: (vale el TOEIC con 2 competencias) | AU95: oferta de asignaturas: https://erasmus.pk.edu.pl/incoming-students/studies-at-cut-faculties-and-subjects/ Faculty of Electrical and Computer Engineering: dr inż. Damian Grela (dgrela@pk.edu.pl) | AW95: no envían ToR en papel y su ToR no es verificable. Aceptamos el ToR si lo envía la Universidad (EWP) | BE95: =VLOOKUP(B95,'TEAMS_30-09-2021'!$D:$AG,30,FALSE) -> 0 | BF95: =VLOOKUP(B95,'ENCUESTAS JUN-2021'!I:I,1,FALSE) -> Cracow University of Technology- Politechnika Krakowska | BG95: =VLOOKUP(B95,'TEAMS_30-09-2021'!D:D,1,FALSE) -> Cracow University of Technology- Politechnika Krakowska | BL95: =VLOOKUP(E95,#REF!,1,FALSE) -> #REF!
A96: 95 | B96: Technical University of Lodz | C96: Politechnika Lodzka | D96: Lodz | E96: PL LODZ02 | F96: PL | H96: 30 de junio (nomination) - 31 de julio (application) | I96: 06.30 | J96: 07.31 | K96: 30 de noviembre | L96: 11.30 | N96: ER | P96: SÍ | S96: Electrical Engineering (Electronics and Automation) | T96: Sí | U96: 2 | V96: 12 | W96: erasmus@info.p.lodz.pl | X96: international office | Y96: SI | Z96: SI | AA96: NO | AB96: NO | AC96: SI | AD96: =_xlfn.TEXTJOIN("/",TRUE,IF(OfertaPlazas[[#This Row],[GITST]]="SI","GITST",""),IF(OfertaPlazas[[#This Row],[GIB]]="SI","GIB",""),IF(OfertaPlazas[[#This Row],[GISD]]="SI","GISD",""),IF(OfertaPlazas[[#This Row],[MASTER]]="SI","MASTER","")) -> GITST/MASTER | AE96: SI | AF96: SI | AG96: SI | AH96: SI | AI96: SI | AJ96: SI | AK96: SI | AL96: SI | AM96: SI | AN96: SI | AO96: SI | AP96: SI | AQ96: SI | AR96: NO | AS96: INGLÉS B2 | AU96: Para los alumnos que van a realizar una movilidad de 3º de grado: No dejan coger asisnaturas de máster. | BE96: =VLOOKUP(B96,'TEAMS_30-09-2021'!$D:$AG,30,FALSE) -> 0 | BF96: =VLOOKUP(B96,'ENCUESTAS JUN-2021'!I:I,1,FALSE) -> #N/A | BG96: =VLOOKUP(B96,'TEAMS_30-09-2021'!D:D,1,FALSE) -> Technical University of Lodz | BL96: =VLOOKUP(E96,#REF!,1,FALSE) -> #REF!
A97: 96 | B97: Poznan University of Technology | C97: Politechnika Poznanska | D97: Poznan | E97: PL POZNAN02 | F97: PL | H97: 15 de mayo (nomination) - 31 de mayo (application) | I97: 05.15 | J97: 05.31 | K97: 31 de octubre (nomination) - 15 de noviembre (application) | L97: 10.31 | M97: 11.15 | N97: ER | P97: SÍ | R97: SÍ | S97: Electrical Engineering (Electronics and Automation) / Biomedical Engineering (Medical Diagnostic and Treatment Technology) | T97: Sí | U97: 4 | V97: 10 | W97: erasmus@put.poznan.pl | X97: international office | Y97: SI | Z97: SI | AA97: SI | AB97: NO | AC97: SI | AD97: =_xlfn.TEXTJOIN("/",TRUE,IF(OfertaPlazas[[#This Row],[GITST]]="SI","GITST",""),IF(OfertaPlazas[[#This Row],[GIB]]="SI","GIB",""),IF(OfertaPlazas[[#This Row],[GISD]]="SI","GISD",""),IF(OfertaPlazas[[#This Row],[MASTER]]="SI","MASTER","")) -> GITST/GIB/MASTER | AE97: SI | AF97: SI | AG97: SI | AH97: SI | AI97: SI | AJ97: SI | AK97: SI | AL97: SI | AM97: SI | AN97: SI | AO97: NO | AP97: NO | AQ97: SI | AR97: NO | AS97: INGLÉS B2 | AT97: (certificado del departamento de lingüística aceptado) | AU97: 2 alumnos en el área de teleco (2*12) y 2 alumnos en el área de bio (2*12) Se puede desdoblar el número de meses (8*5) | AV97: diciembre 2024: se añade el área GITST grado y se aumenta el nº de estudiantes de 2*10 a 4*10 (2 en cada área) / Grado BIO: en el 2025/26 nos comentó Ana Martínez que la Poznan University of Technology había informado que no iban a impartir el Master de Bio | BE97: =VLOOKUP(B97,'TEAMS_30-09-2021'!$D:$AG,30,FALSE) -> 0 | BF97: =VLOOKUP(B97,'ENCUESTAS JUN-2021'!I:I,1,FALSE) -> Poznan University of Technology | BG97: =VLOOKUP(B97,'TEAMS_30-09-2021'!D:D,1,FALSE) -> Poznan University of Technology | BL97: =VLOOKUP(E97,#REF!,1,FALSE) -> #REF!
A98: 97 | B98: Instituto Politécnico do Porto - Instituto Superior de Engenharia do Porto - ISEP | C98: Instituto Politécnico do Porto | D98: Porto | E98: P PORTO05 | F98: PT | H98: 1 de junio | I98: 06.01 | J98: 06.01 | K98: 15 de noviembre | L98: 11.15 | N98: ER | P98: SÍ | R98: SÍ | S98: Electrical Engineering (Electronics and Automation) / Biomedical Engineering (Medical Diagnosticand Treatment Technology) | T98: Sí | U98: 2 | V98: 12 | W98: gmsa@isep.ipp.pt | X98: Goreti Aráujo | Y98: SI | Z98: SI | AA98: SI | AB98: NO | AC98: SI | AD98: =_xlfn.TEXTJOIN("/",TRUE,IF(OfertaPlazas[[#This Row],[GITST]]="SI","GITST",""),IF(OfertaPlazas[[#This Row],[GIB]]="SI","GIB",""),IF(OfertaPlazas[[#This Row],[GISD]]="SI","GISD",""),IF(OfertaPlazas[[#This Row],[MASTER]]="SI","MASTER","")) -> GITST/GIB/MASTER | AE98: SI | AF98: SI | AG98: SI | AH98: SI | AI98: SI | AJ98: SI | AK98: SI | AL98: SI | AM98: SI | AN98: SI | AO98: SI | AP98: SI | AQ98: SI | AR98: NO | AS98: PORTUGUÉS B1 | AY98: Departamental (Facultad) | AZ98: 714 Electrical Engineering / 713 Electronics Engineering / 914 Biomedical Engineering | BA98: ISPE: School of Engineering | BB98: Instituto Politécnico do Porto: Head of International Relations Office: Carla Carneiro: gcri@sc.ipp.pt/ ISEP School of Engineering: Alexandra Trincao: relacoes.externas@isep.ipp.pt | BC98: ETSIT | BD98: Acuerdo: 0713/0714 Electrical Engineering/ 0914 Bimedical Engineering | BE98: =VLOOKUP(B98,'TEAMS_30-09-2021'!$D:$AG,30,FALSE) -> #N/A | BF98: =VLOOKUP(B98,'ENCUESTAS JUN-2021'!I:I,1,FALSE) -> #N/A | BG98: =VLOOKUP(B98,'TEAMS_30-09-2021'!D:D,1,FALSE) -> #N/A | BL98: =VLOOKUP(E98,#REF!,1,FALSE) -> #REF!
A99: 98 | B99: Rzeszów University of Technology | C99: Politechnika Rzeszowska | D99: Rzeszów | E99: PL RZESZOW01 | F99: PL | H99: 15 de junio (nomination) - 30 de junio (application) | I99: 06.15 | J99: 06.30 | K99: 15 de octubre (nomination) - 31 de octubre (application) | L99: 10.15 | M99: 10.31 | N99: ER | P99: SÍ | Q99: SÍ | R99: SÍ | S99: Electrical Engineering (Electronics and Automation) / ICTs / Biomedical Engineering | T99: Sí | U99: 2 | V99: 10 | W99: jruszel@prz.edu.pl (outgoing), monikas@prz.edu.pl(incoming) | X99: Joanna Ruszel | Y99: SI | Z99: SI | AA99: SI | AB99: SI | AC99: SI | AD99: =_xlfn.TEXTJOIN("/",TRUE,IF(OfertaPlazas[[#This Row],[GITST]]="SI","GITST",""),IF(OfertaPlazas[[#This Row],[GIB]]="SI","GIB",""),IF(OfertaPlazas[[#This Row],[GISD]]="SI","GISD",""),IF(OfertaPlazas[[#This Row],[MASTER]]="SI","MASTER","")) -> GITST/GIB/GISD/MASTER | AE99: SI | AF99: SI | AG99: SI | AH99: SI | AI99: SI | AJ99: SI | AK99: SI | AL99: SI | AM99: SI | AN99: SI | AO99: SI | AP99: SI | AQ99: SI | AR99: NO | AS99: INGLÉS B2 | BL99: =VLOOKUP(E99,#REF!,1,FALSE) -> #REF!
A100: 99 | B100: West Pomeranian University of Technology | C100: Zachodniopomorski Uniwersytet Technologiczny w Szczecinie | D100: Szczecin | E100: PL SZCZECI02 | F100: PL | H100: 1 de abril (nomination and application) ) | I100: 04.30 | J100: 04.30 | K100: 31 de octubre (nomination and application) | L100: 10.31 | M100: 10.31 | N100: ER | O100: SÍ | P100: SÍ | S100: Electrical Engineering (Electricity and Energy) / (Electronics and Automation) / Biomedical Engineering (Medical Diagnostic and Treatment Technology) | T100: Sí | U100: 2 | V100: 12 | W100: incoming@zut.edu.pl | X100: international office | Y100: SI | Z100: SI | AA100: NO | AB100: NO | AC100: SI | AD100: =_xlfn.TEXTJOIN("/",TRUE,IF(OfertaPlazas[[#This Row],[GITST]]="SI","GITST",""),IF(OfertaPlazas[[#This Row],[GIB]]="SI","GIB",""),IF(OfertaPlazas[[#This Row],[GISD]]="SI","GISD",""),IF(OfertaPlazas[[#This Row],[MASTER]]="SI","MASTER","")) -> GITST/MASTER | AE100: SI | AF100: SI | AG100: SI | AH100: SI | AI100: SI | AJ100: SI | AK100: SI | AL100: SI | AM100: SI | AN100: SI | AO100: SI | AP100: SI | AQ100: SI | AR100: NO | AS100: INGLÉS B2 | AV100: quitan el áre 914 (sept 2025) | BE100: =VLOOKUP(B100,'TEAMS_30-09-2021'!$D:$AG,30,FALSE) -> 0 | BF100: =VLOOKUP(B100,'ENCUESTAS JUN-2021'!I:I,1,FALSE) -> #N/A | BG100: =VLOOKUP(B100,'TEAMS_30-09-2021'!D:D,1,FALSE) -> West Pomeranian University of Technology | BL100: =VLOOKUP(E100,#REF!,1,FALSE) -> #REF!
...

Sheet Cancelan movilidad
A1: CANCELAN | B1: UNIVERSIDAD | C1: CIUDAD | D1: CÓDIGO ERASMUS | E1: PAIS | F1: Deadline 1 | G1: Deadline 2 | H1: Deadline | I1: Code SECD: 713-Electrical Engineering (Electricity and Energy) | J1: Code SECD: 714-Electrical Engineering (Electronics and Automation) | K1: Code SECD: 061-Computer Science (Information and Communication Technologies) | L1: Code SECD: 914-Biomedical Engineering (Medical Diagnostic and Treatment Technology) | M1: *code SECD 1 | N1: Area de Estudios | O1: code SECD 2 | P1: code SECD 3 | Q1: PROGRAMA | R1: Posibilidad de beca? | S1: PLAZAS | T1: MES | U1: E-mail contacto | V1: Persona de contacto | W1: GRADOS | X1: GITST | Y1: GIB | Z1: MASTER | AA1: S5 | AB1: S6 | AC1: C3 | AD1: S7 | AE1: S8 | AF1: S7+T | AG1: S8+T | AH1: C4º | AI1: C4º+T | AJ1: T | AK1: MS2ºAÑO (UN SEMESTRE) | AL1: MS2ºAÑO+TFM | AM1: TFM | AN1: DT(MASTER) | AO1: CERT | AP1: OBSERVACIONES | AQ1: OBSERVACIONES2 | AR1: ToR verificable | AS1: GICO_CODE | AT1: Acuerdo desde la Universidad de origen | AU1: Areas de estudios | AV1: Departamento Uni de destino | AW1: Contact | AX1: Acuerdo desde la ETSIT-UPM | AY1: Observaciones | AZ1: OBSERVACIONES (archivo Teams) | BA1: Universidades que contestaron la encuesta | BB1: UNIVERSIDADES QUE NO ESTÁN EN TEAMS
A2: Ver e-mail de Sabine Habermalz 26/11 | B2: Universität Ulm | C2: Ulm | D2: D ULM 01 | E2: DE | F2: 30 de abril (nomination) 15 de mayo (application) | G2: 31 de octubre (nomination) 15 de noviembre (application) | H2: 04.30 | J2: SÍ | M2: 714 | N2: Electrical Engineering (Electronics and Automation) | Q2: ER | R2: Sí | S2: 2 | T2: 12 | U2: erasmus@uni-ulm.de | V2: international office | W2: SI | X2: SI | Y2: NO | Z2: SI | AA2: SI | AB2: SI | AC2: SI | AD2: SI | AE2: SI | AF2: SI | AG2: SI | AH2: SI | AI2: SI | AJ2: SI | AK2: SI | AL2: SI | AM2: SI | AN2: NO | AO2: INGLÉS B1 o ALEMÁN B1 o ALEMÁN A2 + curso intensivo de alemán. Para ambos idiomas, se puede descargar el certificate of language proficiency que puede firmar el departamento de lingüística de la ETSIT) | AP2: Para realizar el TFG o TFM el alumno deberá solicitar el curso entero. Mínimo 180 ECTS superados para cursar asignaturas de Máster. | AT2: Departamental | AU2: Electronics and Automation | AV2: Institut für Mikro- und Nanomaterialien | AX2: ETSIT | AZ2: se añade el área 610 ICTs | BA2: Universität Ulm | BB2: Universität Ulm
B3: Technische Universiteit Delft | C3: Delft | D3: NL DELFT 01 | E3: NL | F3: 1 de marzo (nomination) - 1 de abril (aplication) | G3: 1 de octubre | H3: 03.01 | I3: SÍ | J3: SÍ | M3: 713 | N3: Electrical Engineering: (Electricity and Energy); (Electronics and Automation) | O3: 714 | Q3: ER | R3: Sí | S3: 4 | T3: 6 | U3: exchange-eemcs@tudelft.nl | V3: international office | W3: SI | X3: SI | Y3: NO | Z3: SI | AA3: SI | AB3: SI | AC3: SI | AD3: SI | AE3: SI | AF3: NO | AG3: NO | AH3: NO | AI3: NO | AJ3: NO | AK3: SI | AL3: NO | AM3: SI | AN3: NO | AO3: TOEFL iBT 90 o IELTS 6.5 o CPE o CAE | AP3: Asignaturas de Máster en inglés / Mínimo 180 ECTS superados para cursar asignaturas de Máster / TFG no. Extension of the exchange period is not possible . | AT3: Departamental | AU3: Electrical Engineering, Mathematics and Computer Sciences (713 (522)) | AX3: firma: AA // UPM (varias Escuelas) | AZ3: =VLOOKUP(B3,'TEAMS_30-09-2021'!$D:$AG,30,FALSE) -> 0 | BA3: =VLOOKUP(B3,'ENCUESTAS JUN-2021'!I:I,1,FALSE) -> #N/A | BB3: =VLOOKUP(B3,'TEAMS_30-09-2021'!D:D,1,FALSE) -> Technische Universiteit Delft
B4: Universiteit Gent* | C4: Gent | D4: B GENT 01 | E4: BE | F4: 15 de abril (nomination) 15 de mayo (application) | H4: 04.15 | I4: SÍ | M4: 713 | N4: Electrical Engineering (Electricity and Energy) | Q4: ER | R4: Sí | S4: 3 | T4: 5 | U4: QUITAR | W4: NO | X4: NO | Y4: NO | Z4: SI | AA4: NO | AB4: NO | AC4: NO | AD4: NO | AE4: NO | AF4: NO | AG4: NO | AH4: NO | AI4: NO | AJ4: NO | AK4: SI | AL4: SI | AM4: SI | AN4: NO | AO4: INGLES B2: TOEFL min 87 o IELTS 6,0 (min 6,0 in writing) o TOEIC min 785 o FCE, CAE, CPE o University language Center certifying a level B2 o HOLANDES B2 (proof that the student finished successfully a Dutch study programme of at least 1 year) | AQ4: La solicitud de alojamiento abre a ppio de abril así que es mejor hacer la e-nomination pronto aunque el deadline es 15/05 | AS4: GENT-1 | AT4: Departamental | AU4: Se quita | AX4: ETSIT | AZ4: =VLOOKUP(B4,'TEAMS_30-09-2021'!$D:$AG,30,FALSE) -> 0 | BB4: =VLOOKUP(B4,'TEAMS_30-09-2021'!D:D,1,FALSE) -> Universiteit Gent

Sheet Acuerdos no vigentes
A1: UNIVERSIDAD | B1: CIUDAD | C1: CÓDIGO ERASMUS | D1: PAÍS | E1: Deadline 1 FALL SEMESTER | F1: Deadline 1S NOMINACIÓN (OI) | G1: Deadline 1S APLICACIÓN (alumno) | H1: Deadline 2 SPRING SEMESTER | I1: Deadline 2S NOMINACIÓN (OI) | J1: Deadline 2S APLICACIÓN (alumno) | K1: PROGRAMA | L1: Code SECD: 713-Electrical Engineering (Electricity and Energy) | M1: Code SECD: 714-Electrical Engineering (Electronics and Automation) | N1: Code SECD: 061-Computer Science (Information and Communication Technologies) | O1: Code SECD: 914-Biomedical Engineering (Medical Diagnostic and Treatment Technology) | P1: Area de Estudios | Q1: Posibilidad de beca? | R1: PLAZAS | S1: MES | T1: E-mail contacto | U1: Persona de contacto | V1: GRADOS | W1: GITST | X1: GIB | Y1: GISD | Z1: MASTER | AA1: S5 | AB1: S6 | AC1: C3 | AD1: S7 | AE1: S8 | AF1: S7+T | AG1: S8+T | AH1: C4º | AI1: C4º+T | AJ1: T | AK1: MS2ºAÑO (UN SEMESTRE) | AL1: MS2ºAÑO+TFM | AM1: TFM | AN1: DT(MASTER) | AO1: CERT | AP1: OBSERVACIONES | AQ1: OBSERVACIONES2 | AR1: ToR verificable | AS1: GICO_CODE | AT1: Acuerdo desde la Universidad de origen | AU1: Areas de estudios | AV1: Departamento Uni de destino | AW1: Contact | AX1: Acuerdo desde la ETSIT-UPM | AY1: Observaciones | AZ1: OBSERVACIONES (archivo Teams) | BA1: Universidades que contestaron la encuesta | BB1: UNIVERSIDADES QUE NO ESTÁN EN TEAMS
A2: Universidad Católica de Salta | B2: Salta | D2: AR | K2: AB | L2: SI | M2: SI | N2: NO | O2: SI | P2: SI | Q2: SI | R2: 2 | S2: 6 | V2: SI | W2: SI | X2: NO | Y2: NO | Z2: SI | AA2: SI | AB2: NO | AC2: SI | AD2: NO
A3: Universidad Santo Tomas | B3: Bogotá | D3: CO | K3: AB | L3: SI | M3: SI | N3: NO | O3: NO | P3: SI | Q3: SI | R3: 2 | S3: 6 | V3: SI | W3: SI | X3: NO | Y3: NO | Z3: SI | AA3: SI | AB3: NO | AC3: SI | AD3: NO
A4: Universidad Nacional de Colombia | B4: Bogotá | D4: CO | K4: AB | L4: SI | M4: SI | N4: NO | O4: SI | P4: SI | Q4: SI | R4: 2 | S4: 12 | V4: NO | W4: NO | X4: SI | Y4: NO | Z4: NO | AA4: SI | AB4: NO | AC4: NO | AD4: NO
A6: VRIJE Universiteit Amsterdam | B6: Amsterdam | C6: NL AMSTERD 02 | D6: NL | E6: 1 de abril | F6: 1 de octubre | G6: 04.01 | H6: 061 | K6: ER | L6: 1 | M6: 12 | N6: SI | O6: SI | P6: NO | Q6: SI | R6: SI | S6: SI | T6: SI | U6: SI | V6: SI | W6: SI | X6: SI | Y6: SI | Z6: SI | AA6: SI | AB6: NO | AC6: INGLÉS C1 (IELTS 6.5 o TOEFL 92 o CAE o CPE) | AD6: El TFG/TFM se puede realizar unicamente en el departamento de Computer Science. Courses from field of Computer Science/Mathematics | AE6: No se oferta para el curso 2019-20: quieren cancelar el acuerdo
A7: Universidad Privada Boliviana | B7: Cochabamba | D7: BO | K7: AB | L7: SÍ | M7: SÍ | O7: SÍ | Q7: Sí | R7: 2 | S7: 10 | V7: SI | W7: SI | X7: SI | Y7: NO | Z7: NO | AA7: SI | AB7: SI | AC7: SI | AD7: SI | AE7: SI | AF7: SI | AG7: SI | AH7: SI | AI7: SI | AJ7: SI | AK7: NO | AL7: NO | AM7: NO | AN7: NO | AQ7: acuerdo válido hasta 24/25
A8: Universidad Militar Nueva Granada | B8: Bogotá | D8: CO | K8: AB | Q8: Sí | R8: 3 | S8: 6 | V8: SI | W8: SI | X8: SI | Y8: NO | Z8: SI | AA8: SI | AB8: SI | AC8: SI | AD8: SI | AE8: SI | AF8: SI | AG8: SI | AH8: SI | AI8: SI | AJ8: SI | AK8: SI | AL8: SI | AM8: SI | AN8: NO | AP8: se pueden juntar semestres e ir un curso completo | AQ8: acuerdo válido hasta el 2022/23
A9: Universidad EIA (Escuela de Ingenieria de Antioquia) | B9: Medellín | D9: CO | K9: AB | L9: si | M9: si | N9: no | O9: si | Q9: Sí | R9: 2 | S9: 12 | T9: manuela.velez69@eia.edu.co | U9: Jefe de Internacionalización: Manuela Vélez Restrepo | V9: SI | W9: SI | X9: SI | Y9: NO | Z9: SI | AA9: SI | AB9: SI | AC9: SI | AD9: SI | AE9: SI | AF9: SI | AG9: SI | AH9: SI | AI9: SI | AJ9: SI | AK9: SI | AL9: SI | AM9: SI | AN9: NO | AP9: Puede desdoblarse el número de plazas (4 plazas x 6 meses cada una) | AQ9: acuerdo válido hasta el 2023/2024
A10: Universidad Iberoamericana | B10: México | D10: MX | K10: AB | Q10: Sí | R10: 2 | S10: 12 | V10: SI | W10: NO | X10: SI | Y10: NO | Z10: SI | AA10: SI | AB10: SI | AC10: SI | AD10: SI | AE10: SI | AF10: SI | AG10: SI | AH10: SI | AI10: SI | AJ10: SI | AK10: SI | AL10: SI | AM10: SI | AN10: NO | AQ10: acuerdo válido hasta 2021/22 | BG10: =VLOOKUP(B10,#REF!,1,FALSE) -> #REF!
A11: North Carolina Agricultural and Technical State University | B11: North Carolina | D11: US | K11: AB | Q11: Sí | R11: 2 | S11: 12 | V11: NO | W11: NO | X11: NO | Z11: SI | AA11: NO | AB11: NO | AC11: NO | AD11: NO | AE11: NO | AF11: NO | AG11: NO | AH11: NO | AI11: NO | AJ11: NO | AK11: SI | AL11: SI | AM11: SI | AN11: NO | AO11: INGLÉS B2
A12: Instituto Mauá de Tecnología | B12: Sao Paulo | D12: BR | K12: AB | Q12: Sí | R12: 2 | S12: 12 | T12: relacoes-internacionais@maua.br | U12: Julia Carneiro | V12: SI | W12: SI | X12: NO | Z12: NO | AA12: SI | AB12: SI | AC12: SI | AD12: SI | AE12: SI | AF12: SI | AG12: SI | AH12: SI | AI12: SI | AJ12: SI | AK12: NO | AL12: NO | AM12: NO | AN12: NO | AO12: PORTUGUES B1 | AP12: .
A13: Universidad Técnica Particular de Loja | B13: Loja | D13: EC | K13: AB | BG13: =VLOOKUP(B13,#REF!,1,FALSE) -> #REF!
A14: Universidad Tecnológica de Tehuacán | B14: Tehuacán | D14: MX | K14: AB
A15: Universidad de Granada | B15: Granada | D15: ES | K15: SICUE | Q15: Sí | R15: 1 | S15: 12 | V15: NO | W15: NO | X15: NO | Y15: NO | Z15: NO | AA15: NO | AB15: NO | AC15: NO | AD15: NO | AE15: NO | AF15: NO | AG15: NO | AH15: NO | AI15: NO | AJ15: NO | AK15: SI | AL15: SI | AM15: SI | AN15: NO | AQ15: Nuevo acuerdo firmado Noviembre 2020. Es posible desdoblar el número de plazas=2 alumnos para 1 semestre
A16: Universidad Nacional de Ingeniería | B16: Rímac (Callao) | D16: PE | K16: AB | Q16: Sí | R16: 2 | S16: 10 | V16: SI | W16: SI | X16: SI | Y16: NO | Z16: SI | AA16: SI | AB16: SI | AC16: SI | AD16: SI | AE16: SI | AF16: SI | AG16: SI | AH16: SI | AI16: SI | AJ16: SI | AK16: SI | AL16: SI | AM16: SI | AN16: NO | AQ16: acuerdo válido hasta 2022/23 | BG16: =VLOOKUP(B16,#REF!,1,FALSE) -> #REF!
A17: King's College, University of London | B17: Londres | C17: UK LONDON017 | D17: UK | E17: 15 de marzo (e-nomination) - 31 de marzo (application) | F17: 03.15 | G17: 03.31 | H17: 31 de octubre | I17: 03.15 | K17: AB | M17: SÍ | P17: Electrical Engineering (Electronics and Automation) | Q17: No | R17: 2 | S17: 12 | V17: SI | W17: SI | X17: NO | Y17: NO | Z17: SI | AA17: SI | AB17: SI | AC17: SI | AD17: SI | AE17: SI | AF17: SI | AG17: SI | AH17: SI | AI17: SI | AJ17: SI | AK17: SI | AL17: NO | AM17: NO | AN17: NO | AO17: INGLÉS C1 (IELTS: 7.0; minimum of 6.5 in all four skills / CAE 185 overall; minimum 176 in all skills / CPE 185 overall; minimum 176 in each skill / PTE 69 overall, with a minimum of 62 in each skill / TOEFL 100 overall with a minimum of 25 in writing and 23 in each of the other skills / Trinity College London Integrated Skills in English (ISE): Level III (ISEIII) with merit in each skill). Band B of the College’s Language Requirements | AP17: Se requiere un GPA de 3/4 | AQ17: no se oferta en el 2023/24 ni en 2024/25 | AZ17: =VLOOKUP(#REF!,'TEAMS_30-09-2021'!$D:$AG,30,FALSE) -> #REF! | BA17: =VLOOKUP(#REF!,'ENCUESTAS JUN-2021'!F:F,1,FALSE) -> #REF! | BB17: =VLOOKUP(#REF!,'TEAMS_30-09-2021'!A:A,1,FALSE) -> #REF! | BG17: =VLOOKUP(B17,#REF!,1,FALSE) -> #REF!
A18: École Polytechnique | B18: Palaiseau | C18: F PALAISE01 | D18: FR | E18: 15 de marzo (nomination) - 1 de abril (application) | F18: 03.15 | G18: 04.01 | I18: 04.17 | K18: ER | M18: SÍ | P18: Electrical Engineering (Electronics and Automation) | Q18: Sí | R18: 3 | S18: 12 | T18: angelica.nivia@polytechnique.edu | U18: Angélica Nivia | V18: NO | W18: NO | X18: NO | Y18: NO | Z18: SI | AA18: NO | AB18: NO | AC18: NO | AD18: NO | AE18: NO | AF18: NO | AG18: NO | AH18: NO | AI18: NO | AJ18: NO | AK18: SI | AL18: SI | AM18: SI | AN18: NO | AO18: INGLÉS B2 o FRANCÉS B2 | AP18: NO ESTÁ ACTIVO EL ACUERDO ERASMUS: NO SE OFERTA | AQ18: Enviado una propuesta en julio 2018 a Elena Muré pero sin respuesta: A RETOMAR | AT18: no está? | AZ18: =VLOOKUP(#REF!,'TEAMS_30-09-2021'!$D:$AG,30,FALSE) -> #REF! | BA18: =VLOOKUP(#REF!,'ENCUESTAS JUN-2021'!F:F,1,FALSE) -> #REF! | BB18: =VLOOKUP(#REF!,'TEAMS_30-09-2021'!A:A,1,FALSE) -> #REF! | BG18: =VLOOKUP(B18,#REF!,1,FALSE) -> #REF!

Sheet ENCUESTAS JUN-2021
A1: ID | B1: Hora de inicio | C1: Hora de finalización | D1: Correo electrónico | E1: Nombre | F1: Language | G1: Select your country | H1: UNIVERSIDAD | I1: Nombre Universidad (OFERTA DE PLAZAS) | J1: Código Erasmus | K1: Select the name of your University (Austria) | L1: Select the name of your University (Belgium) | M1: Select the name of your University (Bulgary) | N1: Select the name of your University (Czech Rep.) | O1: Select the name of your University (Denmark) | P1: Select the name of your University (Finland) | Q1: Select the name of your University (France) | R1: Select the name of your University (Germany) | S1: Select the name of your University (Greece) | T1: Select the name of your University (Ireland) | U1: Select the name of your University (Italy) | V1: Select the name of your University (Netherlands) | W1: Select the name of your University (Norway) | X1: Select the name of your University (North Macedonia) | Y1: Select the name of your University (Poland) | Z1: Select the name of your University (Portugal) | AA1: Select the name of your University (Romania) | AB1: Select the name of your University (Slovenia) | AC1: Select the name of your University (Sweden) | AD1: Select the name of your University (Switzerland) | AE1: Select the name of your University (Turkey) | AF1: Select the name of your University (UK) | AG1: Please, introduce the Erasmus Code for your University, if the one shown in the previous drop-up menu was incorrect | AH1: Name/Surname of the International Office Coordinator of your University | AI1: e-mail address of the International Office Coordinator | AJ1: Your Name and Surname | AK1: Your function in the International Office | AL1: Your e-mail address | AM1: Would you like to adjust the current number of slots? | AN1: Please, indicate an initial proposal with the number of students (slots) you would like to increase. We will contact you to fix the final number. | AO1: Please, indicate an initial proposal with the number of students (slots) you would like to decrease. We will contact you to fix the final number. | AP1: We are interested in offering 3rd study cycle exchange. Would you agree to exchange students in this 3rd study cycle? | AQ1: Our current fields of study are: - Electrical Engineering: (714 Electronics and automation / 713 Electricity and energy) - ICTs: (611 Computer Use / 612 DB an... | AR1: In which domains would you like to START a new student exchange program with ETS Telecomunicacion-UPM (Spain)? (several options are possible) | AS1: Please, indicate an initial proposal with the number of students (slots) and months per each NEW field of study | AT1: If you have any additional comments, please fill in the box
A2: 11 | B2: 44363.601 | C2: 44363.602 | D2: anonymous | F2: Español (España, alfabetización internacional) | G2: Finland | H2: =CONCATENATE('ENCUESTAS JUN-2021'!$K2,'ENCUESTAS JUN-2021'!$L2,'ENCUESTAS JUN-2021'!$M2,'ENCUESTAS JUN-2021'!$N2,'ENCUESTAS JUN-2021'!$O2,'ENCUESTAS JUN-2021'!$P2,'ENCUESTAS JUN-2021'!$Q2,'ENCUESTAS JUN-2021'!$R2,'ENCUESTAS JUN-2021'!$S2,'ENCUESTAS JUN-2021'!$T2,'ENCUESTAS JUN-2021'!$U2,'ENCUESTAS JUN-2021'!$V2,'ENCUESTAS JUN-2021'!$W2,'ENCUESTAS JUN-2021'!$X2,'ENCUESTAS JUN-2021'!$Y2,'ENCUESTAS JUN-2021'!$Z2,'ENCUESTAS JUN-2021'!$AA2,'ENCUESTAS JUN-2021'!$AB2,'ENCUESTAS JUN-2021'!$AC2,'ENCUESTAS JUN-2021'!$AD2,'ENCUESTAS JUN-2021'!$AE2,'ENCUESTAS JUN-2021'!$AF2) -> University of Oulu (SF OULU 01) | I2: University of Oulu | J2: SF OULU 01 | P2: University of Oulu (SF OULU 01) | AG2: oulu | AH2: jj | AI2: jj | AJ2: uu | AK2: jj | AL2: jj | AM2: Yes, we would like to decrease the current number of slots | AO2: 1 | AP2: Yes | AQ2: Yes | AR2: Computer Science (06); | AS2: 2 | AT2: lll
A3: 12 | B3: 44364.355 | C3: 44364.358 | D3: anonymous | F3: Español (España, alfabetización internacional) | G3: France | H3: =CONCATENATE('ENCUESTAS JUN-2021'!$K3,'ENCUESTAS JUN-2021'!$L3,'ENCUESTAS JUN-2021'!$M3,'ENCUESTAS JUN-2021'!$N3,'ENCUESTAS JUN-2021'!$O3,'ENCUESTAS JUN-2021'!$P3,'ENCUESTAS JUN-2021'!$Q3,'ENCUESTAS JUN-2021'!$R3,'ENCUESTAS JUN-2021'!$S3,'ENCUESTAS JUN-2021'!$T3,'ENCUESTAS JUN-2021'!$U3,'ENCUESTAS JUN-2021'!$V3,'ENCUESTAS JUN-2021'!$W3,'ENCUESTAS JUN-2021'!$X3,'ENCUESTAS JUN-2021'!$Y3,'ENCUESTAS JUN-2021'!$Z3,'ENCUESTAS JUN-2021'!$AA3,'ENCUESTAS JUN-2021'!$AB3,'ENCUESTAS JUN-2021'!$AC3,'ENCUESTAS JUN-2021'!$AD3,'ENCUESTAS JUN-2021'!$AE3,'ENCUESTAS JUN-2021'!$AF3) -> Ecole Nationale Supérieure de l'Electronique et de ses Applications-ENSEA (F CERGY 01) | I3: Ecole Nationale Supérieure de l'Electronique et de ses Applications (ENSEA) | J3: F CERGY 01 | Q3: Ecole Nationale Supérieure de l'Electronique et de ses Applications-ENSEA (F CERGY 01) | AH3: Céline CABRERA | AI3: ri@ensea.fr | AJ3: Eneko CHIPI | AK3: Director of international relations | AL3: eneko.chipi@ensea.fr | AM3: No, no additional adjustment of the current number of slots is required | AP3: Yes | AQ3: No | AT3: We are delighted with our cooperation and would be glad and honoured to renew it in the same conditions. If necessary for your side, we are open to any modification.
A4: 13 | B4: 44364.55 | C4: 44364.557 | D4: anonymous | F4: Español (España, alfabetización internacional) | G4: France | H4: =CONCATENATE('ENCUESTAS JUN-2021'!$K4,'ENCUESTAS JUN-2021'!$L4,'ENCUESTAS JUN-2021'!$M4,'ENCUESTAS JUN-2021'!$N4,'ENCUESTAS JUN-2021'!$O4,'ENCUESTAS JUN-2021'!$P4,'ENCUESTAS JUN-2021'!$Q4,'ENCUESTAS JUN-2021'!$R4,'ENCUESTAS JUN-2021'!$S4,'ENCUESTAS JUN-2021'!$T4,'ENCUESTAS JUN-2021'!$U4,'ENCUESTAS JUN-2021'!$V4,'ENCUESTAS JUN-2021'!$W4,'ENCUESTAS JUN-2021'!$X4,'ENCUESTAS JUN-2021'!$Y4,'ENCUESTAS JUN-2021'!$Z4,'ENCUESTAS JUN-2021'!$AA4,'ENCUESTAS JUN-2021'!$AB4,'ENCUESTAS JUN-2021'!$AC4,'ENCUESTAS JUN-2021'!$AD4,'ENCUESTAS JUN-2021'!$AE4,'ENCUESTAS JUN-2021'!$AF4) -> Centrale SUPELEC (F GIF-YVE 03) | I4: Centrale SUPELEC | J4: F GIF-YVE 03 | Q4: Centrale SUPELEC (F GIF-YVE 03) | AH4: Marc ZOLVER, Dean of International Relations at CentraleSupélec | AI4: marc.zolver@centralesupelec.fr | AJ4: Carine MOROTTI DELORME | AK4: Head of Study Abroad Programmes and Coordinator for Spain | AL4: carine.morotti-delorme@centralesupelec.fr | AM4: No, no additional adjustment of the current number of slots is required | AP4: No | AQ4: No | AT4: Buenas tardes, me parece que le convenio de renovavión entre la UPM ETSIT y el grupo Ecole Centrale está tramitando y por lo tanto estamos al día con respecto a los campos de estudios ofertados. Gracias.
A5: 14 | B5: 44364.58 | C5: 44364.582 | D5: anonymous | F5: Español (España, alfabetización internacional) | G5: France | H5: =CONCATENATE('ENCUESTAS JUN-2021'!$K5,'ENCUESTAS JUN-2021'!$L5,'ENCUESTAS JUN-2021'!$M5,'ENCUESTAS JUN-2021'!$N5,'ENCUESTAS JUN-2021'!$O5,'ENCUESTAS JUN-2021'!$P5,'ENCUESTAS JUN-2021'!$Q5,'ENCUESTAS JUN-2021'!$R5,'ENCUESTAS JUN-2021'!$S5,'ENCUESTAS JUN-2021'!$T5,'ENCUESTAS JUN-2021'!$U5,'ENCUESTAS JUN-2021'!$V5,'ENCUESTAS JUN-2021'!$W5,'ENCUESTAS JUN-2021'!$X5,'ENCUESTAS JUN-2021'!$Y5,'ENCUESTAS JUN-2021'!$Z5,'ENCUESTAS JUN-2021'!$AA5,'ENCUESTAS JUN-2021'!$AB5,'ENCUESTAS JUN-2021'!$AC5,'ENCUESTAS JUN-2021'!$AD5,'ENCUESTAS JUN-2021'!$AE5,'ENCUESTAS JUN-2021'!$AF5) -> Institut d'Optique Théorique et Appliquée (F ORSAY 02) | I5: Institut d'Optique Théorique et Appliquée | J5: F ORSAY 02 | Q5: Institut d'Optique Théorique et Appliquée (F ORSAY 02) | AH5: Pierre BALADI | AI5: pierre.baladi@institutoptique.fr | AJ5: Pierre BALADI | AK5: Head of International Relations | AL5: pierre.baladi@institutoptique.fr | AM5: No, no additional adjustment of the current number of slots is required | AP5: Yes | AQ5: No | AT5: Thanks for this initiative! We are looking forward to continue our cooperation with UPM / ETSIT!
A6: 15 | B6: 44364.582 | C6: 44364.583 | D6: anonymous | F6: Español (España, alfabetización internacional) | G6: France | H6: =CONCATENATE('ENCUESTAS JUN-2021'!$K6,'ENCUESTAS JUN-2021'!$L6,'ENCUESTAS JUN-2021'!$M6,'ENCUESTAS JUN-2021'!$N6,'ENCUESTAS JUN-2021'!$O6,'ENCUESTAS JUN-2021'!$P6,'ENCUESTAS JUN-2021'!$Q6,'ENCUESTAS JUN-2021'!$R6,'ENCUESTAS JUN-2021'!$S6,'ENCUESTAS JUN-2021'!$T6,'ENCUESTAS JUN-2021'!$U6,'ENCUESTAS JUN-2021'!$V6,'ENCUESTAS JUN-2021'!$W6,'ENCUESTAS JUN-2021'!$X6,'ENCUESTAS JUN-2021'!$Y6,'ENCUESTAS JUN-2021'!$Z6,'ENCUESTAS JUN-2021'!$AA6,'ENCUESTAS JUN-2021'!$AB6,'ENCUESTAS JUN-2021'!$AC6,'ENCUESTAS JUN-2021'!$AD6,'ENCUESTAS JUN-2021'!$AE6,'ENCUESTAS JUN-2021'!$AF6) -> HEC (F JOUY-JO 02) | I6: HEC | J6: F JOUY-JO 02 | Q6: HEC (F JOUY-JO 02) | AH6: Iris Ritter | AI6: ritter@hec.fr | AJ6: Iris Ritter | AK6: Director | AL6: ritter@hec.fr | AM6: No, no additional adjustment of the current number of slots is required | AP6: No | AQ6: No
A7: 16 | B7: 44364.603 | C7: 44364.606 | D7: anonymous | F7: Español (España, alfabetización internacional) | G7: Turkey | H7: =CONCATENATE('ENCUESTAS JUN-2021'!$K7,'ENCUESTAS JUN-2021'!$L7,'ENCUESTAS JUN-2021'!$M7,'ENCUESTAS JUN-2021'!$N7,'ENCUESTAS JUN-2021'!$O7,'ENCUESTAS JUN-2021'!$P7,'ENCUESTAS JUN-2021'!$Q7,'ENCUESTAS JUN-2021'!$R7,'ENCUESTAS JUN-2021'!$S7,'ENCUESTAS JUN-2021'!$T7,'ENCUESTAS JUN-2021'!$U7,'ENCUESTAS JUN-2021'!$V7,'ENCUESTAS JUN-2021'!$W7,'ENCUESTAS JUN-2021'!$X7,'ENCUESTAS JUN-2021'!$Y7,'ENCUESTAS JUN-2021'!$Z7,'ENCUESTAS JUN-2021'!$AA7,'ENCUESTAS JUN-2021'!$AB7,'ENCUESTAS JUN-2021'!$AC7,'ENCUESTAS JUN-2021'!$AD7,'ENCUESTAS JUN-2021'!$AE7,'ENCUESTAS JUN-2021'!$AF7) -> Namik Kemal University (TR TEKIRDAG 01) | I7: Namik Kemal University | J7: TR TEKIRDAG 01 | AE7: Namik Kemal University (TR TEKIRDAG 01) | AG7: TR TEKIRDA01 | AH7: Hasan Selçuk ETİ | AI7: hseti@nku.edu.tr | AJ7: Serkan Erdur | AK7: Erasmus officer | AL7: serkanerdur@nku.edu.tr | AM7: No, no additional adjustment of the current number of slots is required | AP7: Yes | AQ7: No
A8: 17 | B8: 44364.657 | C8: 44364.659 | D8: anonymous | F8: Español (España, alfabetización internacional) | G8: Portugal | H8: =CONCATENATE('ENCUESTAS JUN-2021'!$K8,'ENCUESTAS JUN-2021'!$L8,'ENCUESTAS JUN-2021'!$M8,'ENCUESTAS JUN-2021'!$N8,'ENCUESTAS JUN-2021'!$O8,'ENCUESTAS JUN-2021'!$P8,'ENCUESTAS JUN-2021'!$Q8,'ENCUESTAS JUN-2021'!$R8,'ENCUESTAS JUN-2021'!$S8,'ENCUESTAS JUN-2021'!$T8,'ENCUESTAS JUN-2021'!$U8,'ENCUESTAS JUN-2021'!$V8,'ENCUESTAS JUN-2021'!$W8,'ENCUESTAS JUN-2021'!$X8,'ENCUESTAS JUN-2021'!$Y8,'ENCUESTAS JUN-2021'!$Z8,'ENCUESTAS JUN-2021'!$AA8,'ENCUESTAS JUN-2021'!$AB8,'ENCUESTAS JUN-2021'!$AC8,'ENCUESTAS JUN-2021'!$AD8,'ENCUESTAS JUN-2021'!$AE8,'ENCUESTAS JUN-2021'!$AF8) -> Instituto Politécnico do Porto (P PORTO 05) | I8: Instituto Politécnico do Porto | J8: P PORTO 05 | Z8: Instituto Politécnico do Porto (P PORTO 05) | AH8: Carla Carneiro | AI8: carlac@sc.ipp.pt | AJ8: Alexandra Trincão | AK8: Head of International of ISEP ( School of Engineering POrto Polytechnic) | AL8: relacoes.externas@isep.ipp.pt | AM8: No, no additional adjustment of the current number of slots is required | AP8: No | AQ8: No
A9: 18 | B9: 44364.656 | C9: 44364.659 | D9: anonymous | F9: Español (España, alfabetización internacional) | G9: Germany | H9: =CONCATENATE('ENCUESTAS JUN-2021'!$K9,'ENCUESTAS JUN-2021'!$L9,'ENCUESTAS JUN-2021'!$M9,'ENCUESTAS JUN-2021'!$N9,'ENCUESTAS JUN-2021'!$O9,'ENCUESTAS JUN-2021'!$P9,'ENCUESTAS JUN-2021'!$Q9,'ENCUESTAS JUN-2021'!$R9,'ENCUESTAS JUN-2021'!$S9,'ENCUESTAS JUN-2021'!$T9,'ENCUESTAS JUN-2021'!$U9,'ENCUESTAS JUN-2021'!$V9,'ENCUESTAS JUN-2021'!$W9,'ENCUESTAS JUN-2021'!$X9,'ENCUESTAS JUN-2021'!$Y9,'ENCUESTAS JUN-2021'!$Z9,'ENCUESTAS JUN-2021'!$AA9,'ENCUESTAS JUN-2021'!$AB9,'ENCUESTAS JUN-2021'!$AC9,'ENCUESTAS JUN-2021'!$AD9,'ENCUESTAS JUN-2021'!$AE9,'ENCUESTAS JUN-2021'!$AF9) -> TUHH Technische Universität Hamburg-Harburg (D HAMBURG 03) | I9: Hamburg University of Technology | J9: D HAMBURG 03 | R9: TUHH Technische Universität Hamburg-Harburg (D HAMBURG 03) | AG9: The code is correct, but the name has changed to Technische Universität Hamburg | AH9: Elvira Wilberg | AI9: wilberg@tuhh.de | AJ9: Elvira Wilberg | AK9: Director | AL9: wilberg@tuhh.de | AM9: No, no additional adjustment of the current number of slots is required | AP9: No | AQ9: Yes | AR9: Computer Science (06); | AS9: 2
A10: 19 | B10: 44364.701 | C10: 44364.704 | D10: anonymous | F10: Español (España, alfabetización internacional) | G10: Belgium | H10: =CONCATENATE('ENCUESTAS JUN-2021'!$K10,'ENCUESTAS JUN-2021'!$L10,'ENCUESTAS JUN-2021'!$M10,'ENCUESTAS JUN-2021'!$N10,'ENCUESTAS JUN-2021'!$O10,'ENCUESTAS JUN-2021'!$P10,'ENCUESTAS JUN-2021'!$Q10,'ENCUESTAS JUN-2021'!$R10,'ENCUESTAS JUN-2021'!$S10,'ENCUESTAS JUN-2021'!$T10,'ENCUESTAS JUN-2021'!$U10,'ENCUESTAS JUN-2021'!$V10,'ENCUESTAS JUN-2021'!$W10,'ENCUESTAS JUN-2021'!$X10,'ENCUESTAS JUN-2021'!$Y10,'ENCUESTAS JUN-2021'!$Z10,'ENCUESTAS JUN-2021'!$AA10,'ENCUESTAS JUN-2021'!$AB10,'ENCUESTAS JUN-2021'!$AC10,'ENCUESTAS JUN-2021'!$AD10,'ENCUESTAS JUN-2021'!$AE10,'ENCUESTAS JUN-2021'!$AF10) -> Université de Liège (B LIEGE 01) | I10: Université de Liège | J10: B LIEGE 01 | L10: Université de Liège (B LIEGE 01) | AH10: Mrs. Dominique d'Arripe (Institutional Coordinator) | AI10: dominique.darripe@uliege.be | AJ10: Christine REYNDERS | AK10: International Officer (in charge of bilateral agreements) | AL10: christine.reynders@uliege.be | AM10: No, no additional adjustment of the current number of slots is required | AP10: No | AQ10: No | AT10: We will use our in-house system to be connected to EWP. It will be ready during this winter. In the menatime, we can extend our agreement for one additional year without any formalities, and proceed with official renewal as soon as our tool is ready for extending beyond 2022-2023.
A11: 20 | B11: 44365.403 | C11: 44365.406 | D11: anonymous | F11: Español (España, alfabetización internacional) | G11: Belgium | H11: =CONCATENATE('ENCUESTAS JUN-2021'!$K11,'ENCUESTAS JUN-2021'!$L11,'ENCUESTAS JUN-2021'!$M11,'ENCUESTAS JUN-2021'!$N11,'ENCUESTAS JUN-2021'!$O11,'ENCUESTAS JUN-2021'!$P11,'ENCUESTAS JUN-2021'!$Q11,'ENCUESTAS JUN-2021'!$R11,'ENCUESTAS JUN-2021'!$S11,'ENCUESTAS JUN-2021'!$T11,'ENCUESTAS JUN-2021'!$U11,'ENCUESTAS JUN-2021'!$V11,'ENCUESTAS JUN-2021'!$W11,'ENCUESTAS JUN-2021'!$X11,'ENCUESTAS JUN-2021'!$Y11,'ENCUESTAS JUN-2021'!$Z11,'ENCUESTAS JUN-2021'!$AA11,'ENCUESTAS JUN-2021'!$AB11,'ENCUESTAS JUN-2021'!$AC11,'ENCUESTAS JUN-2021'!$AD11,'ENCUESTAS JUN-2021'!$AE11,'ENCUESTAS JUN-2021'!$AF11) -> Katholike Universiteit Leuven (B LEUVEN 01) | I11: Katholike Universiteit Leuven | J11: B LEUVEN 01 | L11: Katholike Universiteit Leuven (B LEUVEN 01) | AG11: B LEUVEN | AH11: Pascale Conard | AI11: pascale.conard@kuleuven.be | AJ11: Pascale Conard | AK11: Policy Advisor | AL11: pascale.conard@kuleuven.be | AM11: No, no additional adjustment of the current number of slots is required | AP11: Yes | AQ11: Yes | AR11: Energy Engineering (0713); | AS11: 2 x 10 months | AT11: details of new agreement to be discussed
A12: 21 | B12: 44365.45 | C12: 44365.452 | D12: anonymous | F12: Español (España, alfabetización internacional) | G12: Poland | H12: =CONCATENATE('ENCUESTAS JUN-2021'!$K12,'ENCUESTAS JUN-2021'!$L12,'ENCUESTAS JUN-2021'!$M12,'ENCUESTAS JUN-2021'!$N12,'ENCUESTAS JUN-2021'!$O12,'ENCUESTAS JUN-2021'!$P12,'ENCUESTAS JUN-2021'!$Q12,'ENCUESTAS JUN-2021'!$R12,'ENCUESTAS JUN-2021'!$S12,'ENCUESTAS JUN-2021'!$T12,'ENCUESTAS JUN-2021'!$U12,'ENCUESTAS JUN-2021'!$V12,'ENCUESTAS JUN-2021'!$W12,'ENCUESTAS JUN-2021'!$X12,'ENCUESTAS JUN-2021'!$Y12,'ENCUESTAS JUN-2021'!$Z12,'ENCUESTAS JUN-2021'!$AA12,'ENCUESTAS JUN-2021'!$AB12,'ENCUESTAS JUN-2021'!$AC12,'ENCUESTAS JUN-2021'!$AD12,'ENCUESTAS JUN-2021'!$AE12,'ENCUESTAS JUN-2021'!$AF12) -> Cracow University of Technology- Politechnika Krakowska (PL KRAKOW 03) | I12: Cracow University of Technology- Politechnika Krakowska | J12: PL KRAKOW 03 | Y12: Cracow University of Technology- Politechnika Krakowska (PL KRAKOW 03) | AG12: PL KRAKOW03 | AH12: Daria Majka-Sitko | AI12: dmajka-sitko@pk.edu.pl | AJ12: Joanna Bebak | AK12: Faculty Erasmus Coordinator at Faculty of Electrical and Computer Engineering | AL12: dgrela@pk.edu.pl | AM12: No, no additional adjustment of the current number of slots is required | AP12: No | AQ12: No
A13: 22 | B13: 44365.471 | C13: 44365.487 | D13: anonymous | F13: Español (España, alfabetización internacional) | G13: Germany | H13: =CONCATENATE('ENCUESTAS JUN-2021'!$K13,'ENCUESTAS JUN-2021'!$L13,'ENCUESTAS JUN-2021'!$M13,'ENCUESTAS JUN-2021'!$N13,'ENCUESTAS JUN-2021'!$O13,'ENCUESTAS JUN-2021'!$P13,'ENCUESTAS JUN-2021'!$Q13,'ENCUESTAS JUN-2021'!$R13,'ENCUESTAS JUN-2021'!$S13,'ENCUESTAS JUN-2021'!$T13,'ENCUESTAS JUN-2021'!$U13,'ENCUESTAS JUN-2021'!$V13,'ENCUESTAS JUN-2021'!$W13,'ENCUESTAS JUN-2021'!$X13,'ENCUESTAS JUN-2021'!$Y13,'ENCUESTAS JUN-2021'!$Z13,'ENCUESTAS JUN-2021'!$AA13,'ENCUESTAS JUN-2021'!$AB13,'ENCUESTAS JUN-2021'!$AC13,'ENCUESTAS JUN-2021'!$AD13,'ENCUESTAS JUN-2021'!$AE13,'ENCUESTAS JUN-2021'!$AF13) -> RWTH - Aachen (D AACHEN 01) | I13: RWTH - Aachen | J13: D AACHEN 01 | R13: RWTH - Aachen (D AACHEN 01) | AH13: Dr.-Ing. Kerstin Jenkes | AI13: international@fb6.rwth-aachen.de | AJ13: Heike Hagena | AK13: Departmental Exchange Advisor | AL13: international@fb6.rwth-aachen.de | AM13: No, no additional adjustment of the current number of slots is required | AP13: No | AQ13: No
A14: 23 | B14: 44365.529 | C14: 44365.533 | D14: anonymous | F14: Español (España, alfabetización internacional) | G14: Finland | H14: =CONCATENATE('ENCUESTAS JUN-2021'!$K14,'ENCUESTAS JUN-2021'!$L14,'ENCUESTAS JUN-2021'!$M14,'ENCUESTAS JUN-2021'!$N14,'ENCUESTAS JUN-2021'!$O14,'ENCUESTAS JUN-2021'!$P14,'ENCUESTAS JUN-2021'!$Q14,'ENCUESTAS JUN-2021'!$R14,'ENCUESTAS JUN-2021'!$S14,'ENCUESTAS JUN-2021'!$T14,'ENCUESTAS JUN-2021'!$U14,'ENCUESTAS JUN-2021'!$V14,'ENCUESTAS JUN-2021'!$W14,'ENCUESTAS JUN-2021'!$X14,'ENCUESTAS JUN-2021'!$Y14,'ENCUESTAS JUN-2021'!$Z14,'ENCUESTAS JUN-2021'!$AA14,'ENCUESTAS JUN-2021'!$AB14,'ENCUESTAS JUN-2021'!$AC14,'ENCUESTAS JUN-2021'!$AD14,'ENCUESTAS JUN-2021'!$AE14,'ENCUESTAS JUN-2021'!$AF14) -> South-Eastern Finland University of Applied Sciences XAMK (SF MIKKELI 06) | I14: South-Eastern Finland University of Applied Sciences XAMK | J14: SF MIKKELI 06 | P14: South-Eastern Finland University of Applied Sciences XAMK (SF MIKKELI 06) | AG14: SF MIKKELI07 | AH14: Eeva Virtanen | AI14: eeva.virtanen@xamk.fi | AJ14: Eeva Virtanen | AK14: Institutional Erasmus Coordinator | AL14: eeva.virtanen@xamk.fi | AM14: No, no additional adjustment of the current number of slots is required | AP14: No | AQ14: No
A15: 24 | B15: 44365.537 | C15: 44365.54 | D15: anonymous | F15: Español (España, alfabetización internacional) | G15: Germany | H15: =CONCATENATE('ENCUESTAS JUN-2021'!$K15,'ENCUESTAS JUN-2021'!$L15,'ENCUESTAS JUN-2021'!$M15,'ENCUESTAS JUN-2021'!$N15,'ENCUESTAS JUN-2021'!$O15,'ENCUESTAS JUN-2021'!$P15,'ENCUESTAS JUN-2021'!$Q15,'ENCUESTAS JUN-2021'!$R15,'ENCUESTAS JUN-2021'!$S15,'ENCUESTAS JUN-2021'!$T15,'ENCUESTAS JUN-2021'!$U15,'ENCUESTAS JUN-2021'!$V15,'ENCUESTAS JUN-2021'!$W15,'ENCUESTAS JUN-2021'!$X15,'ENCUESTAS JUN-2021'!$Y15,'ENCUESTAS JUN-2021'!$Z15,'ENCUESTAS JUN-2021'!$AA15,'ENCUESTAS JUN-2021'!$AB15,'ENCUESTAS JUN-2021'!$AC15,'ENCUESTAS JUN-2021'!$AD15,'ENCUESTAS JUN-2021'!$AE15,'ENCUESTAS JUN-2021'!$AF15) -> Friedrich-Alexander Universität FAU (D ERLANGE 01) | I15: Friedrich-Alexander Universität FAU | J15: D ERLANGE 01 | R15: Friedrich-Alexander Universität FAU (D ERLANGE 01) | AG15: D ERLANGE01 | AH15: Bianca Köndgen | AI15: erasmus@fau.de | AJ15: Boryana Klinkova | AK15: Agreement Coordinator | AL15: erasmus@fau.de | AM15: Yes, we would like to increase the current number of slots | AN15: Not increasing, but we suggest in future to use e.g. 4x5 insetad of 2x10, so semester spots in the agreements. | AP15: No | AQ15: No
A16: 25 | B16: 44365.55 | C16: 44365.56 | D16: anonymous | F16: Español (España, alfabetización internacional) | G16: Sweden | H16: =CONCATENATE('ENCUESTAS JUN-2021'!$K16,'ENCUESTAS JUN-2021'!$L16,'ENCUESTAS JUN-2021'!$M16,'ENCUESTAS JUN-2021'!$N16,'ENCUESTAS JUN-2021'!$O16,'ENCUESTAS JUN-2021'!$P16,'ENCUESTAS JUN-2021'!$Q16,'ENCUESTAS JUN-2021'!$R16,'ENCUESTAS JUN-2021'!$S16,'ENCUESTAS JUN-2021'!$T16,'ENCUESTAS JUN-2021'!$U16,'ENCUESTAS JUN-2021'!$V16,'ENCUESTAS JUN-2021'!$W16,'ENCUESTAS JUN-2021'!$X16,'ENCUESTAS JUN-2021'!$Y16,'ENCUESTAS JUN-2021'!$Z16,'ENCUESTAS JUN-2021'!$AA16,'ENCUESTAS JUN-2021'!$AB16,'ENCUESTAS JUN-2021'!$AC16,'ENCUESTAS JUN-2021'!$AD16,'ENCUESTAS JUN-2021'!$AE16,'ENCUESTAS JUN-2021'!$AF16) -> Lund Institute of Technology (S LUND 01) | I16: Lund Institute of Technology | J16: S LUND 01 | AC16: Lund Institute of Technology (S LUND 01) | AG16: S LUND01 | AH16: Andréa Tarlé Borgström | AI16: andrea.tarle_borgstrom@lth.lu.se | AJ16: Andréa Tarlé Borgström | AK16: International Coordinator | AL16: andrea.tarle_borgstrom@lth.lu.se | AM16: No, no additional adjustment of the current number of slots is required | AP16: No | AQ16: Yes | AR16: Electrical Engineering (0714);Energy Engineering (0713);Computer Science (06);Biomedical Engineering (0914); | AS16: 1 student per subject x 10 months. 4 student places in total (to LTH and to ETSIT). If possible we would like to have flexibility in terms of student nomination in subject areas.
A17: 26 | B17: 44365.598 | C17: 44365.599 | D17: anonymous | F17: Español (España, alfabetización internacional) | G17: Belgium | H17: =CONCATENATE('ENCUESTAS JUN-2021'!$K17,'ENCUESTAS JUN-2021'!$L17,'ENCUESTAS JUN-2021'!$M17,'ENCUESTAS JUN-2021'!$N17,'ENCUESTAS JUN-2021'!$O17,'ENCUESTAS JUN-2021'!$P17,'ENCUESTAS JUN-2021'!$Q17,'ENCUESTAS JUN-2021'!$R17,'ENCUESTAS JUN-2021'!$S17,'ENCUESTAS JUN-2021'!$T17,'ENCUESTAS JUN-2021'!$U17,'ENCUESTAS JUN-2021'!$V17,'ENCUESTAS JUN-2021'!$W17,'ENCUESTAS JUN-2021'!$X17,'ENCUESTAS JUN-2021'!$Y17,'ENCUESTAS JUN-2021'!$Z17,'ENCUESTAS JUN-2021'!$AA17,'ENCUESTAS JUN-2021'!$AB17,'ENCUESTAS JUN-2021'!$AC17,'ENCUESTAS JUN-2021'!$AD17,'ENCUESTAS JUN-2021'!$AE17,'ENCUESTAS JUN-2021'!$AF17) -> Universiteit Gent (B GENT 01) | I17: Universiteit Gent | J17: B GENT 01 | L17: Universiteit Gent (B GENT 01) | AH17: Geneviève Cochez | AI17: genevieve.cochez@ugent.be | AJ17: Vanoutryve Ann | AK17: Faculty International Office | AL17: ann.vanoutryve@ugent.be | AM17: No, no additional adjustment of the current number of slots is required | AP17: No | AQ17: No
